Workbook

Sheet Control Sheet
B2: InterGlobe Aviation
B3: Control Sheet
J5: Current Case | K5: 1
J8: Actual | L8: Explicit Forecast Period
B9: In INR Crores unless stated otherwise | F9: =G9-1 -> 2021 | G9: =H9-1 -> 2022 | H9: =I9-1 -> 2023 | I9: =J9-1 -> 2024 | J9: 2025 | K9: =J9+1 -> 2026 | L9: =K9+1 -> 2027 | M9: =L9+1 -> 2028 | N9: =M9+1 -> 2029 | O9: =N9+1 -> 2030 | P9: =O9+1 -> 2031
B10: Assumptions
A11: # | B11: Revenue
B13: Revenue YoY % Growth
B14: Management Case | L14: 0.198 | M14: 0.198 | N14: 0.198 | O14: 0.198 | P14: 0.198
B15: Best Case | L15: 0.198 | M15: 0.198 | N15: 0.198 | O15: 0.198 | P15: 0.198
B16: Down Case | L16: 0.198 | M16: 0.198 | N16: 0.198 | O16: 0.198 | P16: 0.198
B17: ="Current Case - "& CHOOSE($K$5,$B$14,$B$15,$B$16) -> Current Case - Management Case | L17: =CHOOSE($K$5,L14,L15,L16) -> 0.198 | M17: =CHOOSE($K$5,M14,M15,M16) -> 0.198 | N17: =CHOOSE($K$5,N14,N15,N16) -> 0.198 | O17: =CHOOSE($K$5,O14,O15,O16) -> 0.198 | P17: =CHOOSE($K$5,P14,P15,P16) -> 0.198
B19: Passenger service YoY Growth %
B20: Management Case | L20: 0.2 | M20: 0.2 | N20: 0.2 | O20: 0.2 | P20: 0.2
B21: Best Case | L21: 0.2 | M21: 0.2 | N21: 0.2 | O21: 0.2 | P21: 0.2
B22: Down Case | L22: 0.2 | M22: 0.2 | N22: 0.2 | O22: 0.2 | P22: 0.2
B23: ="Current Case - "& CHOOSE($K$5,$B$14,$B$15,$B$16) -> Current Case - Management Case | L23: =CHOOSE($K$5,L20,L21,L22) -> 0.2 | M23: =CHOOSE($K$5,M20,M21,M22) -> 0.2 | N23: =CHOOSE($K$5,N20,N21,N22) -> 0.2 | O23: =CHOOSE($K$5,O20,O21,O22) -> 0.2 | P23: =CHOOSE($K$5,P20,P21,P22) -> 0.2
B25: Cargo Service YoY Growth %
B26: Management Case | L26: 0.15 | M26: 0.15 | N26: 0.15 | O26: 0.15 | P26: 0.15
B27: Best Case | L27: 0.15 | M27: 0.15 | N27: 0.15 | O27: 0.15 | P27: 0.15
B28: Down Case | L28: 0.15 | M28: 0.15 | N28: 0.15 | O28: 0.15 | P28: 0.15
B29: ="Current Case - "& CHOOSE($K$5,$B$14,$B$15,$B$16) -> Current Case - Management Case | L29: =CHOOSE($K$5,L26,L27,L28) -> 0.15 | M29: =CHOOSE($K$5,M26,M27,M28) -> 0.15 | N29: =CHOOSE($K$5,N26,N27,N28) -> 0.15 | O29: =CHOOSE($K$5,O26,O27,O28) -> 0.15 | P29: =CHOOSE($K$5,P26,P27,P28) -> 0.15
B31: In flight sales YoY Growth %
B32: Management Case | L32: 0.18 | M32: 0.18 | N32: 0.18 | O32: 0.18 | P32: 0.18
B33: Best Case | L33: 0.18 | M33: 0.18 | N33: 0.18 | O33: 0.18 | P33: 0.18
B34: Down Case | L34: 0.18 | M34: 0.18 | N34: 0.18 | O34: 0.18 | P34: 0.18
B35: ="Current Case - "& CHOOSE($K$5,$B$14,$B$15,$B$16) -> Current Case - Management Case | L35: =CHOOSE($K$5,L32,L33,L34) -> 0.18 | M35: =CHOOSE($K$5,M32,M33,M34) -> 0.18 | N35: =CHOOSE($K$5,N32,N33,N34) -> 0.18 | O35: =CHOOSE($K$5,O32,O33,O34) -> 0.18 | P35: =CHOOSE($K$5,P32,P33,P34) -> 0.18
B37: Others YoY Growth %
B38: Management Case | L38: 0.1 | M38: 0.1 | N38: 0.1 | O38: 0.1 | P38: 0.1
B39: Best Case | L39: 0.1 | M39: 0.1 | N39: 0.1 | O39: 0.1 | P39: 0.1
B40: Down Case | L40: 0.1 | M40: 0.1 | N40: 0.1 | O40: 0.1 | P40: 0.1
B41: ="Current Case - "& CHOOSE($K$5,$B$14,$B$15,$B$16) -> Current Case - Management Case | L41: =CHOOSE($K$5,L38,L39,L40) -> 0.1 | M41: =CHOOSE($K$5,M38,M39,M40) -> 0.1 | N41: =CHOOSE($K$5,N38,N39,N40) -> 0.1 | O41: =CHOOSE($K$5,O38,O39,O40) -> 0.1 | P41: =CHOOSE($K$5,P38,P39,P40) -> 0.1
A43: # | B43: Cost of Goods Sold
B45: Gross Margin % Sales
B46: Management Case | F46: ='Income Statement'!J$33 -> 0.35464981 | G46: ='Income Statement'!K$33 -> 0.25028349 | H46: ='Income Statement'!L$33 -> 0.2853641 | I46: ='Income Statement'!M$33 -> 0.41084954 | J46: ='Income Statement'!N$33 -> 0.40373056 | K46: ='Income Statement'!O$33 -> 0.33611654 | L46: =K46-(($K$46-$O$46)/($O$9-$K$9)) -> 0.37708741 | M46: =L46-(($K$46-$O$46)/($O$9-$K$9)) -> 0.41805827 | N46: =M46-(($K$46-$O$46)/($O$9-$K$9)) -> 0.45902914 | O46: 0.5 | P46: 0.5
B47: Best Case | F47: ='Income Statement'!J$33 -> 0.35464981 | G47: ='Income Statement'!K$33 -> 0.25028349 | H47: ='Income Statement'!L$33 -> 0.2853641 | I47: ='Income Statement'!M$33 -> 0.41084954 | J47: ='Income Statement'!N$33 -> 0.40373056 | K47: ='Income Statement'!O$33 -> 0.33611654 | L47: =K47-(($K$47-$O$47)/($O$9-$K$9)) -> 0.38958741 | M47: =L47-(($K$47-$O$47)/($O$9-$K$9)) -> 0.44305827 | N47: =M47-(($K$47-$O$47)/($O$9-$K$9)) -> 0.49652914 | O47: 0.55 | P47: 0.55
B48: Down Case | F48: ='Income Statement'!J$33 -> 0.35464981 | G48: ='Income Statement'!K$33 -> 0.25028349 | H48: ='Income Statement'!L$33 -> 0.2853641 | I48: ='Income Statement'!M$33 -> 0.41084954 | J48: ='Income Statement'!N$33 -> 0.40373056 | K48: ='Income Statement'!O$33 -> 0.33611654 | L48: =K48-(($K$48-$O$48)/($O$9-$K$9)) -> 0.33958741 | M48: =L48-(($K$48-$O$48)/($O$9-$K$9)) -> 0.34305827 | N48: =M48-(($K$48-$O$48)/($O$9-$K$9)) -> 0.34652914 | O48: 0.35 | P48: 0.35
B49: ="Current Case - "& CHOOSE($K$5,$B$14,$B$15,$B$16) -> Current Case - Management Case | F49: =CHOOSE($K$5,F46,F47,F48) -> 0.35464981 | G49: =CHOOSE($K$5,G46,G47,G48) -> 0.25028349 | H49: =CHOOSE($K$5,H46,H47,H48) -> 0.2853641 | I49: =CHOOSE($K$5,I46,I47,I48) -> 0.41084954 | J49: =CHOOSE($K$5,J46,J47,J48) -> 0.40373056 | K49: =CHOOSE($K$5,K46,K47,K48) -> 0.33611654 | L49: =CHOOSE($K$5,L46,L47,L48) -> 0.37708741 | M49: =CHOOSE($K$5,M46,M47,M48) -> 0.41805827 | ... P49: =CHOOSE($K$5,P46,P47,P48) -> 0.5
B51: COGS % Sales | F51: =1-F49 -> 0.64535019 | G51: =1-G49 -> 0.74971651 | H51: =1-H49 -> 0.7146359 | I51: =1-I49 -> 0.58915046 | J51: =1-J49 -> 0.59626944 | K51: =1-K49 -> 0.66388346 | L51: 0.66 | M51: 0.66 | N51: 0.66 | O51: 0.66 | P51: 0.66
B53: Selling, General and Administrative (SG&A) Expenses
B55: Employee benefits expense % Revenue
B56: Management Case | F56: ='Income Statement'!J$39 -> 0.22509221 | G56: ='Income Statement'!K$39 -> 0.13445115 | H56: ='Income Statement'!L$39 -> 0.088063625 | I56: ='Income Statement'!M$39 -> 0.093779343 | J56: ='Income Statement'!N$39 -> 0.092478117 | K56: ='Income Statement'!O$39 -> 0.097363642 | L56: 0.1 | M56: 0.1 | N56: 0.1 | O56: 0.1 | P56: 0.1
B57: Best Case | F57: ='Income Statement'!J$39 -> 0.22509221 | G57: ='Income Statement'!K$39 -> 0.13445115 | H57: ='Income Statement'!L$39 -> 0.088063625 | I57: ='Income Statement'!M$39 -> 0.093779343 | J57: ='Income Statement'!N$39 -> 0.092478117 | K57: ='Income Statement'!O$39 -> 0.097363642 | L57: 0.1 | M57: 0.1 | N57: 0.1 | O57: 0.1 | P57: 0.1
B58: Down Case | F58: ='Income Statement'!J$39 -> 0.22509221 | G58: ='Income Statement'!K$39 -> 0.13445115 | H58: ='Income Statement'!L$39 -> 0.088063625 | I58: ='Income Statement'!M$39 -> 0.093779343 | J58: ='Income Statement'!N$39 -> 0.092478117 | K58: ='Income Statement'!O$39 -> 0.097363642 | L58: 0.1 | M58: 0.1 | N58: 0.1 | O58: 0.1 | P58: 0.1
B59: ="Current Case - "& CHOOSE($K$5,$B$14,$B$15,$B$16) -> Current Case - Management Case | F59: =CHOOSE($K$5,F56,F57,F58) -> 0.22509221 | G59: =CHOOSE($K$5,G56,G57,G58) -> 0.13445115 | H59: =CHOOSE($K$5,H56,H57,H58) -> 0.088063625 | I59: =CHOOSE($K$5,I56,I57,I58) -> 0.093779343 | J59: =CHOOSE($K$5,J56,J57,J58) -> 0.092478117 | K59: =CHOOSE($K$5,K56,K57,K58) -> 0.097363642 | L59: =CHOOSE($K$5,L56,L57,L58) -> 0.1 | M59: =CHOOSE($K$5,M56,M57,M58) -> 0.1 | ... P59: =CHOOSE($K$5,P56,P57,P58) -> 0.1
B61: Other expense % Revenue
B62: Management Case | F62: ='Income Statement'!J$40 -> 0.13048686 | G62: ='Income Statement'!K$40 -> 0.094724998 | H62: ='Income Statement'!L$40 -> 0.078002528 | I62: ='Income Statement'!M$40 -> 0.080256239 | J62: ='Income Statement'!N$40 -> 0.087766652 | K62: ='Income Statement'!O$40 -> 0.097708502 | L62: 0.09 | M62: 0.09 | N62: 0.09 | O62: 0.09 | P62: 0.09
B63: Best Case | F63: ='Income Statement'!J$40 -> 0.13048686 | G63: ='Income Statement'!K$40 -> 0.094724998 | H63: ='Income Statement'!L$40 -> 0.078002528 | I63: ='Income Statement'!M$40 -> 0.080256239 | J63: ='Income Statement'!N$40 -> 0.087766652 | K63: ='Income Statement'!O$40 -> 0.097708502 | L63: 0.09 | M63: 0.09 | N63: 0.09 | O63: 0.09 | P63: 0.09
B64: Down Case | F64: ='Income Statement'!J$40 -> 0.13048686 | G64: ='Income Statement'!K$40 -> 0.094724998 | H64: ='Income Statement'!L$40 -> 0.078002528 | I64: ='Income Statement'!M$40 -> 0.080256239 | J64: ='Income Statement'!N$40 -> 0.087766652 | K64: ='Income Statement'!O$40 -> 0.097708502 | L64: 0.09 | M64: 0.09 | N64: 0.09 | O64: 0.09 | P64: 0.09
B65: ="Current Case - "& CHOOSE($K$5,$B$14,$B$15,$B$16) -> Current Case - Management Case | F65: =CHOOSE($K$5,F62,F63,F64) -> 0.13048686 | G65: =CHOOSE($K$5,G62,G63,G64) -> 0.094724998 | H65: =CHOOSE($K$5,H62,H63,H64) -> 0.078002528 | I65: =CHOOSE($K$5,I62,I63,I64) -> 0.080256239 | J65: =CHOOSE($K$5,J62,J63,J64) -> 0.087766652 | K65: =CHOOSE($K$5,K62,K63,K64) -> 0.097708502 | L65: =CHOOSE($K$5,L62,L63,L64) -> 0.09 | M65: =CHOOSE($K$5,M62,M63,M64) -> 0.09 | ... P65: =CHOOSE($K$5,P62,P63,P64) -> 0.09
B67: Non Current Asset
B69: Tangible Non-Current Asset
B71: Plant, machinery and equipment Growth %
B72: Management Case | L72: 0.25 | M72: 0.25 | N72: 0.25 | O72: 0.25 | P72: 0.25
B73: Best Case | L73: 0.25 | M73: 0.25 | N73: 0.25 | O73: 0.25 | P73: 0.25
B74: Down Case | L74: 0.25 | M74: 0.25 | N74: 0.25 | O74: 0.25 | P74: 0.25
B75: ="Current Case - "& CHOOSE($K$5,$B$14,$B$15,$B$16) -> Current Case - Management Case | L75: =CHOOSE($K$5,L72,L73,L74) -> 0.25 | M75: =CHOOSE($K$5,M72,M73,M74) -> 0.25 | N75: =CHOOSE($K$5,N72,N73,N74) -> 0.25 | O75: =CHOOSE($K$5,O72,O73,O74) -> 0.25 | P75: =CHOOSE($K$5,P72,P73,P74) -> 0.25
B77: Right of use assets Growth %
B78: Management Case | L78: 0.25 | M78: 0.25 | N78: 0.25 | O78: 0.25 | P78: 0.25
B79: Best Case | L79: 0.25 | M79: 0.25 | N79: 0.25 | O79: 0.25 | P79: 0.25
B80: Down Case | L80: 0.25 | M80: 0.25 | N80: 0.25 | O80: 0.25 | P80: 0.25
B81: ="Current Case - "& CHOOSE($K$5,$B$14,$B$15,$B$16) -> Current Case - Management Case | L81: =CHOOSE($K$5,L78,L79,L80) -> 0.25 | M81: =CHOOSE($K$5,M78,M79,M80) -> 0.25 | N81: =CHOOSE($K$5,N78,N79,N80) -> 0.25 | O81: =CHOOSE($K$5,O78,O79,O80) -> 0.25 | P81: =CHOOSE($K$5,P78,P79,P80) -> 0.25
B83: Capital Work in progress Growth %
B84: Management Case | L84: 0 | M84: 0 | N84: 0 | O84: 0 | P84: 0
B85: Best Case | L85: 0 | M85: 0 | N85: 0 | O85: 0 | P85: 0
B86: Down Case | L86: 0 | M86: 0 | N86: 0 | O86: 0 | P86: 0
B87: ="Current Case - "& CHOOSE($K$5,$B$14,$B$15,$B$16) -> Current Case - Management Case | L87: =CHOOSE($K$5,L84,L85,L86) -> 0 | M87: =CHOOSE($K$5,M84,M85,M86) -> 0 | N87: =CHOOSE($K$5,N84,N85,N86) -> 0 | O87: =CHOOSE($K$5,O84,O85,O86) -> 0 | P87: =CHOOSE($K$5,P84,P85,P86) -> 0
B89: Financial Assets Growth %
B90: Management Case | L90: 0.1 | M90: 0.1 | N90: 0.1 | O90: 0.1 | P90: 0.1
B91: Best Case | L91: 0.1 | M91: 0.1 | N91: 0.1 | O91: 0.1 | P91: 0.1
B92: Down Case | L92: 0.1 | M92: 0.1 | N92: 0.1 | O92: 0.1 | P92: 0.1
B93: ="Current Case - "& CHOOSE($K$5,$B$14,$B$15,$B$16) -> Current Case - Management Case | L93: =CHOOSE($K$5,L90,L91,L92) -> 0.1 | M93: =CHOOSE($K$5,M90,M91,M92) -> 0.1 | N93: =CHOOSE($K$5,N90,N91,N92) -> 0.1 | O93: =CHOOSE($K$5,O90,O91,O92) -> 0.1 | P93: =CHOOSE($K$5,P90,P91,P92) -> 0.1
B95: Deferred Tax Growth %
B96: Management Case | L96: 0 | M96: 0 | N96: 0 | O96: 0 | P96: 0
B97: Best Case | L97: 0 | M97: 0 | N97: 0 | O97: 0 | P97: 0
B98: Down Case | L98: 0 | M98: 0 | N98: 0 | O98: 0 | P98: 0
B99: ="Current Case - "& CHOOSE($K$5,$B$14,$B$15,$B$16) -> Current Case - Management Case | L99: =CHOOSE($K$5,L96,L97,L98) -> 0 | M99: =CHOOSE($K$5,M96,M97,M98) -> 0 | N99: =CHOOSE($K$5,N96,N97,N98) -> 0 | O99: =CHOOSE($K$5,O96,O97,O98) -> 0 | P99: =CHOOSE($K$5,P96,P97,P98) -> 0
B101: Income Tax Growth %
B102: Management Case | L102: 0.25 | M102: 0.25 | N102: 0.25 | O102: 0.25 | P102: 0.25
B103: Best Case | L103: 0.25 | M103: 0.25 | N103: 0.25 | O103: 0.25 | P103: 0.25
B104: Down Case | L104: 0.25 | M104: 0.25 | N104: 0.25 | O104: 0.25 | P104: 0.25
B105: ="Current Case - "& CHOOSE($K$5,$B$14,$B$15,$B$16) -> Current Case - Management Case | L105: =CHOOSE($K$5,L102,L103,L104) -> 0.25 | M105: =CHOOSE($K$5,M102,M103,M104) -> 0.25 | N105: =CHOOSE($K$5,N102,N103,N104) -> 0.25 | O105: =CHOOSE($K$5,O102,O103,O104) -> 0.25 | P105: =CHOOSE($K$5,P102,P103,P104) -> 0.25
B107: Other Non-Current Assets % Revenue
B108: Management Case | L108: 0.03 | M108: 0.03 | N108: 0.03 | O108: 0.03 | P108: 0.03
B109: Best Case | L109: 0.03 | M109: 0.03 | N109: 0.03 | O109: 0.03 | P109: 0.03
B110: Down Case | L110: 0.03 | M110: 0.03 | N110: 0.03 | O110: 0.03 | P110: 0.03
B111: ="Current Case - "& CHOOSE($K$5,$B$14,$B$15,$B$16) -> Current Case - Management Case | L111: =CHOOSE($K$5,L108,L109,L110) -> 0.03 | M111: =CHOOSE($K$5,M108,M109,M110) -> 0.03 | N111: =CHOOSE($K$5,N108,N109,N110) -> 0.03 | O111: =CHOOSE($K$5,O108,O109,O110) -> 0.03 | P111: =CHOOSE($K$5,P108,P109,P110) -> 0.03
B113: Intangible Non-Current Asset
B115: Intangible Non Current Asset Growth %
B116: Management Case | L116: 0 | M116: 0 | N116: 0 | O116: 0 | P116: 0
B117: Best Case | L117: 0 | M117: 0 | N117: 0 | O117: 0 | P117: 0
B118: Down Case | L118: 0 | M118: 0 | N118: 0 | O118: 0 | P118: 0
B119: ="Current Case - "& CHOOSE($K$5,$B$14,$B$15,$B$16) -> Current Case - Management Case | L119: =CHOOSE($K$5,L116,L117,L118) -> 0 | M119: =CHOOSE($K$5,M116,M117,M118) -> 0 | N119: =CHOOSE($K$5,N116,N117,N118) -> 0 | O119: =CHOOSE($K$5,O116,O117,O118) -> 0 | P119: =CHOOSE($K$5,P116,P117,P118) -> 0
B121: Intangible Non Current Asset (Under Development) Growth %
B122: Management Case | L122: 0 | M122: 0 | N122: 0 | O122: 0 | P122: 0
B123: Best Case | L123: 0 | M123: 0 | N123: 0 | O123: 0 | P123: 0
B124: Down Case | L124: 0 | M124: 0 | N124: 0 | O124: 0 | P124: 0
B125: ="Current Case - "& CHOOSE($K$5,$B$14,$B$15,$B$16) -> Current Case - Management Case | L125: =CHOOSE($K$5,L122,L123,L124) -> 0 | M125: =CHOOSE($K$5,M122,M123,M124) -> 0 | N125: =CHOOSE($K$5,N122,N123,N124) -> 0 | O125: =CHOOSE($K$5,O122,O123,O124) -> 0 | P125: =CHOOSE($K$5,P122,P123,P124) -> 0
B127: Tax Rate
B129: Marginal Tax Rate
...

Sheet Schedule Sheet
D1: ḥ
B2: ='Control Sheet'!B2 -> InterGlobe Aviation
B3: Schedule Sheet
I5: Current Case | J5: 0
D8: Actual | J8: Explicit Forecast Period
B9: In INR Crores unless stated otherwise | D9: 2021 | E9: =D9+1 -> 2022 | F9: =E9+1 -> 2023 | G9: =F9+1 -> 2024 | H9: 2025 | I9: =H9+1 -> 2026 | J9: =I9+1 -> 2027 | K9: =J9+1 -> 2028 | L9: =K9+1 -> 2029 | M9: =L9+1 -> 2030 | N9: =M9+1 -> 2031
B11: Sales Schedule
B13: Revenue | D13: ='Income Statement'!J12 -> 146406.31 | E13: ='Income Statement'!K12 -> 259309.27 | F13: ='Income Statement'!L12 -> 544464.53 | G13: ='Income Statement'!M12 -> 689043 | H13: ='Income Statement'!N12 -> 808029 | I13: ='Income Statement'!O12 -> 849619 | J13: =SUM(J14,J16,J18,J20) -> 1015783.4 | K13: =SUM(K14,K16,K18,K20) -> 1214721.6 | L13: =SUM(L14,L16,L18,L20) -> 1452929.1 | M13: =SUM(M14,M16,M18,M20) -> 1738192.8 | N13: =SUM(N14,N16,N18,N20) -> 2079847.9
B14: Passenger service | D14: 129619.69 | E14: 239102.72 | F14: 512577.6 | G14: 646089.29 | H14: 742111 | I14: 789026 | J14: =I14*J15+I14 -> 946831.2 | K14: =J14*K15+J14 -> 1136197.4 | L14: =K14*L15+K14 -> 1363436.9 | M14: =L14*M15+L14 -> 1636124.3 | N14: =M14*N15+M14 -> 1963349.2
J15: ='Control Sheet'!L23 -> 0.2 | K15: ='Control Sheet'!M23 -> 0.2 | L15: ='Control Sheet'!N23 -> 0.2 | M15: ='Control Sheet'!O23 -> 0.2 | N15: ='Control Sheet'!P23 -> 0.2
B16: Cargo Service | D16: 11451.02 | E16: 14974.65 | F16: 15837.01 | G16: 17943.97 | H16: 22651 | I16: 24837 | J16: =I16*J17+I16 -> 28562.55 | K16: =J16*K17+J16 -> 32846.932 | L16: =K16*L17+K16 -> 37773.972 | M16: =L16*M17+L16 -> 43440.068 | N16: =M16*N17+M16 -> 49956.078
J17: ='Control Sheet'!L29 -> 0.15 | K17: ='Control Sheet'!M29 -> 0.15 | L17: ='Control Sheet'!N29 -> 0.15 | M17: ='Control Sheet'!O29 -> 0.15 | N17: ='Control Sheet'!P29 -> 0.15
B18: In flight sales | D18: 1028.25 | E18: 2462.31 | F18: 7662.06 | G18: 9835.39 | H18: 11424 | I18: 13226 | J18: =I18*J19+I18 -> 15606.68 | K18: =J18*K19+J18 -> 18415.882 | L18: =K18*L19+K18 -> 21730.741 | M18: =L18*M19+L18 -> 25642.275 | N18: =M18*N19+M18 -> 30257.884
J19: ='Control Sheet'!L35 -> 0.18 | K19: ='Control Sheet'!M35 -> 0.18 | L19: ='Control Sheet'!N35 -> 0.18 | M19: ='Control Sheet'!O35 -> 0.18 | N19: ='Control Sheet'!P35 -> 0.18
B20: Others | D20: 4307.35 | E20: 2769.59 | F20: 8387.86 | G20: 15174.35 | H20: 31843 | I20: 22530 | J20: =I20*J21+I20 -> 24783 | K20: =J20*K21+J20 -> 27261.3 | L20: =K20*L21+K20 -> 29987.43 | M20: =L20*M21+L20 -> 32986.173 | N20: =M20*N21+M20 -> 36284.79
J21: ='Control Sheet'!L41 -> 0.1 | K21: ='Control Sheet'!M41 -> 0.1 | L21: ='Control Sheet'!N41 -> 0.1 | M21: ='Control Sheet'!O41 -> 0.1 | N21: ='Control Sheet'!P41 -> 0.1
B23: Cost of Goods Sold Schedule
B25: COGS % Sales | J25: ='Control Sheet'!L51 -> 0.66 | K25: ='Control Sheet'!M51 -> 0.66 | L25: ='Control Sheet'!N51 -> 0.66 | M25: ='Control Sheet'!O51 -> 0.66 | N25: ='Control Sheet'!P51 -> 0.66
B26: COGS | D26: ='Income Statement'!J25 -> 94483.34 | E26: ='Income Statement'!K25 -> 194408.44 | F26: ='Income Statement'!L25 -> 389093.9 | G26: ='Income Statement'!M25 -> 405950 | H26: ='Income Statement'!N25 -> 481803 | I26: ='Income Statement'!O25 -> 564048 | J26: =J13*J25 -> 670417.06 | K26: =K13*K25 -> 801716.23 | L26: =L13*L25 -> 958933.19 | M26: =M13*M25 -> 1147207.3 | N26: =N13*N25 -> 1372699.6
D27: =D26/D13 -> 0.64535019 | E27: =E26/E13 -> 0.74971651 | F27: =F26/F13 -> 0.7146359 | G27: =G26/G13 -> 0.58915046 | H27: =H26/H13 -> 0.59626944 | I27: =I26/I13 -> 0.66388346
B28: SG&A (Excluding Depreciation and Interest Expenses) Schedule
D29: =AVERAGE(D27:I27) -> 0.65983433
B30: Employee Benefit Expenses | D30: ='Income Statement'!J36 -> 32954.92 | E30: ='Income Statement'!K36 -> 34864.43 | F30: ='Income Statement'!L36 -> 47947.52 | G30: ='Income Statement'!M36 -> 64618 | H30: ='Income Statement'!N36 -> 74725 | I30: ='Income Statement'!O36 -> 82722 | J30: =J13*J31 -> 101578.34 | K30: =K13*K31 -> 121472.16 | L30: =L13*L31 -> 188880.78 | M30: =M13*M31 -> 260728.92 | N30: =N13*N31 -> 311977.19
B31: Employee Benefit Expenses % Revenue | D31: =D30/D13 -> 0.22509221 | E31: =E30/E13 -> 0.13445115 | F31: =F30/F13 -> 0.088063625 | G31: =G30/G13 -> 0.093779343 | H31: =H30/H13 -> 0.092478117 | I31: ='Control Sheet'!K59 -> 0.097363642 | J31: 0.1 | K31: 0.1 | L31: 0.13 | M31: 0.15 | N31: 0.15
B33: Other Expenses | D33: ='Income Statement'!J37 -> 19104.1 | E33: ='Income Statement'!K37 -> 24563.07 | F33: ='Income Statement'!L37 -> 42469.61 | G33: ='Income Statement'!M37 -> 55300 | H33: ='Income Statement'!N37 -> 70918 | I33: ='Income Statement'!O37 -> 83015 | J33: =J13*J34 -> 91420.509 | K33: =K13*K34 -> 109324.94 | L33: =L13*L34 -> 130763.62 | M33: =M13*M34 -> 156437.35 | N33: =N13*N34 -> 187186.31
B34: Other Expenses % Revenue | D34: =D33/D13 -> 0.13048686 | E34: =E33/E13 -> 0.094724998 | F34: =F33/F13 -> 0.078002528 | G34: =G33/G13 -> 0.080256239 | H34: =H33/H13 -> 0.087766652 | I34: =I33/I13 -> 0.097708502 | J34: ='Control Sheet'!L65 -> 0.09 | K34: ='Control Sheet'!M65 -> 0.09 | L34: ='Control Sheet'!N65 -> 0.09 | M34: ='Control Sheet'!O65 -> 0.09 | N34: ='Control Sheet'!P65 -> 0.09
B36: Total SG&A | D36: =D33+D30 -> 52059.02 | E36: =E33+E30 -> 59427.5 | F36: =F33+F30 -> 90417.13 | G36: =G33+G30 -> 119918 | H36: =H33+H30 -> 145643 | I36: =I33+I30 -> 165737 | J36: =J33+J30 -> 192998.85 | K36: =K33+K30 -> 230797.1 | ... N36: =N33+N30 -> 499163.5
B37: Total SG&A % Revenue | D37: =D36/D13 -> 0.35557907 | E37: =E36/E13 -> 0.22917615 | F37: =F36/F13 -> 0.16606615 | G37: =G36/G13 -> 0.17403558 | H37: =H36/H13 -> 0.18024477 | I37: =I36/I13 -> 0.19507214 | J37: =J36/J13 -> 0.19 | K37: =K36/K13 -> 0.19 | ... N37: =N36/N13 -> 0.24
B39: Non-Current Asset Schedule
B41: ='Control Sheet'!B71 -> Plant, machinery and equipment Growth %
B43: Opening PM&E | J43: ='Balance Sheet'!O9 -> 110871 | K43: =J46 -> 117767.33 | L43: =K46 -> 124424.94 | M43: =L46 -> 130673.22 | N43: =M46 -> 136305.67
B44: Add: Capex during the year | J44: =I46*J47 -> 27717.75 | K44: =J46*K47 -> 29441.831 | L44: =K46*L47 -> 31106.236 | M44: =L46*M47 -> 32668.304 | N44: =M46*N47 -> 34076.418
B45: Less: Depreciation | I45: =('Income Statement'!O48)/SUM('Balance Sheet'!O9,'Balance Sheet'!O10,'Balance Sheet'!O12)*'Balance Sheet'!O9 -> 18973.575 | J45: =I45+J44/$C$90 -> 20821.425 | K45: =J45+K44/$C$90 -> 22784.213 | L45: =K45+L44/$C$90 -> 24857.962 | M45: =L45+M44/$C$90 -> 27035.849 | N45: =M45+N44/$C$90 -> 29307.61
B46: Closing PM&E | I46: ='Balance Sheet'!O9 -> 110871 | J46: =J43+J44-J45 -> 117767.33 | K46: =K43+K44-K45 -> 124424.94 | L46: =L43+L44-L45 -> 130673.22 | M46: =M43+M44-M45 -> 136305.67 | N46: =N43+N44-N45 -> 141074.48
J47: ='Control Sheet'!L75 -> 0.25 | K47: ='Control Sheet'!M75 -> 0.25 | L47: ='Control Sheet'!N75 -> 0.25 | M47: ='Control Sheet'!O75 -> 0.25 | N47: ='Control Sheet'!P75 -> 0.25
B49: Right of use assets | J49: ='Balance Sheet'!O10 -> 520540 | K49: =J52 -> 552918.29 | L49: =K52 -> 584175.85 | M49: =L52 -> 613511.53 | N49: =M52 -> 639955.94
B50: Addition during the year | J50: =I52*J53 -> 130135 | K50: =J52*K53 -> 138229.57 | L50: =K52*L53 -> 146043.96 | M50: =L52*M53 -> 153377.88 | N50: =M52*N53 -> 159988.98
B51: Less: Depreciation | I51: ='Income Statement'!O48/SUM('Balance Sheet'!O9,'Balance Sheet'!O10,'Balance Sheet'!O12)*'Balance Sheet'!O10 -> 89081.044 | J51: =I51+J50/$C$90 -> 97756.711 | K51: =J51+K50/$C$90 -> 106972.02 | L51: =K51+L50/$C$90 -> 116708.28 | M51: =L51+M50/$C$90 -> 126933.47 | N51: =M51+N50/$C$90 -> 137599.4
B52: Closing Right of use assets | I52: ='Balance Sheet'!O10 -> 520540 | J52: =J49+J50-J51 -> 552918.29 | K52: =K49+K50-K51 -> 584175.85 | L52: =L49+L50-L51 -> 613511.53 | M52: =M49+M50-M51 -> 639955.94 | N52: =N49+N50-N51 -> 662345.52
B53: YoY Growth % | J53: ='Control Sheet'!L81 -> 0.25 | K53: ='Control Sheet'!M81 -> 0.25 | L53: ='Control Sheet'!N81 -> 0.25 | M53: ='Control Sheet'!O81 -> 0.25 | N53: ='Control Sheet'!P81 -> 0.25
B55: ='Control Sheet'!B83 -> Capital Work in progress Growth %
B56: Capital Work In Progress | D56: ='Balance Sheet'!J$11 -> 663.51 | E56: ='Balance Sheet'!K$11 -> 1193.18 | F56: 0 | G56: ='Balance Sheet'!M$11 -> 1 | H56: ='Balance Sheet'!N$11 -> 7 | I56: ='Balance Sheet'!O$11 -> 387 | J56: 0 | K56: =J56*(1+K57) -> 0 | L56: =K56*(1+L57) -> 0 | M56: =L56*(1+M57) -> 0 | N56: =M56*(1+N57) -> 0
B57: YoY Growth % | E57: =E56/D56-1 -> 0.79828488 | F57: =F56/E56-1 -> -1 | G57: 0 | H57: =H56/G56-1 -> 6 | I57: =I56/H56-1 -> 54.285714 | J57: ='Control Sheet'!L$87 -> 0 | K57: ='Control Sheet'!M$87 -> 0 | L57: ='Control Sheet'!N$87 -> 0 | M57: ='Control Sheet'!O$87 -> 0 | N57: ='Control Sheet'!P$87 -> 0
B59: ='Control Sheet'!B89 -> Financial Assets Growth %
B60: Financial Assets | D60: =SUM('Balance Sheet'!J15:J17) -> 15823.74 | E60: =SUM('Balance Sheet'!K15:K17) -> 20911.34 | F60: =SUM('Balance Sheet'!L15:L17) -> 24500.34 | G60: =SUM('Balance Sheet'!M15:M17) -> 62711 | H60: =SUM('Balance Sheet'!N15:N17) -> 88116 | I60: =SUM('Balance Sheet'!O15:O17) -> 90417 | J60: =I60*(1+J61) -> 99458.7 | K60: =J60*(1+K61) -> 109404.57 | L60: =K60*(1+L61) -> 119250.98 | M60: =L60*(1+M61) -> 128791.06 | N60: =M60*(1+N61) -> 139094.34
B61: YoY Growth % | E61: =E60/D60-1 -> 0.32151691 | F61: =F60/E60-1 -> 0.17162936 | G61: =G60/F60-1 -> 1.5595971 | H61: =H60/G60-1 -> 0.40511234 | I61: =I60/H60-1 -> 0.026113305 | J61: ='Control Sheet'!L$93 -> 0.1 | K61: ='Control Sheet'!M$93 -> 0.1 | L61: 0.09 | M61: 0.08 | N61: 0.08
B63: ='Control Sheet'!B95 -> Deferred Tax Growth %
B64: Deferred Tax | D64: ='Balance Sheet'!J19 -> 3026.93 | E64: ='Balance Sheet'!K19 -> 2949.44 | F64: ='Balance Sheet'!L19 -> 2949.44 | G64: ='Balance Sheet'!M19 -> 4192 | H64: ='Balance Sheet'!N19 -> 4192 | I64: ='Balance Sheet'!O19 -> 0 | J64: =I64*(1+J65) -> 0 | K64: =J64*(1+K65) -> 0 | L64: =K64*(1+L65) -> 0 | M64: =L64*(1+M65) -> 0 | N64: =M64*(1+N65) -> 0
B65: YoY Growth % | E65: =E64/D64-1 -> -0.025600196 | F65: =F64/E64-1 -> 0 | G65: =G64/F64-1 -> 0.42128675 | H65: =H64/G64-1 -> 0 | I65: =I64/H64-1 -> -1 | J65: ='Control Sheet'!L$99 -> 0 | K65: ='Control Sheet'!M$99 -> 0 | L65: ='Control Sheet'!N$99 -> 0 | M65: ='Control Sheet'!O$99 -> 0 | N65: ='Control Sheet'!P$99 -> 0
B67: ='Control Sheet'!B101 -> Income Tax Growth %
B68: Income Tax | D68: ='Balance Sheet'!J20 -> 5139.53 | E68: ='Balance Sheet'!K20 -> 7119.22 | F68: ='Balance Sheet'!L20 -> 10997.87 | G68: ='Balance Sheet'!M20 -> 16101 | H68: ='Balance Sheet'!N20 -> 17080 | I68: ='Balance Sheet'!O20 -> 19775 | J68: =I68*(1+J69) -> 24718.75 | K68: =J68*(1+K69) -> 30898.438 | L68: =K68*(1+L69) -> 38623.047 | M68: =L68*(1+M69) -> 48278.809 | N68: =M68*(1+N69) -> 60348.511
B69: YoY Growth % | E69: =E68/D68-1 -> 0.38518892 | F69: =F68/E68-1 -> 0.5448139 | G69: =G68/F68-1 -> 0.46401076 | H69: =H68/G68-1 -> 0.060803677 | I69: =I68/H68-1 -> 0.15778689 | J69: ='Control Sheet'!L$105 -> 0.25 | K69: ='Control Sheet'!M$105 -> 0.25 | L69: ='Control Sheet'!N$105 -> 0.25 | M69: ='Control Sheet'!O$105 -> 0.25 | N69: ='Control Sheet'!P$105 -> 0.25
B71: ='Control Sheet'!B107 -> Other Non-Current Assets % Revenue
B72: Other Non-Current Assets | D72: ='Balance Sheet'!J21 -> 9498.13 | E72: ='Balance Sheet'!K$21 -> 12266.99 | F72: ='Balance Sheet'!L$21 -> 14971.32 | G72: ='Balance Sheet'!M$21 -> 19161 | H72: ='Balance Sheet'!N$21 -> 24169 | I72: ='Balance Sheet'!O$21 -> 38373 | J72: =I72*(1+J73) -> 42210.3 | K72: =J72*(1+K73) -> 46431.33 | L72: =K72*(1+L73) -> 51074.463 | M72: =L72*(1+M73) -> 56181.909 | N72: =M72*(1+N73) -> 61800.1
B73: Other Non-Current Assets % Revenue | D73: =D72/D13 -> 0.064875141 | E73: =E72/E13 -> 0.047306408 | F73: =F72/F13 -> 0.027497328 | G73: =G72/G13 -> 0.027808134 | H73: =H72/H13 -> 0.029911055 | I73: =I72/I13 -> 0.04516495 | J73: 0.1 | K73: 0.1 | L73: 0.1 | M73: 0.1 | N73: 0.1
B75: ='Control Sheet'!B115 -> Intangible Non Current Asset Growth %
B76: Intangible Non Current Asset - Amount Spend | J76: ='Balance Sheet'!O12 -> 160 | K76: =J79 -> 159.99893 | L76: =K79 -> 159.99786 | M76: =L79 -> 159.99679 | N76: =M79 -> 159.99572
B77: Addition during the year | J77: =I79*(J82) -> 0 | K77: =J76*(K82) -> 0 | L77: =K76*(L82) -> 0 | M77: =L76*(M82) -> 0 | N77: =M76*(N82) -> 0
B78: Less: Depreciation | I78: ='Income Statement'!O48/SUM('Balance Sheet'!O9,'Balance Sheet'!O10,'Balance Sheet'!O12)/'Balance Sheet'!O12 -> 0.0010695749 | J78: =I78+J77/$C$90 -> 0.0010695749 | K78: =J78+K77/$C$90 -> 0.0010695749 | L78: =K78+L77/$C$90 -> 0.0010695749 | M78: =L78+M77/$C$90 -> 0.0010695749 | N78: =M78+N77/$C$90 -> 0.0010695749
B79: Closing Intangible Non-Current Asset | D79: ='Balance Sheet'!J12 -> 334.96 | E79: ='Balance Sheet'!K12 -> 215.62 | F79: ='Balance Sheet'!L12 -> 107.27 | G79: ='Balance Sheet'!M12 -> 483 | H79: ='Balance Sheet'!N12 -> 299 | I79: ='Balance Sheet'!O12 -> 160 | J79: =J76+J77-J78 -> 159.99893 | K79: =K76+K77-K78 -> 159.99786 | L79: =L76+L77-L78 -> 159.99679 | M79: =M76+M77-M78 -> 159.99572 | N79: =N76+N77-N78 -> 159.99465
K80: =K79/J79-1 -> -6.6848879e-06 | L80: =L79/K79-1 -> -6.6849326e-06 | M80: =M79/L79-1 -> -6.6849773e-06 | N80: =N79/M79-1 -> -6.685022e-06
B82: YoY Growth % | E82: =E79/D79-1 -> -0.35628135 | F82: =F79/E79-1 -> -0.50250441 | G82: =G79/F79-1 -> 3.5026568 | H82: =H79/G79-1 -> -0.38095238 | I82: =J76/H79-1 -> -0.46488294 | J82: ='Control Sheet'!L$119 -> 0 | K82: ='Control Sheet'!M$119 -> 0 | L82: ='Control Sheet'!N$119 -> 0 | M82: ='Control Sheet'!O$119 -> 0 | N82: ='Control Sheet'!P$119 -> 0
B84: ='Control Sheet'!B121 -> Intangible Non Current Asset (Under Development) Growth %
B85: Intangible Non Current Asset - Under Development | D85: ='Balance Sheet'!J13 -> 54.19 | E85: ='Balance Sheet'!K13 -> 60.39 | F85: ='Balance Sheet'!L13 -> 208.17 | G85: ='Balance Sheet'!M13 -> 13 | H85: ='Balance Sheet'!N13 -> 23 | I85: ='Balance Sheet'!O13 -> 206 | J85: =I85*(1+J86) -> 206 | K85: =J85*(1+K86) -> 206 | L85: =K85*(1+L86) -> 206 | M85: =L85*(1+M86) -> 206 | N85: =M85*(1+N86) -> 206
B86: YoY Growth % | E86: =E85/D85-1 -> 0.11441225 | F86: =F85/E85-1 -> 2.4470939 | G86: =G85/F85-1 -> -0.93755104 | H86: =H85/G85-1 -> 0.76923077 | I86: =I85/H85-1 -> 7.9565217 | J86: ='Control Sheet'!L$125 -> 0 | K86: ='Control Sheet'!M$125 -> 0 | L86: ='Control Sheet'!N$125 -> 0 | M86: ='Control Sheet'!O$125 -> 0 | N86: ='Control Sheet'!P$125 -> 0
B88: Depreciation Schedule
C90: 15
B91: Total Depreciation | J91: =J51+J45+J78 -> 118578.14 | K91: =K51+K45+K78 -> 129756.23 | L91: =L51+L45+L78 -> 141566.24 | M91: =M51+M45+M78 -> 153969.32 | N91: =N51+N45+N78 -> 166907.02
B92: Total Net Deprecialble Fixed Asset | J92: =J46+J52+J79 -> 670845.61 | K92: =K46+K52+K79 -> 708760.79 | L92: =L46+L52+L79 -> 744344.74 | M92: =M46+M52+M79 -> 776421.6 | N92: =N46+N52+N79 -> 803579.99
B94: Depreciation% Revenue | J94: =J91/J13 -> 0.11673565 | K94: =K91/K13 -> 0.10681973 | L94: =L91/L13 -> 0.097435068 | M94: =M91/M13 -> 0.088580116 | N94: =N91/N13 -> 0.080249625
B95: Depreciation% Net fixed asset | J95: =J91/J92 -> 0.1767592 | K95: =K91/K92 -> 0.18307479 | L95: =L91/L92 -> 0.19018908 | M95: =M91/M92 -> 0.19830633 | N95: =N91/N92 -> 0.2077043
B97: Depreciation Waterfall Schedule (PE&M)
B99: 2026 | I99: =I45+I51+I78 -> 108054.62 | J99: =I99 -> 108054.62 | K99: =J99 -> 108054.62 | L99: =K99 -> 108054.62 | M99: =L99 -> 108054.62 | N99: =M99 -> 108054.62
B100: =B99+1 -> 2027 | J100: =J91-J99 -> 10523.517 | K100: =J100 -> 10523.517 | L100: =K100 -> 10523.517 | M100: =L100 -> 10523.517 | N100: =M100 -> 10523.517
B101: =B100+1 -> 2028 | K101: =K91-K99-K100 -> 11178.094 | L101: =K101 -> 11178.094 | M101: =L101 -> 11178.094 | N101: =M101 -> 11178.094
B102: =B101+1 -> 2029 | L102: =L91-L99-L100-L101 -> 11810.013 | M102: =L102 -> 11810.013 | N102: =M102 -> 11810.013
B103: =B102+1 -> 2030 | M103: =M91-M99-M100-M101-M102 -> 12403.079 | N103: =M103 -> 12403.079
B104: =B103+1 -> 2031 | N104: =N91-N99-N100-N102-N103-N101 -> 12937.693
B105: Total Depreciation | I105: =SUM(I99:I103) -> 108054.62 | J105: =SUM(J99:J103) -> 118578.14 | K105: =SUM(K99:K103) -> 129756.23 | L105: =SUM(L99:L103) -> 141566.24 | M105: =SUM(M99:M103) -> 153969.32 | N105: =SUM(N99:N104) -> 166907.02
B108: Tax Expenses Schedule
B110: Revenue | D110: =D13 -> 146406.31 | E110: =E13 -> 259309.27 | F110: =F13 -> 544464.53 | G110: =G13 -> 689043 | H110: =H13 -> 808029 | I110: =I13 -> 849619 | J110: =J13 -> 1015783.4 | K110: =K13 -> 1214721.6 | ... N110: =N13 -> 2079847.9
B111: Less: COGS | D111: =D26 -> 94483.34 | E111: =E26 -> 194408.44 | F111: =F26 -> 389093.9 | G111: =G26 -> 405950 | H111: =H26 -> 481803 | I111: =I26 -> 564048 | J111: =J26 -> 670417.06 | K111: =K26 -> 801716.23 | ... N111: =N26 -> 1372699.6
B112: Less: SG&A Expenses | D112: =D36 -> 52059.02 | E112: =E36 -> 59427.5 | F112: =F36 -> 90417.13 | G112: =G36 -> 119918 | H112: =H36 -> 145643 | I112: =I36 -> 165737 | J112: =J36 -> 192998.85 | K112: =K36 -> 230797.1 | ... N112: =N36 -> 499163.5
B113: Less: Depreciation and Amortization | D113: ='Income Statement'!J48 -> 46994.46 | E113: ='Income Statement'!K48 -> 50686 | F113: ='Income Statement'!L48 -> 51029.69 | G113: ='Income Statement'!M48 -> 64257 | H113: ='Income Statement'!N48 -> 86802 | I113: ='Income Statement'!O48 -> 108082 | J113: =J91 -> 118578.14 | K113: =K91 -> 129756.23 | L113: =L91 -> 141566.24 | M113: =M91 -> 153969.32 | N113: =N91 -> 166907.02
B114: Less: Interest Expenses | D114: ='Income Statement'!J53*-1-'Income Statement'!J51 -> 11050.19 | E114: ='Income Statement'!K53*-1-'Income Statement'!K51 -> 16324.17 | F114: ='Income Statement'!L53*-1-'Income Statement'!L51 -> 16967.66 | G114: ='Income Statement'!M53*-1-'Income Statement'!M51 -> 18424.54 | H114: ='Income Statement'!N53*-1-'Income Statement'!N51 -> 17847 | I114: ='Income Statement'!O53*-1-'Income Statement'!O51-'Income Statement'!O52 -> 31357 | J114: =J234-J240 -> 21202.773 | K114: =K234-K240 -> 7263.8507 | L114: =L234-L240 -> -10175.786 | M114: =M234-M240 -> -23956.656 | N114: =N234-N240 -> -21178.021
B115: Earning before Tax | D115: =D110-D111-D112-D113-D114 -> -58180.7 | E115: =E110-E111-E112-E113-E114 -> -61536.84 | F115: =F110-F111-F112-F113-F114 -> -3043.85 | G115: =G110-G111-G112-G113-G114 -> 80493.46 | H115: =H110-H111-H112-H113-H114 -> 75934 | I115: =I110-I111-I112-I113-I114 -> -19605 | J115: =J110-J111-J112-J113-J114 -> 12586.605 | K115: =K110-K111-K112-K113-K114 -> 45188.152 | ... N115: =N110-N111-N112-N113-N114 -> 62255.799
B116: Less: Tax Expenses | D116: ='Income Statement'!J59 -> -116.43 | E116: ='Income Statement'!K59 -> 81.61 | F116: ='Income Statement'!L59 -> 14.04 | G116: ='Income Statement'!M59 -> -1232 | H116: ='Income Statement'!N59 -> 3350 | I116: ='Income Statement'!O59 -> 4331 | J116: =J115*J119*-1 -> -3146.6512 | K116: =K115*K119*-1 -> -11297.038 | L116: =L115*L119*-1 -> -10740.258 | M116: =M115*M119*-1 -> -10951.654 | N116: =N115*N119*-1 -> -15563.95
B117: Net Income | D117: =D115-D116 -> -58064.27 | E117: =E115-E116 -> -61618.45 | F117: =F115-F116 -> -3057.89 | G117: =G115-G116 -> 81725.46 | H117: =H115-H116 -> 72584 | I117: =I115-I116 -> -23936 | J117: =J115+J116 -> 9439.9536 | K117: =K115+K116 -> 33891.114 | L117: =L115+L116 -> 32220.774 | M117: =M115+M116 -> 32854.962 | N117: =N115+N116 -> 46691.849
B119: Marginal Tax Rate | I119: 0.25 | J119: ='Control Sheet'!L133 -> 0.25 | K119: ='Control Sheet'!M133 -> 0.25 | L119: ='Control Sheet'!N133 -> 0.25 | M119: ='Control Sheet'!O133 -> 0.25 | N119: ='Control Sheet'!P133 -> 0.25
B121: Retained Earnings Schedule (Dividends)
B123: Retained Earning - Beginning of the year | D123: ='Balance Sheet'!I43 -> 54931.44 | E123: =D126 -> -2740.51 | F123: =E126 -> -63733.17 | G123: =F126 -> -65694.84 | H123: =G126 -> 16105 | I123: =H126 -> 89818 | J123: =I126 -> 65845 | K123: =J126 -> 75284.954 | L123: =K126 -> 109176.07 | ... N123: =M126 -> 174251.8
B124: Add: Net Income | D124: =D117 -> -58064.27 | E124: =E117 -> -61618.45 | F124: =F117 -> -3057.89 | G124: =G117 -> 81725.46 | H124: =H117 -> 72584 | I124: =I117 -> -23936 | J124: =J117 -> 9439.9536 | K124: =K117 -> 33891.114 | ... N124: =N117 -> 46691.849
B125: Less: Dividend Paid | D125: =392.32*-1 -> -392.32 | E125: =625.79*-1 -> -625.79 | F125: =1096.22*-1 -> -1096.22 | G125: =74.38*-1 -> -74.38 | H125: =1129*-1 -> -1129 | I125: =37 -> 37 | J125: 0 | K125: 0 | L125: 0 | M125: 0 | N125: 0
B126: Retained Earnings - Ending of year | D126: =D123+D124-D125 -> -2740.51 | E126: =E123+E124-E125 -> -63733.17 | F126: =F123+F124-F125 -> -65694.84 | G126: =G123+G124-G125 -> 16105 | H126: =H123+H124-H125 -> 89818 | I126: =I123+I124-I125 -> 65845 | J126: =SUM(J123:J125) -> 75284.954 | K126: =SUM(K123:K125) -> 109176.07 | L126: =SUM(L123:L125) -> 141396.84 | M126: =SUM(M123:M125) -> 174251.8 | N126: =SUM(N123:N125) -> 220943.65
I127: ='Balance Sheet'!O43 -> 65845
B128: Dividend Payout Rate % | I128: 0.3 | J128: ='Control Sheet'!L149 -> 0 | K128: ='Control Sheet'!M149 -> 0 | L128: ='Control Sheet'!N149 -> 0 | M128: ='Control Sheet'!O149 -> 0 | N128: ='Control Sheet'!P149 -> 0
B130: Working Capital Schedule
N131: 365
B132: Trade Receivables
B133: Revenue | D133: =D13 -> 146406.31 | E133: =E13 -> 259309.27 | F133: =F13 -> 544464.53 | G133: =G13 -> 689043 | H133: =H13 -> 808029 | I133: =I13 -> 849619 | J133: =J13 -> 1015783.4 | K133: =K13 -> 1214721.6 | ... N133: =N13 -> 2079847.9
...

Sheet 3 Statement Model
B2: ='Control Sheet'!B2 -> InterGlobe Aviation
B3: 3 Statement Model
J5: Current Case | K5: 0
P7: CAGR
D8: Actual | J8: Explicit Forecast Period | P8: 5 Years | Q8: 3 Years
B9: In INR Crores unless stated otherwise | D9: 2021 | E9: =D9+1 -> 2022 | F9: =E9+1 -> 2023 | G9: =F9+1 -> 2024 | H9: =G9+1 -> 2025 | I9: =H9+1 -> 2026 | J9: =I9+1 -> 2027 | K9: =J9+1 -> 2028 | L9: =K9+1 -> 2029 | ... N9: =M9+1 -> 2031
B11: Income Statement
B13: Revenue | D13: ='Schedule Sheet'!D13 -> 146406.31 | E13: ='Schedule Sheet'!E13 -> 259309.27 | F13: ='Schedule Sheet'!F13 -> 544464.53 | G13: ='Schedule Sheet'!G13 -> 689043 | H13: ='Schedule Sheet'!H13 -> 808029 | I13: ='Schedule Sheet'!I13 -> 849619 | J13: ='Schedule Sheet'!J13 -> 1015783.4 | K13: ='Schedule Sheet'!K13 -> 1214721.6 | ... N13: ='Schedule Sheet'!N13 -> 2079847.9 | P13: =IF(OR(I13<=0,N13<=0),"NM",_xlfn.RRI($N$9-$I$9,I13,N13)) -> 0.19608343 | Q13: =IF(OR(K13<=0,N13<=0),"NM",_xlfn.RRI($N$9-$K$9,K13,N13)) -> 0.19633171
B14: Less: Cost of Goods Sold | D14: ='Schedule Sheet'!D26*-1 -> -94483.34 | E14: ='Schedule Sheet'!E26*-1 -> -194408.44 | F14: ='Schedule Sheet'!F26*-1 -> -389093.9 | G14: ='Schedule Sheet'!G26*-1 -> -405950 | H14: ='Schedule Sheet'!H26*-1 -> -481803 | I14: ='Schedule Sheet'!I26*-1 -> -564048 | J14: ='Schedule Sheet'!J26*-1 -> -670417.06 | K14: ='Schedule Sheet'!K26*-1 -> -801716.23 | ... N14: ='Schedule Sheet'!N26*-1 -> -1372699.6 | P14: =_xlfn.RRI($N$9-$I$9,I14,N14) -> 0.19468082 | Q14: =_xlfn.RRI($N$9-$K$9,K14,N14) -> 0.19633171
B15: Gross Profit | D15: =D13+D14 -> 51922.97 | E15: =E13+E14 -> 64900.83 | F15: =F13+F14 -> 155370.63 | G15: =G13+G14 -> 283093 | H15: =H13+H14 -> 326226 | I15: =I13+I14 -> 285571 | J15: =J13+J14 -> 345366.37 | K15: =K13+K14 -> 413005.33 | ... N15: =N13+N14 -> 707148.3 | P15: =IF(OR(I15<=0,N15<=0),"NM",_xlfn.RRI($N$9-$I$9,I15,N15)) -> 0.19883463 | Q15: =IF(OR(K15<=0,N15<=0),"NM",_xlfn.RRI($N$9-$K$9,K15,N15)) -> 0.19633171
B17: Gross Margin % Revenue | D17: =D15/D13 -> 0.35464981 | E17: =E15/E13 -> 0.25028349 | F17: =F15/F13 -> 0.2853641 | G17: =G15/G13 -> 0.41084954 | H17: =H15/H13 -> 0.40373056 | I17: =I15/I13 -> 0.33611654 | J17: =J15/J13 -> 0.34 | K17: =K15/K13 -> 0.34 | ... N17: =N15/N13 -> 0.34
B19: Less: SG&A (Excluding Depreciation and Amortization)
B21: ='Schedule Sheet'!B30 -> Employee Benefit Expenses | D21: ='Schedule Sheet'!D30 -> 32954.92 | E21: ='Schedule Sheet'!E30 -> 34864.43 | F21: ='Schedule Sheet'!F30 -> 47947.52 | G21: ='Schedule Sheet'!G30 -> 64618 | H21: ='Schedule Sheet'!H30 -> 74725 | I21: ='Schedule Sheet'!I30 -> 82722 | J21: ='Schedule Sheet'!J30 -> 101578.34 | K21: ='Schedule Sheet'!K30 -> 121472.16 | ... N21: ='Schedule Sheet'!N30 -> 311977.19 | P21: =IF(OR(I21<=0,N21<=0),"NM",_xlfn.RRI($N$9-$I$9,I21,N21)) -> 0.30406838 | Q21: =IF(OR(K21<=0,N21<=0),"NM",_xlfn.RRI($N$9-$K$9,K21,N21)) -> 0.36945795
B22: ='Schedule Sheet'!B33 -> Other Expenses | D22: ='Schedule Sheet'!D33 -> 19104.1 | E22: ='Schedule Sheet'!E33 -> 24563.07 | F22: ='Schedule Sheet'!F33 -> 42469.61 | G22: ='Schedule Sheet'!G33 -> 55300 | H22: ='Schedule Sheet'!H33 -> 70918 | I22: ='Schedule Sheet'!I33 -> 83015 | J22: ='Schedule Sheet'!J33 -> 91420.509 | K22: ='Schedule Sheet'!K33 -> 109324.94 | ... N22: ='Schedule Sheet'!N33 -> 187186.31 | P22: =IF(OR(I22<=0,N22<=0),"NM",_xlfn.RRI($N$9-$I$9,I22,N22)) -> 0.17658553 | Q22: =IF(OR(K22<=0,N22<=0),"NM",_xlfn.RRI($N$9-$K$9,K22,N22)) -> 0.19633171
B24: Total SG&A | D24: =(D21+D22)*-1 -> -52059.02 | E24: =(E21+E22)*-1 -> -59427.5 | F24: =(F21+F22)*-1 -> -90417.13 | G24: =(G21+G22)*-1 -> -119918 | H24: =(H21+H22)*-1 -> -145643 | I24: =(I21+I22)*-1 -> -165737 | J24: =(J21+J22)*-1 -> -192998.85 | K24: =(K21+K22)*-1 -> -230797.1 | ... N24: =(N21+N22)*-1 -> -499163.5 | P24: =_xlfn.RRI($N$9-$I$9,I24,N24) -> 0.24670778 | Q24: =_xlfn.RRI($N$9-$K$9,K24,N24) -> 0.29321528
B25: EBITDA | D25: =D15+D24 -> -136.05 | E25: =E15+E24 -> 5473.33 | F25: =F15+F24 -> 64953.5 | G25: =G15+G24 -> 163175 | H25: =H15+H24 -> 180583 | I25: =I15+I24 -> 119834 | J25: =J15+J24 -> 152367.51 | K25: =K15+K24 -> 182208.23 | ... N25: =N15+N24 -> 207984.79 | P25: =IF(OR(I25<=0,N25<=0),"NM",_xlfn.RRI($N$9-$I$9,I25,N25)) -> 0.11658118 | Q25: =IF(OR(K25<=0,N25<=0),"NM",_xlfn.RRI($N$9-$K$9,K25,N25)) -> 0.045092012
B27: EBITDA Margin | D27: =D25/D13 -> -0.00092926323 | E27: =E25/E13 -> 0.021107344 | F27: =F25/F13 -> 0.11929795 | G27: =G25/G13 -> 0.23681396 | H27: =H25/H13 -> 0.22348579 | I27: =I25/I13 -> 0.1410444 | J27: =J25/J13 -> 0.15 | K27: =K25/K13 -> 0.15 | ... N27: =N25/N13 -> 0.1
B29: Less: Depreciation and Amortization
B30: Depreciation | D30: ='Income Statement'!J48*-1 -> -46994.46 | E30: ='Income Statement'!K48*-1 -> -50686 | F30: ='Income Statement'!L48*-1 -> -51029.69 | G30: ='Income Statement'!M48*-1 -> -64257 | H30: ='Income Statement'!N48*-1 -> -86802 | I30: ='Income Statement'!O48*-1 -> -108082 | J30: ='Schedule Sheet'!J105*-1 -> -118578.14 | K30: ='Schedule Sheet'!K105*-1 -> -129756.23 | L30: ='Schedule Sheet'!L105*-1 -> -141566.24 | M30: ='Schedule Sheet'!M105*-1 -> -153969.32 | N30: ='Schedule Sheet'!N105*-1 -> -166907.02 | P30: =_xlfn.RRI($N$9-$I$9,I30,N30) -> 0.090797777 | Q30: =_xlfn.RRI($N$9-$K$9,K30,N30) -> 0.087548894
B31: EBIT | D31: =D25+D30 -> -47130.51 | E31: =E25+E30 -> -45212.67 | F31: =F25+F30 -> 13923.81 | G31: =G25+G30 -> 98918 | H31: =H25+H30 -> 93781 | I31: =I25+I30 -> 11752 | J31: =J25+J30 -> 33789.378 | K31: =K25+K30 -> 52452.003 | ... N31: =N25+N30 -> 41077.777 | P31: =IF(OR(I31<=0,N31<=0),"NM",_xlfn.RRI($N$9-$I$9,I31,N31)) -> 0.28439625 | Q31: =IF(OR(K31<=0,N31<=0),"NM",_xlfn.RRI($N$9-$K$9,K31,N31)) -> -0.078246168
B33: EBIT Margin | D33: =D31/D13 -> -0.32191584 | E33: =E31/E13 -> -0.17435809 | F33: =F31/F13 -> 0.025573401 | G33: =G31/G13 -> 0.14355853 | H33: =H31/H13 -> 0.11606143 | I33: =I31/I13 -> 0.013832082 | J33: =J31/J13 -> 0.033264352 | K33: =K31/K13 -> 0.043180269 | ... N33: =N31/N13 -> 0.019750375
B35: Less: Interest Expenses
B36: Finance Cost | D36: ='Income Statement'!J53*-1 -> 21419.83 | E36: ='Income Statement'!K53*-1 -> 23580.15 | F36: ='Income Statement'!L53*-1 -> 31317.31 | G36: ='Income Statement'!M53*-1 -> 41693.54 | H36: ='Income Statement'!N53*-1 -> 50800 | I36: ='Income Statement'!O53*-1 -> 58908 | J36: ='Schedule Sheet'!J234 -> 63865.677 | K36: ='Schedule Sheet'!K234 -> 67999.928 | L36: ='Schedule Sheet'!L234 -> 91529.249 | M36: ='Schedule Sheet'!M234 -> 97716.842 | N36: ='Schedule Sheet'!N234 -> 103612.85 | P36: =IF(OR(I36<=0,N36<=0),"NM",_xlfn.RRI($N$9-$I$9,I36,N36)) -> 0.11956128 | Q36: =IF(OR(K36<=0,N36<=0),"NM",_xlfn.RRI($N$9-$K$9,K36,N36)) -> 0.15071664
B37: Exceptional Items | D37: 0 | E37: 0 | F37: 0 | G37: 0 | H37: 0 | I37: ='Income Statement'!O52*-1 -> 17964 | J37: 0 | K37: 0 | L37: 0 | M37: 0 | N37: 0
B38: Add: Other Income | D38: ='Income Statement'!J51 -> 10369.64 | E38: ='Income Statement'!K51 -> 7255.98 | F38: ='Income Statement'!L51 -> 14349.65 | G38: ='Income Statement'!M51 -> 23269 | H38: ='Income Statement'!N51 -> 32953 | I38: ='Income Statement'!O51 -> 45515 | J38: ='Schedule Sheet'!J240 -> 42662.904 | K38: ='Schedule Sheet'!K240 -> 60736.078 | L38: ='Schedule Sheet'!L240 -> 101705.04 | M38: ='Schedule Sheet'!M240 -> 121673.5 | N38: ='Schedule Sheet'!N240 -> 124790.88 | P38: =IF(OR(I38<=0,N38<=0),"NM",_xlfn.RRI($N$9-$I$9,I38,N38)) -> 0.22350474 | Q38: =IF(OR(K38<=0,N38<=0),"NM",_xlfn.RRI($N$9-$K$9,K38,N38)) -> 0.27129214
B39: EBT | D39: =D31-D36-D37+D38 -> -58180.7 | E39: =E31-E36-E37+E38 -> -61536.84 | F39: =F31-F36-F37+F38 -> -3043.85 | G39: =G31-G36-G37+G38 -> 80493.46 | H39: =H31-H36-H37+H38 -> 75934 | I39: =I31-I36-I37+I38 -> -19605 | J39: =J31-J36-J37+J38 -> 12586.605 | K39: =K31-K36-K37+K38 -> 45188.152 | ... N39: =N31-N36-N37+N38 -> 62255.799 | P39: =IF(OR(I39<=0,N39<=0),"NM",_xlfn.RRI($N$9-$I$9,I39,N39)) -> NM | Q39: =IF(OR(K39<=0,N39<=0),"NM",_xlfn.RRI($N$9-$K$9,K39,N39)) -> 0.1127179
B41: Less: Taxes | D41: ='Income Statement'!J59 -> -116.43 | E41: ='Income Statement'!K59 -> 81.61 | F41: ='Income Statement'!L59 -> 14.04 | G41: ='Income Statement'!M59 -> -1232 | H41: ='Income Statement'!N59 -> 3350 | I41: ='Income Statement'!O59 -> 4331 | J41: ='Schedule Sheet'!J116 -> -3146.6512 | K41: ='Schedule Sheet'!K116 -> -11297.038 | L41: ='Schedule Sheet'!L116 -> -10740.258 | M41: ='Schedule Sheet'!M116 -> -10951.654 | N41: ='Schedule Sheet'!N116 -> -15563.95 | P41: =IF(OR(I41<=0,N41<=0),"NM",_xlfn.RRI($N$9-$I$9,I41,N41)) -> NM | Q41: =_xlfn.RRI($N$9-$K$9,K41,N41) -> 0.1127179
B42: Net Income | D42: =D39-D41 -> -58064.27 | E42: =E39-E41 -> -61618.45 | F42: =F39-F41 -> -3057.89 | G42: =G39-G41 -> 81725.46 | H42: =H39-H41 -> 72584 | I42: =I39-I41 -> -23936 | J42: =J39+J41 -> 9439.9536 | K42: =K39+K41 -> 33891.114 | L42: =L39+L41 -> 32220.774 | M42: =M39+M41 -> 32854.962 | N42: =N39+N41 -> 46691.849 | P42: =IF(OR(I42<=0,N42<=0),"NM",_xlfn.RRI($N$9-$I$9,I42,N42)) -> NM | Q42: =IF(OR(K42<=0,N42<=0),"NM",_xlfn.RRI($N$9-$K$9,K42,N42)) -> 0.1127179
B44: Sales Growth % | D44: =IFERROR(D13/C13-1,"NM") -> NM | E44: =IFERROR(E13/D13-1,"NM") -> 0.77116184 | F44: =IFERROR(F13/E13-1,"NM") -> 1.0996724 | G44: =IFERROR(G13/F13-1,"NM") -> 0.2655425 | H44: =IFERROR(H13/G13-1,"NM") -> 0.17268298 | I44: =IFERROR(I13/H13-1,"NM") -> 0.051470925 | J44: =IFERROR(J13/I13-1,"NM") -> 0.19557523 | K44: =IFERROR(K13/J13-1,"NM") -> 0.19584699 | ... N44: =IFERROR(N13/M13-1,"NM") -> 0.19655765
B45: Gross Profit Margin % | D45: =IFERROR(D15/D13,"NM") -> 0.35464981 | E45: =IFERROR(E15/E13,"NM") -> 0.25028349 | F45: =IFERROR(F15/F13,"NM") -> 0.2853641 | G45: =IFERROR(G15/G13,"NM") -> 0.41084954 | H45: =IFERROR(H15/H13,"NM") -> 0.40373056 | I45: =IFERROR(I15/I13,"NM") -> 0.33611654 | J45: =IFERROR(J15/J13,"NM") -> 0.34 | K45: =IFERROR(K15/K13,"NM") -> 0.34 | ... N45: =IFERROR(N15/N13,"NM") -> 0.34
B46: EBITDA Margin % | D46: =IFERROR(D25/D13,"NM") -> -0.00092926323 | E46: =IFERROR(E25/E13,"NM") -> 0.021107344 | F46: =IFERROR(F25/F13,"NM") -> 0.11929795 | G46: =IFERROR(G25/G13,"NM") -> 0.23681396 | H46: =IFERROR(H25/H13,"NM") -> 0.22348579 | I46: =IFERROR(I25/I13,"NM") -> 0.1410444 | J46: =IFERROR(J25/J13,"NM") -> 0.15 | K46: =IFERROR(K25/K13,"NM") -> 0.15 | ... N46: =IFERROR(N25/N13,"NM") -> 0.1
B47: EBIT Margin % | D47: =IFERROR(D31/D13,"NM") -> -0.32191584 | E47: =IFERROR(E31/E13,"NM") -> -0.17435809 | F47: =IFERROR(F31/F13,"NM") -> 0.025573401 | G47: =IFERROR(G31/G13,"NM") -> 0.14355853 | H47: =IFERROR(H31/H13,"NM") -> 0.11606143 | I47: =IFERROR(I31/I13,"NM") -> 0.013832082 | J47: =IFERROR(J31/J13,"NM") -> 0.033264352 | K47: =IFERROR(K31/K13,"NM") -> 0.043180269 | ... N47: =IFERROR(N31/N13,"NM") -> 0.019750375
B48: Actual Tax Rate % | D48: =IFERROR(-D41/D39,"NM") -> -0.0020011791 | E48: =IFERROR(-E41/E39,"NM") -> 0.0013261974 | F48: =IFERROR(-F41/F39,"NM") -> 0.0046125795 | G48: =IFERROR(-G41/G39,"NM") -> 0.015305591 | H48: =IFERROR(-H41/H39,"NM") -> -0.04411726 | I48: =IFERROR(-I41/I39,"NM") -> 0.22091303 | J48: =IFERROR(-J41/J39,"NM") -> 0.25 | K48: =IFERROR(-K41/K39,"NM") -> 0.25 | ... N48: =IFERROR(-N41/N39,"NM") -> 0.25
B49: Net Income Margin % | D49: =IFERROR(D42/D13,"NM") -> -0.39659677 | E49: =IFERROR(E42/E13,"NM") -> -0.23762533 | F49: =IFERROR(F42/F13,"NM") -> -0.0056163255 | G49: =IFERROR(G42/G13,"NM") -> 0.1186072 | H49: =IFERROR(H42/H13,"NM") -> 0.089828459 | I49: =IFERROR(I42/I13,"NM") -> -0.028172628 | J49: =IFERROR(J42/J13,"NM") -> 0.0092932738 | K49: =IFERROR(K42/K13,"NM") -> 0.027900315 | ... N49: =IFERROR(N42/N13,"NM") -> 0.022449646
B51: Balance Sheet
B53: Assets
B54: Cash | D54: ='Cash Flow Statement'!J95 -> 5088.85 | E54: ='Cash Flow Statement'!K95 -> 10153.29 | F54: ='Cash Flow Statement'!L95 -> 12679.69 | G54: ='Cash Flow Statement'!M95 -> 6953 | H54: ='Cash Flow Statement'!N95 -> 10731 | I54: ='Cash Flow Statement'!O95 -> 13239 | J54: =J202 -> 12850.011 | K54: =K202 -> 75594.011 | L54: =L202 -> 30667.139 | M54: =M202 -> 7441.8579 | N54: =N202 -> 19363.639
B55: Bank balances other than cash and cash equivalents, above | D55: ='Balance Sheet'!J28 -> 107187.8 | E55: ='Balance Sheet'!K28 -> 91048.12 | F55: ='Balance Sheet'!L28 -> 105717.16 | G55: ='Balance Sheet'!M28 -> 160253 | H55: ='Balance Sheet'!N28 -> 178898 | I55: ='Balance Sheet'!O28 -> 226754 | J55: =I55+4292.118555 -> 231046.12 | K55: =J55-591.684659731 -> 230454.43 | L55: =K55+2236.845325515 -> 232691.28 | M55: =L55+831.768270362 -> 233523.05 | N55: =M55+532.783730967 -> 234055.83
B56: Inventory | D56: ='Schedule Sheet'!D140 -> 3164.18 | E56: ='Schedule Sheet'!E140 -> 4080.63 | F56: ='Schedule Sheet'!F140 -> 5910.67 | G56: ='Schedule Sheet'!G140 -> 6248 | H56: ='Schedule Sheet'!H140 -> 8203 | I56: ='Schedule Sheet'!I140 -> 9848 | J56: ='Schedule Sheet'!J140 -> 11020.554 | K56: ='Schedule Sheet'!K140 -> 13178.897 | ... N56: ='Schedule Sheet'!N140 -> 22564.925
B57: Trade Receivables | D57: ='Schedule Sheet'!D134 -> 2189.78 | E57: ='Schedule Sheet'!E134 -> 3329.23 | F57: ='Schedule Sheet'!F134 -> 5199.04 | G57: ='Schedule Sheet'!G134 -> 6425 | H57: ='Schedule Sheet'!H134 -> 7397 | I57: ='Schedule Sheet'!I134 -> 5996 | J57: ='Schedule Sheet'!J134 -> 13914.842 | K57: ='Schedule Sheet'!K134 -> 16640.021 | ... N57: ='Schedule Sheet'!N134 -> 22792.854
B58: Prepaid Expenses | D58: ='Schedule Sheet'!D146 -> 390.93 | E58: ='Schedule Sheet'!E146 -> 632.38 | F58: ='Schedule Sheet'!F146 -> 669.73 | G58: ='Schedule Sheet'!G146 -> 1029 | H58: ='Schedule Sheet'!H146 -> 2138 | I58: ='Schedule Sheet'!I146 -> 3399 | J58: ='Schedule Sheet'!J146 -> 4692.9194 | K58: ='Schedule Sheet'!K146 -> 5612.0136 | ... N58: ='Schedule Sheet'!N146 -> 9608.8974
B59: Financial Current Assets | D59: ='Schedule Sheet'!D156 -> 80872.96 | E59: ='Schedule Sheet'!E156 -> 84345.82 | F59: ='Schedule Sheet'!F156 -> 125977.96 | G59: ='Schedule Sheet'!G156 -> 172993 | H59: ='Schedule Sheet'!H156 -> 283615 | I59: ='Schedule Sheet'!I156 -> 305385 | J59: ='Schedule Sheet'!J156 -> 355524.2 | K59: ='Schedule Sheet'!K156 -> 425152.54 | ... N59: ='Schedule Sheet'!N156 -> 727946.78
B60: Other Current Assets | D60: ='Schedule Sheet'!D151 -> 9244.67 | E60: ='Schedule Sheet'!E151 -> 8699.32 | F60: ='Schedule Sheet'!F151 -> 5332.89 | G60: ='Schedule Sheet'!G151 -> 4630 | H60: ='Schedule Sheet'!H151 -> 16049 | I60: ='Schedule Sheet'!I151 -> 14671 | J60: ='Schedule Sheet'!J151 -> 30473.503 | K60: ='Schedule Sheet'!K151 -> 36441.647 | ... N60: ='Schedule Sheet'!N151 -> 62395.438
B61: Total Current Assests | D61: =SUM(D54:D60) -> 208139.17 | E61: =SUM(E54:E60) -> 202288.79 | F61: =SUM(F54:F60) -> 261487.14 | G61: =SUM(G54:G60) -> 358531 | H61: =SUM(H54:H60) -> 507031 | I61: =SUM(I54:I60) -> 579292 | J61: =SUM(J54:J60) -> 659522.15 | K61: =SUM(K54:K60) -> 803073.57 | ... N61: =SUM(N54:N60) -> 1098728.4
B63: Plant, Machinery and Equipment | D63: ='Balance Sheet'!J9 -> 7969.66 | E63: ='Balance Sheet'!K9 -> 8239.53 | F63: ='Balance Sheet'!L9 -> 11111.69 | G63: ='Balance Sheet'!M9 -> 19029 | H63: ='Balance Sheet'!N9 -> 26779 | I63: ='Balance Sheet'!O9 -> 110871 | J63: ='Schedule Sheet'!J46 -> 117767.33 | K63: ='Schedule Sheet'!K46 -> 124424.94 | L63: ='Schedule Sheet'!L46 -> 130673.22 | M63: ='Schedule Sheet'!M46 -> 136305.67 | N63: ='Schedule Sheet'!N46 -> 141074.48
B64: ='Schedule Sheet'!B49 -> Right of use assets | D64: ='Balance Sheet'!J10 -> 179861.71 | E64: ='Balance Sheet'!K10 -> 204381.48 | F64: ='Balance Sheet'!L10 -> 265364.95 | G64: ='Balance Sheet'!M10 -> 342023 | H64: ='Balance Sheet'!N10 -> 490739 | I64: ='Schedule Sheet'!I52 -> 520540 | J64: ='Schedule Sheet'!J52 -> 552918.29 | K64: ='Schedule Sheet'!K52 -> 584175.85 | L64: ='Schedule Sheet'!L52 -> 613511.53 | M64: ='Schedule Sheet'!M52 -> 639955.94 | N64: ='Schedule Sheet'!N52 -> 662345.52
B65: ='Schedule Sheet'!B56 -> Capital Work In Progress | D65: ='Schedule Sheet'!D56 -> 663.51 | E65: ='Schedule Sheet'!E56 -> 1193.18 | F65: ='Schedule Sheet'!F56 -> 0 | G65: ='Schedule Sheet'!G56 -> 1 | H65: ='Schedule Sheet'!H56 -> 7 | I65: ='Schedule Sheet'!I56 -> 387 | J65: ='Schedule Sheet'!K56 -> 0 | K65: ='Schedule Sheet'!L56 -> 0 | L65: ='Schedule Sheet'!M56 -> 0 | M65: ='Schedule Sheet'!N56 -> 0 | N65: ='Schedule Sheet'!O56 -> 0
B66: ='Schedule Sheet'!B72 -> Other Non-Current Assets | D66: ='Schedule Sheet'!D72 -> 9498.13 | E66: ='Schedule Sheet'!E72 -> 12266.99 | F66: ='Schedule Sheet'!F72 -> 14971.32 | G66: ='Schedule Sheet'!G72 -> 19161 | H66: ='Schedule Sheet'!H72 -> 24169 | I66: ='Schedule Sheet'!I72 -> 38373 | J66: ='Schedule Sheet'!J72 -> 42210.3 | K66: ='Schedule Sheet'!K72 -> 46431.33 | ... N66: ='Schedule Sheet'!N72 -> 61800.1
B67: ='Schedule Sheet'!B60 -> Financial Assets | D67: ='Schedule Sheet'!D60 -> 15823.74 | E67: ='Schedule Sheet'!E60 -> 20911.34 | F67: ='Schedule Sheet'!F60 -> 24500.34 | G67: ='Schedule Sheet'!G60 -> 62711 | H67: ='Schedule Sheet'!H60 -> 88116 | I67: ='Schedule Sheet'!I60 -> 90417 | J67: ='Schedule Sheet'!J60 -> 99458.7 | K67: ='Schedule Sheet'!K60 -> 109404.57 | ... N67: ='Schedule Sheet'!N60 -> 139094.34
B68: ='Schedule Sheet'!B64 -> Deferred Tax | D68: ='Schedule Sheet'!D64 -> 3026.93 | E68: ='Schedule Sheet'!E64 -> 2949.44 | F68: ='Schedule Sheet'!F64 -> 2949.44 | G68: ='Schedule Sheet'!G64 -> 4192 | H68: ='Schedule Sheet'!H64 -> 4192 | I68: ='Schedule Sheet'!I64 -> 0 | J68: ='Schedule Sheet'!J64 -> 0 | K68: ='Schedule Sheet'!K64 -> 0 | ... N68: ='Schedule Sheet'!N64 -> 0
B69: ='Schedule Sheet'!B68 -> Income Tax | D69: ='Schedule Sheet'!D68 -> 5139.53 | E69: ='Schedule Sheet'!E68 -> 7119.22 | F69: ='Schedule Sheet'!F68 -> 10997.87 | G69: ='Schedule Sheet'!G68 -> 16101 | H69: ='Schedule Sheet'!H68 -> 17080 | I69: ='Schedule Sheet'!I68 -> 19775 | J69: ='Schedule Sheet'!J68 -> 24718.75 | K69: ='Schedule Sheet'!K68 -> 30898.438 | ... N69: ='Schedule Sheet'!N68 -> 60348.511
B70: ='Schedule Sheet'!B76 -> Intangible Non Current Asset - Amount Spend | D70: ='Schedule Sheet'!D79 -> 334.96 | E70: ='Schedule Sheet'!E79 -> 215.62 | F70: ='Schedule Sheet'!F79 -> 107.27 | G70: ='Schedule Sheet'!G79 -> 483 | H70: ='Schedule Sheet'!H79 -> 299 | I70: ='Schedule Sheet'!J79 -> 159.99893 | J70: ='Schedule Sheet'!J79 -> 159.99893 | K70: ='Schedule Sheet'!K79 -> 159.99786 | L70: ='Schedule Sheet'!L79 -> 159.99679 | M70: ='Schedule Sheet'!M79 -> 159.99572 | N70: ='Schedule Sheet'!N79 -> 159.99465
B71: ='Schedule Sheet'!B85 -> Intangible Non Current Asset - Under Development | D71: ='Schedule Sheet'!D85 -> 54.19 | E71: ='Schedule Sheet'!E85 -> 60.39 | F71: ='Schedule Sheet'!F85 -> 208.17 | G71: ='Schedule Sheet'!G85 -> 13 | H71: ='Schedule Sheet'!H85 -> 23 | I71: ='Schedule Sheet'!I85+0.001069575 -> 206.00107 | J71: ='Schedule Sheet'!J85 -> 206 | K71: ='Schedule Sheet'!K85 -> 206 | L71: ='Schedule Sheet'!L85 -> 206 | M71: ='Schedule Sheet'!M85 -> 206 | N71: ='Schedule Sheet'!N85 -> 206
B72: Total Non-Current Assests | D72: =SUM(D63:D71) -> 222372.36 | E72: =SUM(E63:E71) -> 257337.19 | F72: =SUM(F63:F71) -> 330211.05 | G72: =SUM(G63:G71) -> 463714 | H72: =SUM(H63:H71) -> 651404 | I72: =SUM(I63:I71) -> 780729 | J72: =SUM(J63:J71) -> 837439.36 | K72: =SUM(K63:K71) -> 895701.12 | ... N72: =SUM(N63:N71) -> 1065028.9
B74: Total Assets | D74: =SUM(D61,D72) -> 430511.53 | E74: =SUM(E61,E72) -> 459625.98 | F74: =SUM(F61,F72) -> 591698.19 | G74: =SUM(G61,G72) -> 822245 | H74: =SUM(H61,H72) -> 1158435 | I74: =SUM(I61,I72) -> 1360021 | J74: =SUM(J61,J72) -> 1496961.5 | K74: =SUM(K61,K72) -> 1698774.7 | ... N74: =SUM(N61,N72) -> 2163757.3
B77: Liability and Shareholder's Equity
B78: Trade Payables | D78: =SUM('Balance Sheet'!J63:J64) -> 15513.29 | E78: =SUM('Balance Sheet'!K63:K64) -> 31518.2 | F78: =SUM('Balance Sheet'!L63:L64) -> 32089.89 | G78: =SUM('Balance Sheet'!M63:M64) -> 31576 | H78: =SUM('Balance Sheet'!N63:N64) -> 41756 | I78: =SUM('Balance Sheet'!O63:O64) -> 49905 | J78: ='Schedule Sheet'!J161 -> 55102.772 | K78: ='Schedule Sheet'!K161 -> 65894.484 | L78: ='Schedule Sheet'!L161 -> 65680.355 | M78: ='Schedule Sheet'!M161 -> 78575.84 | N78: ='Schedule Sheet'!N161 -> 94020.523
B79: Provision | D79: ='Balance Sheet'!J67 -> 30.76 | E79: ='Balance Sheet'!K67 -> 30.76 | F79: ='Balance Sheet'!L67 -> 30.76 | G79: ='Balance Sheet'!M67 -> 5890 | H79: ='Balance Sheet'!N67 -> 17468 | I79: ='Balance Sheet'!O67 -> 26210 | J79: ='Schedule Sheet'!J176 -> 30473.503 | K79: ='Schedule Sheet'!K176 -> 36441.647 | L79: ='Schedule Sheet'!L176 -> 43587.872 | M79: ='Schedule Sheet'!M176 -> 34763.857 | N79: ='Schedule Sheet'!N176 -> 41596.959
B80: Other Current Liability | D80: ='Balance Sheet'!J66 -> 16083.58 | E80: ='Balance Sheet'!K66 -> 7602.76 | F80: ='Balance Sheet'!L66 -> 2896.5 | G80: ='Balance Sheet'!M66 -> 65334 | H80: ='Balance Sheet'!N66 -> 83727 | I80: ='Balance Sheet'!O66 -> 87657 | J80: ='Schedule Sheet'!J180 -> 96422.7 | K80: ='Schedule Sheet'!K180 -> 104136.52 | L80: ='Schedule Sheet'!L180 -> 112467.44 | M80: ='Schedule Sheet'!M180 -> 121464.83 | N80: ='Schedule Sheet'!N180 -> 131182.02
B81: Financial Liability | D81: =SUM('Balance Sheet'!J60:J61) -> 91974.92 | E81: =SUM('Balance Sheet'!K60:K61) -> 114030.07 | F81: =SUM('Balance Sheet'!L60:L61) -> 126296.04 | G81: =SUM('Balance Sheet'!M60:M61) -> 134166 | H81: =SUM('Balance Sheet'!N60:N61) -> 121415 | I81: =SUM('Balance Sheet'!O60:O61) -> 132787 | J81: ='Schedule Sheet'!J166 -> 142209.68 | K81: ='Schedule Sheet'!K166 -> 170061.02 | L81: ='Schedule Sheet'!L166 -> 203410.07 | M81: ='Schedule Sheet'!M166 -> 243347 | N81: ='Schedule Sheet'!N166 -> 291178.71
B82: Current tax liabilities (net) | D82: ='Balance Sheet'!J68 -> 17923.74 | E82: ='Balance Sheet'!K68 -> 33584.98 | F82: ='Balance Sheet'!L68 -> 50820.64 | G82: ='Balance Sheet'!M68 -> 31 | H82: ='Balance Sheet'!N68 -> 31 | I82: ='Balance Sheet'!O68 -> 43 | J82: 43 | K82: 43 | L82: 43 | M82: 43 | N82: 43
B83: Deferred incentives | D83: ='Balance Sheet'!J69 -> 476.03 | E83: ='Balance Sheet'!K69 -> 476.04 | F83: ='Balance Sheet'!L69 -> 476.04 | G83: ='Balance Sheet'!M69 -> 476 | H83: ='Balance Sheet'!N69 -> 258 | I83: ='Balance Sheet'!O69 -> 48 | J83: 43 | K83: 43 | L83: 43 | M83: 43 | N83: 43
B84: Other financial liabilities | D84: ='Balance Sheet'!J65 -> 47234.6 | E84: ='Balance Sheet'!K65 -> 36928.59 | F84: ='Balance Sheet'!L65 -> 25901.59 | G84: ='Balance Sheet'!M65 -> 70509 | H84: ='Balance Sheet'!N65 -> 77523 | I84: ='Balance Sheet'!O65 -> 86060 | J84: ='Schedule Sheet'!J171 -> 91420.509 | K84: ='Schedule Sheet'!K171 -> 109324.94 | L84: ='Schedule Sheet'!L171 -> 116234.33 | M84: ='Schedule Sheet'!M171 -> 139055.43 | N84: ='Schedule Sheet'!N171 -> 166387.83
B85: Total Current Liability | D85: =SUM(D78:D84) -> 189236.92 | E85: =SUM(E78:E84) -> 224171.4 | F85: =SUM(F78:F84) -> 238511.46 | G85: =SUM(G78:G84) -> 307982 | H85: =SUM(H78:H84) -> 342178 | I85: =SUM(I78:I84) -> 382710 | J85: =SUM(J78:J84) -> 415715.16 | K85: =SUM(K78:K84) -> 485944.6 | ... N85: =SUM(N78:N84) -> 724452.04
B87: Financial liabilities | D87: =SUM('Balance Sheet'!J49:J50) -> 206621.62 | E87: =SUM('Balance Sheet'!K49:K50) -> 254748.3 | F87: =SUM('Balance Sheet'!L49:L50) -> 322246.09 | G87: =SUM('Balance Sheet'!M49:M50) -> 378635 | H87: =SUM('Balance Sheet'!N49:N50) -> 546683 | I87: =SUM('Balance Sheet'!O49:O50) -> 644705 | J87: =SUM('Schedule Sheet'!J200,'Schedule Sheet'!J201) -> 676940.25 | K87: =SUM('Schedule Sheet'!K200,'Schedule Sheet'!K201) -> 710787.26 | L87: =SUM('Schedule Sheet'!L200,'Schedule Sheet'!L201) -> 746326.63 | M87: =SUM('Schedule Sheet'!M200,'Schedule Sheet'!M201) -> 761253.16 | N87: =SUM('Schedule Sheet'!N200,'Schedule Sheet'!N201) -> 776478.22
B88: Other financial liabilities | D88: ='Balance Sheet'!J51 -> 26049.29 | E88: ='Balance Sheet'!K51 -> 33093 | F88: ='Balance Sheet'!L51 -> 78811.1 | G88: ='Balance Sheet'!M51 -> 92343 | H88: ='Balance Sheet'!N51 -> 151192 | I88: ='Balance Sheet'!O51 -> 229111 | J88: ='Schedule Sheet'!J210 -> 284419.36 | K88: ='Schedule Sheet'!K210 -> 340122.04 | L88: ='Schedule Sheet'!L210 -> 319644.4 | M88: ='Schedule Sheet'!M210 -> 330256.64 | N88: ='Schedule Sheet'!N210 -> 353574.15
B89: Provisions | D89: ='Balance Sheet'!J52 -> 5522.94 | E89: ='Balance Sheet'!K52 -> 5896.88 | F89: ='Balance Sheet'!L52 -> 13364.54 | G89: ='Balance Sheet'!M52 -> 22301 | H89: ='Balance Sheet'!N52 -> 24079 | I89: ='Balance Sheet'!O52 -> 33100 | J89: ='Schedule Sheet'!J214 -> 39720 | K89: ='Schedule Sheet'!K214 -> 47664 | L89: ='Schedule Sheet'!L214 -> 57196.8 | M89: ='Schedule Sheet'!M214 -> 68636.16 | N89: ='Schedule Sheet'!N214 -> 82363.392
B90: Other non-current liabilities | D90: ='Balance Sheet'!J54 -> 241.9 | E90: ='Balance Sheet'!K54 -> 342.79 | F90: ='Balance Sheet'!L54 -> 451.97 | G90: ='Balance Sheet'!M54 -> 717 | H90: ='Balance Sheet'!N54 -> 573 | I90: ='Balance Sheet'!O54 -> 521 | J90: ='Schedule Sheet'!J220 -> 1015.7834 | K90: ='Schedule Sheet'!K220 -> 1214.7216 | L90: ='Schedule Sheet'!L220 -> 1452.9291 | M90: ='Schedule Sheet'!M220 -> 1738.1928 | N90: ='Schedule Sheet'!N220 -> 2079.8479
B91: Non controlling interest | D91: ='Balance Sheet'!J46 -> 0 | E91: ='Balance Sheet'!K46 -> 0 | F91: ='Balance Sheet'!L46 -> 0 | G91: ='Balance Sheet'!M46 -> 0 | H91: ='Balance Sheet'!N46 -> 0 | I91: 163 | J91: 0 | K91: 0 | L91: 0 | M91: 0 | N91: 0
B92: Deferred incentives | D92: ='Balance Sheet'!J55 -> 1730.27 | E92: ='Balance Sheet'!K55 -> 1254.23 | F92: ='Balance Sheet'!L55 -> 778.19 | G92: ='Balance Sheet'!M55 -> 302 | H92: ='Balance Sheet'!N55 -> 48 | I92: ='Balance Sheet'!O55 -> 0 | J92: ='Schedule Sheet'!J226 -> 0 | K92: ='Schedule Sheet'!K226 -> 0 | L92: ='Schedule Sheet'!L226 -> 0 | M92: ='Schedule Sheet'!M226 -> 0 | N92: ='Schedule Sheet'!N226 -> 0
B93: Total Non-Current Liability | D93: =SUM(D87:D92) -> 240166.02 | E93: =SUM(E87:E92) -> 295335.2 | F93: =SUM(F87:F92) -> 415651.89 | G93: =SUM(G87:G92) -> 494298 | H93: =SUM(H87:H92) -> 722575 | I93: =SUM(I87:I92) -> 907600 | J93: =SUM(J87:J92) -> 1002095.4 | K93: =SUM(K87:K92) -> 1099788 | ... N93: =SUM(N87:N92) -> 1214495.6
B95: Equity share capital | D95: ='Balance Sheet'!J42 -> 3849.1 | E95: ='Balance Sheet'!K42 -> 3852.55 | F95: ='Balance Sheet'!L42 -> 3855.47 | G95: ='Balance Sheet'!M42 -> 3860 | H95: ='Balance Sheet'!N42 -> 3864 | I95: ='Balance Sheet'!O42 -> 3866 | J95: =I95 -> 3866 | K95: =J95 -> 3866 | L95: =K95 -> 3866 | M95: =L95 -> 3866 | N95: =M95 -> 3866
B96: Other equity | D96: ='Balance Sheet'!J43 -> -2740.51 | E96: ='Balance Sheet'!K43 -> -63733.17 | F96: ='Balance Sheet'!L43 -> -66320.63 | G96: ='Balance Sheet'!M43 -> 16105 | H96: ='Balance Sheet'!N43 -> 89818 | I96: ='Balance Sheet'!O43 -> 65845 | J96: ='Schedule Sheet'!J126 -> 75284.954 | K96: ='Schedule Sheet'!K126 -> 109176.07 | L96: ='Schedule Sheet'!L126 -> 141396.84 | M96: ='Schedule Sheet'!M126 -> 174251.8 | N96: ='Schedule Sheet'!N126 -> 220943.65
B97: Total Shareholder's Equity | D97: =D95+D96 -> 1108.59 | E97: =E95+E96 -> -59880.62 | F97: =F95+F96 -> -62465.16 | G97: =G95+G96 -> 19965 | H97: =H95+H96 -> 93682 | I97: =I95+I96 -> 69711 | J97: =J95+J96 -> 79150.954 | K97: =K95+K96 -> 113042.07 | ... N97: =N95+N96 -> 224809.65
B99: Total Liability and Shareholder's Equity | D99: =D97+D93+D85 -> 430511.53 | E99: =E97+E93+E85 -> 459625.98 | F99: =F97+F93+F85 -> 591698.19 | G99: =G97+G93+G85 -> 822245 | H99: =H97+H93+H85 -> 1158435 | I99: =I97+I93+I85 -> 1360021 | J99: =J97+J93+J85 -> 1496961.5 | K99: =K97+K93+K85 -> 1698774.7 | ... N99: =N97+N93+N85 -> 2163757.3
D101: =D74-D99 -> 0 | E101: =E74-E99 -> 0 | F101: =F74-F99 -> 0 | G101: =G74-G99 -> 0 | H101: =H74-H99 -> 0 | I101: =I74-I99 -> 0 | J101: =J74-J99 -> 0 | K101: =K74-K99 -> 0 | ... N101: =N74-N99 -> 0
B103: Net Working Capital | D103: =D61-D85 -> 18902.25 | E103: =E61-E85 -> -21882.61 | F103: =F61-F85 -> 22975.68 | G103: =G61-G85 -> 50549 | H103: =H61-H85 -> 164853 | I103: =I61-I85 -> 196582 | J103: =J61-J85 -> 243806.98 | K103: =K61-K85 -> 317128.96 | ... N103: =N61-N85 -> 374276.32
B104: Trade Receivables Days | D104: =D57/D13*365 -> 5.4592572 | E104: =E57/E13*365 -> 4.6861763 | F104: =F57/F13*365 -> 3.4853503 | G104: =G57/G13*365 -> 3.4034523 | H104: =H57/H13*365 -> 3.3413467 | I104: =I57/I13*365 -> 2.5759076 | J104: =J57/J13*365 -> 5 | K104: =K57/K13*365 -> 5 | ... N104: =N57/N13*365 -> 4
B105: Inventory Days | D105: =-D56/D14*365 -> 12.223591 | E105: =-E56/E14*365 -> 7.6613441 | F105: =-F56/F14*365 -> 5.544663 | G105: =-G56/G14*365 -> 5.6177362 | H105: =-H56/H14*365 -> 6.2143552 | I105: =-I56/I14*365 -> 6.3727201 | J105: =-J56/J14*365 -> 6 | K105: =-K56/K14*365 -> 6 | ... N105: =-N56/N14*365 -> 6
B106: Trade Payables Days | D106: =D78/D13*365 -> 38.675593 | E106: =E78/E13*365 -> 44.364565 | F106: =F78/F13*365 -> 21.512531 | G106: =G78/G13*365 -> 16.726445 | H106: =H78/H13*365 -> 18.861873 | I106: =I78/I13*365 -> 21.439404 | J106: =J78/J13*365 -> 19.8 | K106: =K78/K13*365 -> 19.8 | ... N106: =N78/N13*365 -> 16.5
B107: Prepaid Expenses % Sales | D107: =D58/D13 -> 0.0026701718 | E107: =E58/E13 -> 0.0024387096 | F107: =F58/F13 -> 0.0012300709 | G107: =G58/G13 -> 0.0014933756 | H107: =H58/H13 -> 0.0026459446 | I107: =I58/I13 -> 0.0040006167 | J107: =J58/J13 -> 0.00462 | K107: =K58/K13 -> 0.00462 | ... N107: =N58/N13 -> 0.00462
B108: Other Current Assets % Sales | D108: =D60/D13 -> 0.063143931 | E108: =E60/E13 -> 0.033548049 | F108: =F60/F13 -> 0.0097947427 | G108: =G60/G13 -> 0.0067194645 | H108: =H60/H13 -> 0.019861911 | I108: =I60/I13 -> 0.01726774 | J108: =J60/J13 -> 0.03 | K108: =K60/K13 -> 0.03 | ... N108: =N60/N13 -> 0.03
B109: Other Current Liability % Sales | D109: =D80/D13 -> 0.10985578 | E109: =E80/E13 -> 0.029319276 | F109: =F80/F13 -> 0.0053199058 | G109: =G80/G13 -> 0.094818466 | H109: =H80/H13 -> 0.10361881 | I109: =I80/I13 -> 0.10317213 | J109: =J80/J13 -> 0.094924466 | K109: =K80/K13 -> 0.085728713 | ... N109: =N80/N13 -> 0.06307289
B110: Other Payables % Sales | D110: =D79/D13 -> 0.00021010023 | E110: =E79/E13 -> 0.00011862283 | F110: =F79/F13 -> 5.6495875e-05 | G110: =G79/G13 -> 0.0085480877 | H110: =H79/H13 -> 0.021618036 | I110: =I79/I13 -> 0.030849122 | J110: =J79/J13 -> 0.03 | K110: =K79/K13 -> 0.03 | ... N110: =N79/N13 -> 0.02
B112: Cash Flow Statement
B114: Earning before tax | D114: =D39 -> -58180.7 | E114: =E39 -> -61536.84 | F114: =F39 -> -3043.85 | G114: =G39 -> 80493.46 | H114: =H39 -> 75934 | I114: =I39 -> -19605 | J114: =J39 -> 12586.605 | K114: =K39 -> 45188.152 | ... N114: =N39 -> 62255.799
B115: Depreciation & Amortization | D115: ='Cash Flow Statement'!J12 -> 46994.46 | E115: ='Cash Flow Statement'!K12 -> 50686 | F115: ='Cash Flow Statement'!L12 -> 51029.69 | G115: ='Cash Flow Statement'!M12 -> 64257 | H115: ='Cash Flow Statement'!N12 -> 86802 | I115: ='Cash Flow Statement'!O12 -> 108082 | J115: =J30*-1 -> 118578.14 | K115: =K30*-1 -> 129756.23 | L115: =L30*-1 -> 141566.24 | M115: =M30*-1 -> 153969.32 | N115: =N30*-1 -> 166907.02
B116: Depreciation and amortisation expense
B117: Deferred rent amortisation (included in Aircraft and engine rentals)
B119: Interest Expenses | D119: =SUM('Cash Flow Statement'!J13,'Cash Flow Statement'!J25,'Cash Flow Statement'!J15) -> 20858.33 | E119: =SUM('Cash Flow Statement'!K13,'Cash Flow Statement'!K25,'Cash Flow Statement'!K15) -> 23310.07 | F119: =SUM('Cash Flow Statement'!L13,'Cash Flow Statement'!L25,'Cash Flow Statement'!L15) -> 31066.9 | G119: =SUM('Cash Flow Statement'!M13,'Cash Flow Statement'!M25,'Cash Flow Statement'!M15) -> 41689 | H119: =SUM('Cash Flow Statement'!N13,'Cash Flow Statement'!N25,'Cash Flow Statement'!N15) -> 50799 | I119: =SUM('Cash Flow Statement'!O13,'Cash Flow Statement'!O25,'Cash Flow Statement'!O15) -> 58901 | J119: =J36 -> 63865.677 | K119: =K36 -> 67999.928 | L119: =L36 -> 91529.249 | M119: =M36 -> 97716.842 | N119: =N36 -> 103612.85
B120: Interest on lease liabilities
B121: Interest on borrowings measured at amortised cost
B122: Finance lease charges on finance lease obligations measured at amortised cost
B123: Interest accretion on provisions and other financial liabilities measured at amortised cost (net)
B125: Interest Income | D125: ='Cash Flow Statement'!J17+'Cash Flow Statement'!J20 -> -2443.85 | E125: ='Cash Flow Statement'!K17+'Cash Flow Statement'!K20 -> -2019.38 | F125: ='Cash Flow Statement'!L17+'Cash Flow Statement'!L20 -> -4655.34 | G125: ='Cash Flow Statement'!M17+'Cash Flow Statement'!M20 -> -11583 | H125: ='Cash Flow Statement'!N17+'Cash Flow Statement'!N20 -> -15953 | I125: ='Cash Flow Statement'!O17+'Cash Flow Statement'!O20 -> -19523 | J125: ='Schedule Sheet'!J243*-1 -> -22749.145 | K125: ='Schedule Sheet'!K243*-1 -> -26727.856 | L125: ='Schedule Sheet'!L243*-1 -> -31388.808 | M125: ='Schedule Sheet'!M243*-1 -> -36857.928 | N125: ='Schedule Sheet'!N243*-1 -> -43352.056
B126: Interest income from bank deposits
B127: Interest income from financial assets at amortised cost
B129: Foreign Exchange | D129: ='Cash Flow Statement'!J14 -> -4664.75 | E129: ='Cash Flow Statement'!K14 -> 7886.01 | F129: ='Cash Flow Statement'!L14 -> 30035.37 | G129: ='Cash Flow Statement'!M14 -> 8262 | H129: ='Cash Flow Statement'!N14 -> 17083 | I129: ='Cash Flow Statement'!O14 -> 93186 | J129: =I129 -> 93186 | K129: =J129 -> 93186 | L129: 0 | M129: 0 | N129: 0
B130: Unrealised foreign exchange loss (net) | L130: 0 | M130: 0 | N130: 0
L131: 0 | M131: 0 | N131: 0
...

Sheet Common Sized Model
B2: ='Control Sheet'!B2 -> InterGlobe Aviation
B3: Common Sized Statement Model
H5: Current Case | I5: 1
D7: Actual | J7: Explicit Forecast Period
B8: In INR Crores unless stated otherwise | D8: 2021 | E8: =D8+1 -> 2022 | F8: =E8+1 -> 2023 | G8: =F8+1 -> 2024 | H8: =G8+1 -> 2025 | I8: =H8+1 -> 2026 | J8: =I8+1 -> 2027 | K8: =J8+1 -> 2028 | L8: =K8+1 -> 2029 | ... N8: =M8+1 -> 2031
B10: Common Sized Income Statement
B12: Revenue | D12: ='3 Statement Model'!D13/'3 Statement Model'!D$13 -> 1 | E12: ='3 Statement Model'!E13/'3 Statement Model'!E$13 -> 1 | F12: ='3 Statement Model'!F13/'3 Statement Model'!F$13 -> 1 | G12: ='3 Statement Model'!G13/'3 Statement Model'!G$13 -> 1 | H12: ='3 Statement Model'!H13/'3 Statement Model'!H$13 -> 1 | I12: ='3 Statement Model'!I13/'3 Statement Model'!I$13 -> 1 | J12: ='3 Statement Model'!J13/'3 Statement Model'!J$13 -> 1 | K12: ='3 Statement Model'!K13/'3 Statement Model'!K$13 -> 1 | ... N12: ='3 Statement Model'!N13/'3 Statement Model'!N$13 -> 1
B13: Less: Cost of Goods Sold | D13: ='3 Statement Model'!D14/'3 Statement Model'!D$13 -> -0.64535019 | E13: ='3 Statement Model'!E14/'3 Statement Model'!E$13 -> -0.74971651 | F13: ='3 Statement Model'!F14/'3 Statement Model'!F$13 -> -0.7146359 | G13: ='3 Statement Model'!G14/'3 Statement Model'!G$13 -> -0.58915046 | H13: ='3 Statement Model'!H14/'3 Statement Model'!H$13 -> -0.59626944 | I13: ='3 Statement Model'!I14/'3 Statement Model'!I$13 -> -0.66388346 | J13: ='3 Statement Model'!J14/'3 Statement Model'!J$13 -> -0.66 | K13: ='3 Statement Model'!K14/'3 Statement Model'!K$13 -> -0.66 | ... N13: ='3 Statement Model'!N14/'3 Statement Model'!N$13 -> -0.66
B14: Gross Profit | D14: ='3 Statement Model'!D15/'3 Statement Model'!D$13 -> 0.35464981 | E14: ='3 Statement Model'!E15/'3 Statement Model'!E$13 -> 0.25028349 | F14: ='3 Statement Model'!F15/'3 Statement Model'!F$13 -> 0.2853641 | G14: ='3 Statement Model'!G15/'3 Statement Model'!G$13 -> 0.41084954 | H14: ='3 Statement Model'!H15/'3 Statement Model'!H$13 -> 0.40373056 | I14: ='3 Statement Model'!I15/'3 Statement Model'!I$13 -> 0.33611654 | J14: ='3 Statement Model'!J15/'3 Statement Model'!J$13 -> 0.34 | K14: ='3 Statement Model'!K15/'3 Statement Model'!K$13 -> 0.34 | ... N14: ='3 Statement Model'!N15/'3 Statement Model'!N$13 -> 0.34
B16: Less: SG&A (Excluding Depreciation and Amortization)
B17: ='3 Statement Model'!B21 -> Employee Benefit Expenses | D17: ='3 Statement Model'!D21/'3 Statement Model'!D$13 -> 0.22509221 | E17: ='3 Statement Model'!E21/'3 Statement Model'!E$13 -> 0.13445115 | F17: ='3 Statement Model'!F21/'3 Statement Model'!F$13 -> 0.088063625 | G17: ='3 Statement Model'!G21/'3 Statement Model'!G$13 -> 0.093779343 | H17: ='3 Statement Model'!H21/'3 Statement Model'!H$13 -> 0.092478117 | I17: ='3 Statement Model'!I21/'3 Statement Model'!I$13 -> 0.097363642 | J17: ='3 Statement Model'!J21/'3 Statement Model'!J$13 -> 0.1 | K17: ='3 Statement Model'!K21/'3 Statement Model'!K$13 -> 0.1 | ... N17: ='3 Statement Model'!N21/'3 Statement Model'!N$13 -> 0.15
B18: ='3 Statement Model'!B22 -> Other Expenses | D18: ='3 Statement Model'!D22/'3 Statement Model'!D$13 -> 0.13048686 | E18: ='3 Statement Model'!E22/'3 Statement Model'!E$13 -> 0.094724998 | F18: ='3 Statement Model'!F22/'3 Statement Model'!F$13 -> 0.078002528 | G18: ='3 Statement Model'!G22/'3 Statement Model'!G$13 -> 0.080256239 | H18: ='3 Statement Model'!H22/'3 Statement Model'!H$13 -> 0.087766652 | I18: ='3 Statement Model'!I22/'3 Statement Model'!I$13 -> 0.097708502 | J18: ='3 Statement Model'!J22/'3 Statement Model'!J$13 -> 0.09 | K18: ='3 Statement Model'!K22/'3 Statement Model'!K$13 -> 0.09 | ... N18: ='3 Statement Model'!N22/'3 Statement Model'!N$13 -> 0.09
B20: ='3 Statement Model'!B24 -> Total SG&A | D20: ='3 Statement Model'!D24/'3 Statement Model'!D$13 -> -0.35557907 | E20: ='3 Statement Model'!E24/'3 Statement Model'!E$13 -> -0.22917615 | F20: ='3 Statement Model'!F24/'3 Statement Model'!F$13 -> -0.16606615 | G20: ='3 Statement Model'!G24/'3 Statement Model'!G$13 -> -0.17403558 | H20: ='3 Statement Model'!H24/'3 Statement Model'!H$13 -> -0.18024477 | I20: ='3 Statement Model'!I24/'3 Statement Model'!I$13 -> -0.19507214 | J20: ='3 Statement Model'!J24/'3 Statement Model'!J$13 -> -0.19 | K20: ='3 Statement Model'!K24/'3 Statement Model'!K$13 -> -0.19 | ... N20: ='3 Statement Model'!N24/'3 Statement Model'!N$13 -> -0.24
B21: ='3 Statement Model'!B25 -> EBITDA | D21: ='3 Statement Model'!D25/'3 Statement Model'!D$13 -> -0.00092926323 | E21: ='3 Statement Model'!E25/'3 Statement Model'!E$13 -> 0.021107344 | F21: ='3 Statement Model'!F25/'3 Statement Model'!F$13 -> 0.11929795 | G21: ='3 Statement Model'!G25/'3 Statement Model'!G$13 -> 0.23681396 | H21: ='3 Statement Model'!H25/'3 Statement Model'!H$13 -> 0.22348579 | I21: ='3 Statement Model'!I25/'3 Statement Model'!I$13 -> 0.1410444 | J21: ='3 Statement Model'!J25/'3 Statement Model'!J$13 -> 0.15 | K21: ='3 Statement Model'!K25/'3 Statement Model'!K$13 -> 0.15 | ... N21: ='3 Statement Model'!N25/'3 Statement Model'!N$13 -> 0.1
B23: ='3 Statement Model'!B29 -> Less: Depreciation and Amortization
B24: ='3 Statement Model'!B30 -> Depreciation | D24: ='3 Statement Model'!D30/'3 Statement Model'!D$13 -> -0.32098657 | E24: ='3 Statement Model'!E30/'3 Statement Model'!E$13 -> -0.19546544 | F24: ='3 Statement Model'!F30/'3 Statement Model'!F$13 -> -0.093724544 | G24: ='3 Statement Model'!G30/'3 Statement Model'!G$13 -> -0.093255428 | H24: ='3 Statement Model'!H30/'3 Statement Model'!H$13 -> -0.10742436 | I24: ='3 Statement Model'!I30/'3 Statement Model'!I$13 -> -0.12721232 | J24: ='3 Statement Model'!J30/'3 Statement Model'!J$13 -> -0.11673565 | K24: ='3 Statement Model'!K30/'3 Statement Model'!K$13 -> -0.10681973 | ... N24: ='3 Statement Model'!N30/'3 Statement Model'!N$13 -> -0.080249625
B25: ='3 Statement Model'!B31 -> EBIT | D25: ='3 Statement Model'!D31/'3 Statement Model'!D$13 -> -0.32191584 | E25: ='3 Statement Model'!E31/'3 Statement Model'!E$13 -> -0.17435809 | F25: ='3 Statement Model'!F31/'3 Statement Model'!F$13 -> 0.025573401 | G25: ='3 Statement Model'!G31/'3 Statement Model'!G$13 -> 0.14355853 | H25: ='3 Statement Model'!H31/'3 Statement Model'!H$13 -> 0.11606143 | I25: ='3 Statement Model'!I31/'3 Statement Model'!I$13 -> 0.013832082 | J25: ='3 Statement Model'!J31/'3 Statement Model'!J$13 -> 0.033264352 | K25: ='3 Statement Model'!K31/'3 Statement Model'!K$13 -> 0.043180269 | ... N25: ='3 Statement Model'!N31/'3 Statement Model'!N$13 -> 0.019750375
B27: ='3 Statement Model'!B35 -> Less: Interest Expenses
B28: ='3 Statement Model'!B36 -> Finance Cost | D28: ='3 Statement Model'!D36/'3 Statement Model'!D$13*-1 -> -0.14630401 | E28: ='3 Statement Model'!E36/'3 Statement Model'!E$13*-1 -> -0.090934466 | F28: ='3 Statement Model'!F36/'3 Statement Model'!F$13*-1 -> -0.057519468 | G28: ='3 Statement Model'!G36/'3 Statement Model'!G$13*-1 -> -0.060509344 | H28: ='3 Statement Model'!H36/'3 Statement Model'!H$13*-1 -> -0.062869031 | I28: ='3 Statement Model'!I36/'3 Statement Model'!I$13*-1 -> -0.069334608 | J28: ='3 Statement Model'!J36/'3 Statement Model'!J$13*-1 -> -0.062873321 | K28: ='3 Statement Model'!K36/'3 Statement Model'!K$13*-1 -> -0.055979848 | ... N28: ='3 Statement Model'!N36/'3 Statement Model'!N$13*-1 -> -0.049817514
B29: ='3 Statement Model'!B37 -> Exceptional Items | D29: ='3 Statement Model'!D37/'3 Statement Model'!D$13*-1 -> 0 | E29: ='3 Statement Model'!E37/'3 Statement Model'!E$13*-1 -> 0 | F29: ='3 Statement Model'!F37/'3 Statement Model'!F$13*-1 -> 0 | G29: ='3 Statement Model'!G37/'3 Statement Model'!G$13*-1 -> 0 | H29: ='3 Statement Model'!H37/'3 Statement Model'!H$13*-1 -> 0 | I29: ='3 Statement Model'!I37/'3 Statement Model'!I$13*-1 -> -0.021143595 | J29: ='3 Statement Model'!J37/'3 Statement Model'!J$13*-1 -> 0 | K29: ='3 Statement Model'!K37/'3 Statement Model'!K$13*-1 -> 0 | ... N29: ='3 Statement Model'!N37/'3 Statement Model'!N$13*-1 -> 0
B30: ='3 Statement Model'!B38 -> Add: Other Income | D30: ='3 Statement Model'!D38/'3 Statement Model'!D$13 -> 0.070827822 | E30: ='3 Statement Model'!E38/'3 Statement Model'!E$13 -> 0.027981954 | F30: ='3 Statement Model'!F38/'3 Statement Model'!F$13 -> 0.026355528 | G30: ='3 Statement Model'!G38/'3 Statement Model'!G$13 -> 0.033770026 | H30: ='3 Statement Model'!H38/'3 Statement Model'!H$13 -> 0.040781952 | I30: ='3 Statement Model'!I38/'3 Statement Model'!I$13 -> 0.053571071 | J30: ='3 Statement Model'!J38/'3 Statement Model'!J$13 -> 0.042 | K30: ='3 Statement Model'!K38/'3 Statement Model'!K$13 -> 0.05 | ... N30: ='3 Statement Model'!N38/'3 Statement Model'!N$13 -> 0.06
B31: ='3 Statement Model'!B39 -> EBT | D31: ='3 Statement Model'!D39/'3 Statement Model'!D$13 -> -0.39739202 | E31: ='3 Statement Model'!E39/'3 Statement Model'!E$13 -> -0.23731061 | F31: ='3 Statement Model'!F39/'3 Statement Model'!F$13 -> -0.0055905387 | G31: ='3 Statement Model'!G39/'3 Statement Model'!G$13 -> 0.11681921 | H31: ='3 Statement Model'!H39/'3 Statement Model'!H$13 -> 0.09397435 | I31: ='3 Statement Model'!I39/'3 Statement Model'!I$13 -> -0.023075049 | J31: ='3 Statement Model'!J39/'3 Statement Model'!J$13 -> 0.012391032 | K31: ='3 Statement Model'!K39/'3 Statement Model'!K$13 -> 0.03720042 | ... N31: ='3 Statement Model'!N39/'3 Statement Model'!N$13 -> 0.029932861
B33: ='3 Statement Model'!B41 -> Less: Taxes | D33: ='3 Statement Model'!D41/'3 Statement Model'!D$13 -> -0.00079525261 | E33: ='3 Statement Model'!E41/'3 Statement Model'!E$13 -> 0.00031472072 | F33: ='3 Statement Model'!F41/'3 Statement Model'!F$13 -> 2.5786804e-05 | G33: ='3 Statement Model'!G41/'3 Statement Model'!G$13 -> -0.0017879871 | H33: ='3 Statement Model'!H41/'3 Statement Model'!H$13 -> 0.0041458908 | I33: ='3 Statement Model'!I41/'3 Statement Model'!I$13 -> 0.005097579 | J33: ='3 Statement Model'!J41/'3 Statement Model'!J$13 -> -0.0030977579 | K33: ='3 Statement Model'!K41/'3 Statement Model'!K$13 -> -0.0093001051 | ... N33: ='3 Statement Model'!N41/'3 Statement Model'!N$13 -> -0.0074832152
B34: ='3 Statement Model'!B42 -> Net Income | D34: ='3 Statement Model'!D42/'3 Statement Model'!D$13 -> -0.39659677 | E34: ='3 Statement Model'!E42/'3 Statement Model'!E$13 -> -0.23762533 | F34: ='3 Statement Model'!F42/'3 Statement Model'!F$13 -> -0.0056163255 | G34: ='3 Statement Model'!G42/'3 Statement Model'!G$13 -> 0.1186072 | H34: ='3 Statement Model'!H42/'3 Statement Model'!H$13 -> 0.089828459 | I34: ='3 Statement Model'!I42/'3 Statement Model'!I$13 -> -0.028172628 | J34: ='3 Statement Model'!J42/'3 Statement Model'!J$13 -> 0.0092932738 | K34: ='3 Statement Model'!K42/'3 Statement Model'!K$13 -> 0.027900315 | ... N34: ='3 Statement Model'!N42/'3 Statement Model'!N$13 -> 0.022449646
B36: ='3 Statement Model'!B51 -> Balance Sheet
B38: ='3 Statement Model'!B53 -> Assets
B39: ='3 Statement Model'!B54 -> Cash | D39: ='3 Statement Model'!D54/'3 Statement Model'!D$74 -> 0.011820473 | E39: ='3 Statement Model'!E54/'3 Statement Model'!E$74 -> 0.022090331 | F39: ='3 Statement Model'!F54/'3 Statement Model'!F$74 -> 0.02142932 | G39: ='3 Statement Model'!G54/'3 Statement Model'!G$74 -> 0.0084561171 | H39: ='3 Statement Model'!H54/'3 Statement Model'!H$74 -> 0.0092633596 | I39: ='3 Statement Model'!I54/'3 Statement Model'!I$74 -> 0.0097344085 | J39: ='3 Statement Model'!J54/'3 Statement Model'!J$74 -> 0.0085840622 | K39: ='3 Statement Model'!K54/'3 Statement Model'!K$74 -> 0.044499139 | ... N39: ='3 Statement Model'!N54/'3 Statement Model'!N$74 -> 0.0089490808
B40: ='3 Statement Model'!B55 -> Bank balances other than cash and cash equivalents, above | D40: ='3 Statement Model'!D55/'3 Statement Model'!D$74 -> 0.24897777 | E40: ='3 Statement Model'!E55/'3 Statement Model'!E$74 -> 0.19809176 | F40: ='3 Statement Model'!F55/'3 Statement Model'!F$74 -> 0.17866737 | G40: ='3 Statement Model'!G55/'3 Statement Model'!G$74 -> 0.1948969 | H40: ='3 Statement Model'!H55/'3 Statement Model'!H$74 -> 0.15443076 | I40: ='3 Statement Model'!I55/'3 Statement Model'!I$74 -> 0.16672831 | J40: ='3 Statement Model'!J55/'3 Statement Model'!J$74 -> 0.15434339 | K40: ='3 Statement Model'!K55/'3 Statement Model'!K$74 -> 0.13565921 | ... N40: ='3 Statement Model'!N55/'3 Statement Model'!N$74 -> 0.10817102
B41: ='3 Statement Model'!B56 -> Inventory | D41: ='3 Statement Model'!D56/'3 Statement Model'!D$74 -> 0.0073498148 | E41: ='3 Statement Model'!E56/'3 Statement Model'!E$74 -> 0.0088781535 | F41: ='3 Statement Model'!F56/'3 Statement Model'!F$74 -> 0.0099893326 | G41: ='3 Statement Model'!G56/'3 Statement Model'!G$74 -> 0.0075987084 | H41: ='3 Statement Model'!H56/'3 Statement Model'!H$74 -> 0.0070811051 | I41: ='3 Statement Model'!I56/'3 Statement Model'!I$74 -> 0.0072410647 | J41: ='3 Statement Model'!J56/'3 Statement Model'!J$74 -> 0.0073619491 | K41: ='3 Statement Model'!K56/'3 Statement Model'!K$74 -> 0.0077578839 | ... N41: ='3 Statement Model'!N56/'3 Statement Model'!N$74 -> 0.010428584
B42: ='3 Statement Model'!B57 -> Trade Receivables | D42: ='3 Statement Model'!D57/'3 Statement Model'!D$74 -> 0.0050864608 | E42: ='3 Statement Model'!E57/'3 Statement Model'!E$74 -> 0.007243346 | F42: ='3 Statement Model'!F57/'3 Statement Model'!F$74 -> 0.0087866417 | G42: ='3 Statement Model'!G57/'3 Statement Model'!G$74 -> 0.0078139727 | H42: ='3 Statement Model'!H57/'3 Statement Model'!H$74 -> 0.0063853388 | I42: ='3 Statement Model'!I57/'3 Statement Model'!I$74 -> 0.0044087555 | J42: ='3 Statement Model'!J57/'3 Statement Model'!J$74 -> 0.0092953903 | K42: ='3 Statement Model'!K57/'3 Statement Model'!K$74 -> 0.009795308 | ... N42: ='3 Statement Model'!N57/'3 Statement Model'!N$74 -> 0.010533924
B43: ='3 Statement Model'!B58 -> Prepaid Expenses | D43: ='3 Statement Model'!D58/'3 Statement Model'!D$74 -> 0.0009080593 | E43: ='3 Statement Model'!E58/'3 Statement Model'!E$74 -> 0.0013758578 | F43: ='3 Statement Model'!F58/'3 Statement Model'!F$74 -> 0.0011318777 | G43: ='3 Statement Model'!G58/'3 Statement Model'!G$74 -> 0.0012514518 | H43: ='3 Statement Model'!H58/'3 Statement Model'!H$74 -> 0.0018455934 | I43: ='3 Statement Model'!I58/'3 Statement Model'!I$74 -> 0.0024992261 | J43: ='3 Statement Model'!J58/'3 Statement Model'!J$74 -> 0.0031349633 | K43: ='3 Statement Model'!K58/'3 Statement Model'!K$74 -> 0.0033035656 | ... N43: ='3 Statement Model'!N58/'3 Statement Model'!N$74 -> 0.0044408388
B44: ='3 Statement Model'!B59 -> Financial Current Assets | D44: ='3 Statement Model'!D59/'3 Statement Model'!D$74 -> 0.18785318 | E44: ='3 Statement Model'!E59/'3 Statement Model'!E$74 -> 0.18350969 | F44: ='3 Statement Model'!F59/'3 Statement Model'!F$74 -> 0.21290915 | G44: ='3 Statement Model'!G59/'3 Statement Model'!G$74 -> 0.21039106 | H44: ='3 Statement Model'!H59/'3 Statement Model'!H$74 -> 0.24482599 | I44: ='3 Statement Model'!I59/'3 Statement Model'!I$74 -> 0.22454433 | J44: ='3 Statement Model'!J59/'3 Statement Model'!J$74 -> 0.23749722 | K44: ='3 Statement Model'!K59/'3 Statement Model'!K$74 -> 0.25027012 | ... N44: ='3 Statement Model'!N59/'3 Statement Model'!N$74 -> 0.33642718
B45: ='3 Statement Model'!B60 -> Other Current Assets | D45: ='3 Statement Model'!D60/'3 Statement Model'!D$74 -> 0.021473687 | E45: ='3 Statement Model'!E60/'3 Statement Model'!E$74 -> 0.018926954 | F45: ='3 Statement Model'!F60/'3 Statement Model'!F$74 -> 0.009012855 | G45: ='3 Statement Model'!G60/'3 Statement Model'!G$74 -> 0.0056309251 | H45: ='3 Statement Model'!H60/'3 Statement Model'!H$74 -> 0.013854036 | I45: ='3 Statement Model'!I60/'3 Statement Model'!I$74 -> 0.010787333 | J45: ='3 Statement Model'!J60/'3 Statement Model'!J$74 -> 0.020356905 | K45: ='3 Statement Model'!K60/'3 Statement Model'!K$74 -> 0.021451724 | ... N45: ='3 Statement Model'!N60/'3 Statement Model'!N$74 -> 0.028836616
B46: ='3 Statement Model'!B61 -> Total Current Assests | D46: ='3 Statement Model'!D61/'3 Statement Model'!D$74 -> 0.48346944 | E46: ='3 Statement Model'!E61/'3 Statement Model'!E$74 -> 0.44011609 | F46: ='3 Statement Model'!F61/'3 Statement Model'!F$74 -> 0.44192655 | G46: ='3 Statement Model'!G61/'3 Statement Model'!G$74 -> 0.43603914 | H46: ='3 Statement Model'!H61/'3 Statement Model'!H$74 -> 0.43768619 | I46: ='3 Statement Model'!I61/'3 Statement Model'!I$74 -> 0.42594342 | J46: ='3 Statement Model'!J61/'3 Statement Model'!J$74 -> 0.44057388 | K46: ='3 Statement Model'!K61/'3 Statement Model'!K$74 -> 0.47273695 | ... N46: ='3 Statement Model'!N61/'3 Statement Model'!N$74 -> 0.50778724
B48: ='3 Statement Model'!B63 -> Plant, Machinery and Equipment | D48: ='3 Statement Model'!D63/'3 Statement Model'!D$74 -> 0.018512071 | E48: ='3 Statement Model'!E63/'3 Statement Model'!E$74 -> 0.017926598 | F48: ='3 Statement Model'!F63/'3 Statement Model'!F$74 -> 0.018779321 | G48: ='3 Statement Model'!G63/'3 Statement Model'!G$74 -> 0.023142737 | H48: ='3 Statement Model'!H63/'3 Statement Model'!H$74 -> 0.023116532 | I48: ='3 Statement Model'!I63/'3 Statement Model'!I$74 -> 0.081521535 | J48: ='3 Statement Model'!J63/'3 Statement Model'!J$74 -> 0.078670911 | K48: ='3 Statement Model'!K63/'3 Statement Model'!K$74 -> 0.073243935 | ... N48: ='3 Statement Model'!N63/'3 Statement Model'!N$74 -> 0.065198846
B49: ='3 Statement Model'!B64 -> Right of use assets | D49: ='3 Statement Model'!D64/'3 Statement Model'!D$74 -> 0.41778605 | E49: ='3 Statement Model'!E64/'3 Statement Model'!E$74 -> 0.44466912 | F49: ='3 Statement Model'!F64/'3 Statement Model'!F$74 -> 0.44848025 | G49: ='3 Statement Model'!G64/'3 Statement Model'!G$74 -> 0.4159624 | H49: ='3 Statement Model'!H64/'3 Statement Model'!H$74 -> 0.42362239 | I49: ='3 Statement Model'!I64/'3 Statement Model'!I$74 -> 0.38274409 | J49: ='3 Statement Model'!J64/'3 Statement Model'!J$74 -> 0.36936039 | K49: ='3 Statement Model'!K64/'3 Statement Model'!K$74 -> 0.34388071 | ... N49: ='3 Statement Model'!N64/'3 Statement Model'!N$74 -> 0.30610897
B50: ='3 Statement Model'!B65 -> Capital Work In Progress | D50: ='3 Statement Model'!D65/'3 Statement Model'!D$74 -> 0.0015412131 | E50: ='3 Statement Model'!E65/'3 Statement Model'!E$74 -> 0.0025959803 | F50: ='3 Statement Model'!F65/'3 Statement Model'!F$74 -> 0 | G50: ='3 Statement Model'!G65/'3 Statement Model'!G$74 -> 1.2161825e-06 | H50: ='3 Statement Model'!H65/'3 Statement Model'!H$74 -> 6.0426351e-06 | I50: ='3 Statement Model'!I65/'3 Statement Model'!I$74 -> 0.00028455443 | J50: ='3 Statement Model'!J65/'3 Statement Model'!J$74 -> 0 | K50: ='3 Statement Model'!K65/'3 Statement Model'!K$74 -> 0 | ... N50: ='3 Statement Model'!N65/'3 Statement Model'!N$74 -> 0
B51: ='3 Statement Model'!B66 -> Other Non-Current Assets | D51: ='3 Statement Model'!D66/'3 Statement Model'!D$74 -> 0.022062429 | E51: ='3 Statement Model'!E66/'3 Statement Model'!E$74 -> 0.02668907 | F51: ='3 Statement Model'!F66/'3 Statement Model'!F$74 -> 0.025302291 | G51: ='3 Statement Model'!G66/'3 Statement Model'!G$74 -> 0.023303273 | H51: ='3 Statement Model'!H66/'3 Statement Model'!H$74 -> 0.020863493 | I51: ='3 Statement Model'!I66/'3 Statement Model'!I$74 -> 0.028215006 | J51: ='3 Statement Model'!J66/'3 Statement Model'!J$74 -> 0.028197318 | K51: ='3 Statement Model'!K66/'3 Statement Model'!K$74 -> 0.027332247 | ... N51: ='3 Statement Model'!N66/'3 Statement Model'!N$74 -> 0.028561475
... B59: ='3 Statement Model'!B74 -> Total Assets | D59: ='3 Statement Model'!D74/'3 Statement Model'!D$74 -> 1 | E59: ='3 Statement Model'!E74/'3 Statement Model'!E$74 -> 1 | F59: ='3 Statement Model'!F74/'3 Statement Model'!F$74 -> 1 | G59: ='3 Statement Model'!G74/'3 Statement Model'!G$74 -> 1 | H59: ='3 Statement Model'!H74/'3 Statement Model'!H$74 -> 1 | I59: ='3 Statement Model'!I74/'3 Statement Model'!I$74 -> 1 | J59: ='3 Statement Model'!J74/'3 Statement Model'!J$74 -> 1 | K59: ='3 Statement Model'!K74/'3 Statement Model'!K$74 -> 1 | ... N59: ='3 Statement Model'!N74/'3 Statement Model'!N$74 -> 1
B62: ='3 Statement Model'!B77 -> Liability and Shareholder's Equity
B63: ='3 Statement Model'!B78 -> Trade Payables | D63: ='3 Statement Model'!D78/'3 Statement Model'!D$99 -> 0.036034552 | E63: ='3 Statement Model'!E78/'3 Statement Model'!E$99 -> 0.068573582 | F63: ='3 Statement Model'!F78/'3 Statement Model'!F$99 -> 0.054233544 | G63: ='3 Statement Model'!G78/'3 Statement Model'!G$99 -> 0.038402179 | H63: ='3 Statement Model'!H78/'3 Statement Model'!H$99 -> 0.036045182 | I63: ='3 Statement Model'!I78/'3 Statement Model'!I$99 -> 0.036694286 | J63: ='3 Statement Model'!J78/'3 Statement Model'!J$99 -> 0.036809746 | K63: ='3 Statement Model'!K78/'3 Statement Model'!K$99 -> 0.03878942 | ... N63: ='3 Statement Model'!N78/'3 Statement Model'!N$99 -> 0.043452435
B64: ='3 Statement Model'!B79 -> Provision | D64: ='3 Statement Model'!D79/'3 Statement Model'!D$99 -> 7.1449887e-05 | E64: ='3 Statement Model'!E79/'3 Statement Model'!E$99 -> 6.692398e-05 | F64: ='3 Statement Model'!F79/'3 Statement Model'!F$99 -> 5.1985963e-05 | G64: ='3 Statement Model'!G79/'3 Statement Model'!G$99 -> 0.0071633151 | H64: ='3 Statement Model'!H79/'3 Statement Model'!H$99 -> 0.015078964 | I64: ='3 Statement Model'!I79/'3 Statement Model'!I$99 -> 0.019271761 | J64: ='3 Statement Model'!J79/'3 Statement Model'!J$99 -> 0.020356905 | K64: ='3 Statement Model'!K79/'3 Statement Model'!K$99 -> 0.021451724 | ... N64: ='3 Statement Model'!N79/'3 Statement Model'!N$99 -> 0.01922441
B65: ='3 Statement Model'!B80 -> Other Current Liability | D65: ='3 Statement Model'!D80/'3 Statement Model'!D$99 -> 0.037359232 | E65: ='3 Statement Model'!E80/'3 Statement Model'!E$99 -> 0.016541189 | F65: ='3 Statement Model'!F80/'3 Statement Model'!F$99 -> 0.0048952321 | G65: ='3 Statement Model'!G80/'3 Statement Model'!G$99 -> 0.079458069 | H65: ='3 Statement Model'!H80/'3 Statement Model'!H$99 -> 0.072275959 | I65: ='3 Statement Model'!I80/'3 Statement Model'!I$99 -> 0.064452681 | J65: ='3 Statement Model'!J80/'3 Statement Model'!J$99 -> 0.064412277 | K65: ='3 Statement Model'!K80/'3 Statement Model'!K$99 -> 0.061300958 | ... N65: ='3 Statement Model'!N80/'3 Statement Model'!N$99 -> 0.060626956
B66: ='3 Statement Model'!B81 -> Financial Liability | D66: ='3 Statement Model'!D81/'3 Statement Model'!D$99 -> 0.21364101 | E66: ='3 Statement Model'!E81/'3 Statement Model'!E$99 -> 0.24809318 | F66: ='3 Statement Model'!F81/'3 Statement Model'!F$99 -> 0.21344672 | G66: ='3 Statement Model'!G81/'3 Statement Model'!G$99 -> 0.16317034 | H66: ='3 Statement Model'!H81/'3 Statement Model'!H$99 -> 0.10480951 | I66: ='3 Statement Model'!I81/'3 Statement Model'!I$99 -> 0.097635992 | J66: ='3 Statement Model'!J81/'3 Statement Model'!J$99 -> 0.094998889 | K66: ='3 Statement Model'!K81/'3 Statement Model'!K$99 -> 0.10010805 | ... N66: ='3 Statement Model'!N81/'3 Statement Model'!N$99 -> 0.13457087
B67: ='3 Statement Model'!B82 -> Current tax liabilities (net) | D67: ='3 Statement Model'!D82/'3 Statement Model'!D$99 -> 0.041633589 | E67: ='3 Statement Model'!E82/'3 Statement Model'!E$99 -> 0.073070239 | F67: ='3 Statement Model'!F82/'3 Statement Model'!F$99 -> 0.085889463 | G67: ='3 Statement Model'!G82/'3 Statement Model'!G$99 -> 3.7701658e-05 | H67: ='3 Statement Model'!H82/'3 Statement Model'!H$99 -> 2.6760241e-05 | I67: ='3 Statement Model'!I82/'3 Statement Model'!I$99 -> 3.1617159e-05 | J67: ='3 Statement Model'!J82/'3 Statement Model'!J$99 -> 2.8724853e-05 | K67: ='3 Statement Model'!K82/'3 Statement Model'!K$99 -> 2.5312362e-05 | ... N67: ='3 Statement Model'!N82/'3 Statement Model'!N$99 -> 1.9872839e-05
B68: ='3 Statement Model'!B83 -> Deferred incentives | D68: ='3 Statement Model'!D83/'3 Statement Model'!D$99 -> 0.0011057311 | E68: ='3 Statement Model'!E83/'3 Statement Model'!E$99 -> 0.0010357117 | F68: ='3 Statement Model'!F83/'3 Statement Model'!F$99 -> 0.00080453178 | G68: ='3 Statement Model'!G83/'3 Statement Model'!G$99 -> 0.00057890288 | H68: ='3 Statement Model'!H83/'3 Statement Model'!H$99 -> 0.00022271427 | I68: ='3 Statement Model'!I83/'3 Statement Model'!I$99 -> 3.5293573e-05 | J68: ='3 Statement Model'!J83/'3 Statement Model'!J$99 -> 2.8724853e-05 | K68: ='3 Statement Model'!K83/'3 Statement Model'!K$99 -> 2.5312362e-05 | ... N68: ='3 Statement Model'!N83/'3 Statement Model'!N$99 -> 1.9872839e-05
B69: ='3 Statement Model'!B84 -> Other financial liabilities | D69: ='3 Statement Model'!D84/'3 Statement Model'!D$99 -> 0.10971739 | E69: ='3 Statement Model'!E84/'3 Statement Model'!E$99 -> 0.080344871 | F69: ='3 Statement Model'!F84/'3 Statement Model'!F$99 -> 0.043775003 | G69: ='3 Statement Model'!G84/'3 Statement Model'!G$99 -> 0.085751814 | H69: ='3 Statement Model'!H84/'3 Statement Model'!H$99 -> 0.066920457 | I69: ='3 Statement Model'!I84/'3 Statement Model'!I$99 -> 0.063278435 | J69: ='3 Statement Model'!J84/'3 Statement Model'!J$99 -> 0.061070714 | K69: ='3 Statement Model'!K84/'3 Statement Model'!K$99 -> 0.064355173 | ... N69: ='3 Statement Model'!N84/'3 Statement Model'!N$99 -> 0.076897642
B70: ='3 Statement Model'!B85 -> Total Current Liability | D70: ='3 Statement Model'!D85/'3 Statement Model'!D$99 -> 0.43956295 | E70: ='3 Statement Model'!E85/'3 Statement Model'!E$99 -> 0.48772569 | F70: ='3 Statement Model'!F85/'3 Statement Model'!F$99 -> 0.40309648 | G70: ='3 Statement Model'!G85/'3 Statement Model'!G$99 -> 0.37456233 | H70: ='3 Statement Model'!H85/'3 Statement Model'!H$99 -> 0.29537954 | I70: ='3 Statement Model'!I85/'3 Statement Model'!I$99 -> 0.28140007 | J70: ='3 Statement Model'!J85/'3 Statement Model'!J$99 -> 0.27770598 | K70: ='3 Statement Model'!K85/'3 Statement Model'!K$99 -> 0.28605595 | ... N70: ='3 Statement Model'!N85/'3 Statement Model'!N$99 -> 0.33481206
B73: ='3 Statement Model'!B87 -> Financial liabilities | D73: ='3 Statement Model'!D87/'3 Statement Model'!D$99 -> 0.47994445 | E73: ='3 Statement Model'!E87/'3 Statement Model'!E$99 -> 0.55425131 | F73: ='3 Statement Model'!F87/'3 Statement Model'!F$99 -> 0.54461226 | G73: ='3 Statement Model'!G87/'3 Statement Model'!G$99 -> 0.46048927 | H73: ='3 Statement Model'!H87/'3 Statement Model'!H$99 -> 0.47191513 | I73: ='3 Statement Model'!I87/'3 Statement Model'!I$99 -> 0.47404047 | J73: ='3 Statement Model'!J87/'3 Statement Model'!J$99 -> 0.45220952 | K73: ='3 Statement Model'!K87/'3 Statement Model'!K$99 -> 0.41841173 | ... N73: ='3 Statement Model'!N87/'3 Statement Model'!N$99 -> 0.35885643
B74: ='3 Statement Model'!B88 -> Other financial liabilities | D74: ='3 Statement Model'!D88/'3 Statement Model'!D$99 -> 0.060507764 | E74: ='3 Statement Model'!E88/'3 Statement Model'!E$99 -> 0.071999846 | F74: ='3 Statement Model'!F88/'3 Statement Model'!F$99 -> 0.13319476 | G74: ='3 Statement Model'!G88/'3 Statement Model'!G$99 -> 0.11230594 | H74: ='3 Statement Model'!H88/'3 Statement Model'!H$99 -> 0.13051401 | I74: ='3 Statement Model'!I88/'3 Statement Model'!I$99 -> 0.16846137 | J74: ='3 Statement Model'!J88/'3 Statement Model'!J$99 -> 0.18999778 | K74: ='3 Statement Model'!K88/'3 Statement Model'!K$99 -> 0.2002161 | ... N74: ='3 Statement Model'!N88/'3 Statement Model'!N$99 -> 0.16340749
B75: ='3 Statement Model'!B89 -> Provisions | D75: ='3 Statement Model'!D89/'3 Statement Model'!D$99 -> 0.012828785 | E75: ='3 Statement Model'!E89/'3 Statement Model'!E$99 -> 0.012829736 | F75: ='3 Statement Model'!F89/'3 Statement Model'!F$99 -> 0.022586752 | G75: ='3 Statement Model'!G89/'3 Statement Model'!G$99 -> 0.027122086 | H75: ='3 Statement Model'!H89/'3 Statement Model'!H$99 -> 0.020785802 | I75: ='3 Statement Model'!I89/'3 Statement Model'!I$99 -> 0.024337859 | J75: ='3 Statement Model'!J89/'3 Statement Model'!J$99 -> 0.026533748 | K75: ='3 Statement Model'!K89/'3 Statement Model'!K$99 -> 0.02805787 | ... N75: ='3 Statement Model'!N89/'3 Statement Model'!N$99 -> 0.038064986
B76: ='3 Statement Model'!B90 -> Other non-current liabilities | D76: ='3 Statement Model'!D90/'3 Statement Model'!D$99 -> 0.00056188971 | E76: ='3 Statement Model'!E90/'3 Statement Model'!E$99 -> 0.00074580205 | F76: ='3 Statement Model'!F90/'3 Statement Model'!F$99 -> 0.00076385226 | G76: ='3 Statement Model'!G90/'3 Statement Model'!G$99 -> 0.00087200287 | H76: ='3 Statement Model'!H90/'3 Statement Model'!H$99 -> 0.00049463285 | I76: ='3 Statement Model'!I90/'3 Statement Model'!I$99 -> 0.00038308232 | J76: ='3 Statement Model'!J90/'3 Statement Model'!J$99 -> 0.00067856349 | K76: ='3 Statement Model'!K90/'3 Statement Model'!K$99 -> 0.00071505748 | ... N76: ='3 Statement Model'!N90/'3 Statement Model'!N$99 -> 0.00096122052
B77: ='3 Statement Model'!B91 -> Non controlling interest | D77: ='3 Statement Model'!D91/'3 Statement Model'!D$99 -> 0 | E77: ='3 Statement Model'!E91/'3 Statement Model'!E$99 -> 0 | F77: ='3 Statement Model'!F91/'3 Statement Model'!F$99 -> 0 | G77: ='3 Statement Model'!G91/'3 Statement Model'!G$99 -> 0 | H77: ='3 Statement Model'!H91/'3 Statement Model'!H$99 -> 0 | I77: ='3 Statement Model'!I91/'3 Statement Model'!I$99 -> 0.00011985109 | J77: ='3 Statement Model'!J91/'3 Statement Model'!J$99 -> 0 | K77: ='3 Statement Model'!K91/'3 Statement Model'!K$99 -> 0 | ... N77: ='3 Statement Model'!N91/'3 Statement Model'!N$99 -> 0
B78: ='3 Statement Model'!B92 -> Deferred incentives | D78: ='3 Statement Model'!D92/'3 Statement Model'!D$99 -> 0.0040191026 | E78: ='3 Statement Model'!E92/'3 Statement Model'!E$99 -> 0.0027288057 | F78: ='3 Statement Model'!F92/'3 Statement Model'!F$99 -> 0.0013151806 | G78: ='3 Statement Model'!G92/'3 Statement Model'!G$99 -> 0.00036728712 | H78: ='3 Statement Model'!H92/'3 Statement Model'!H$99 -> 4.1435212e-05 | I78: ='3 Statement Model'!I92/'3 Statement Model'!I$99 -> 0 | J78: ='3 Statement Model'!J92/'3 Statement Model'!J$99 -> 0 | K78: ='3 Statement Model'!K92/'3 Statement Model'!K$99 -> 0 | ... N78: ='3 Statement Model'!N92/'3 Statement Model'!N$99 -> 0
B79: ='3 Statement Model'!B93 -> Total Non-Current Liability | D79: ='3 Statement Model'!D93/'3 Statement Model'!D$99 -> 0.55786199 | E79: ='3 Statement Model'!E93/'3 Statement Model'!E$99 -> 0.6425555 | F79: ='3 Statement Model'!F93/'3 Statement Model'!F$99 -> 0.70247281 | G79: ='3 Statement Model'!G93/'3 Statement Model'!G$99 -> 0.60115659 | H79: ='3 Statement Model'!H93/'3 Statement Model'!H$99 -> 0.62375101 | I79: ='3 Statement Model'!I93/'3 Statement Model'!I$99 -> 0.66734264 | J79: ='3 Statement Model'!J93/'3 Statement Model'!J$99 -> 0.66941961 | K79: ='3 Statement Model'!K93/'3 Statement Model'!K$99 -> 0.64740076 | ... N79: ='3 Statement Model'!N93/'3 Statement Model'!N$99 -> 0.56129013
B81: ='3 Statement Model'!B95 -> Equity share capital | D81: ='3 Statement Model'!D95/'3 Statement Model'!D$99 -> 0.0089407594 | E81: ='3 Statement Model'!E95/'3 Statement Model'!E$99 -> 0.0083819239 | F81: ='3 Statement Model'!F95/'3 Statement Model'!F$99 -> 0.0065159402 | G81: ='3 Statement Model'!G95/'3 Statement Model'!G$99 -> 0.0046944645 | H81: ='3 Statement Model'!H95/'3 Statement Model'!H$99 -> 0.0033355346 | I81: ='3 Statement Model'!I95/'3 Statement Model'!I$99 -> 0.0028426032 | J81: ='3 Statement Model'!J95/'3 Statement Model'!J$99 -> 0.0025825647 | K81: ='3 Statement Model'!K95/'3 Statement Model'!K$99 -> 0.0022757579 | ... N81: ='3 Statement Model'!N95/'3 Statement Model'!N$99 -> 0.0017867068
B82: ='3 Statement Model'!B96 -> Other equity | D82: ='3 Statement Model'!D96/'3 Statement Model'!D$99 -> -0.0063657064 | E82: ='3 Statement Model'!E96/'3 Statement Model'!E$99 -> -0.13866311 | F82: ='3 Statement Model'!F96/'3 Statement Model'!F$99 -> -0.11208523 | G82: ='3 Statement Model'!G96/'3 Statement Model'!G$99 -> 0.01958662 | H82: ='3 Statement Model'!H96/'3 Statement Model'!H$99 -> 0.077533914 | I82: ='3 Statement Model'!I96/'3 Statement Model'!I$99 -> 0.048414694 | J82: ='3 Statement Model'!J96/'3 Statement Model'!J$99 -> 0.050291843 | K82: ='3 Statement Model'!K96/'3 Statement Model'!K$99 -> 0.064267538 | ... N82: ='3 Statement Model'!N96/'3 Statement Model'!N$99 -> 0.10211111
B83: ='3 Statement Model'!B97 -> Total Shareholder's Equity | D83: ='3 Statement Model'!D97/'3 Statement Model'!D$99 -> 0.002575053 | E83: ='3 Statement Model'!E97/'3 Statement Model'!E$99 -> -0.13028119 | F83: ='3 Statement Model'!F97/'3 Statement Model'!F$99 -> -0.10556929 | G83: ='3 Statement Model'!G97/'3 Statement Model'!G$99 -> 0.024281084 | H83: ='3 Statement Model'!H97/'3 Statement Model'!H$99 -> 0.080869449 | I83: ='3 Statement Model'!I97/'3 Statement Model'!I$99 -> 0.051257297 | J83: ='3 Statement Model'!J97/'3 Statement Model'!J$99 -> 0.052874408 | K83: ='3 Statement Model'!K97/'3 Statement Model'!K$99 -> 0.066543296 | ... N83: ='3 Statement Model'!N97/'3 Statement Model'!N$99 -> 0.10389781
B85: ='3 Statement Model'!B99 -> Total Liability and Shareholder's Equity | D85: ='3 Statement Model'!D99/'3 Statement Model'!D$99 -> 1 | E85: ='3 Statement Model'!E99/'3 Statement Model'!E$99 -> 1 | F85: ='3 Statement Model'!F99/'3 Statement Model'!F$99 -> 1 | G85: ='3 Statement Model'!G99/'3 Statement Model'!G$99 -> 1 | H85: ='3 Statement Model'!H99/'3 Statement Model'!H$99 -> 1 | I85: ='3 Statement Model'!I99/'3 Statement Model'!I$99 -> 1 | J85: ='3 Statement Model'!J99/'3 Statement Model'!J$99 -> 1 | K85: ='3 Statement Model'!K99/'3 Statement Model'!K$99 -> 1 | ... N85: ='3 Statement Model'!N99/'3 Statement Model'!N$99 -> 1

Sheet Ratio Analysis
B2: ='Control Sheet'!B2 -> InterGlobe Aviation
B3: Ratio Analysis
H5: Current Case | I5: 1
D8: Actual | E8: Actual | K8: Explicit Forecast Period
B9: In INR Crores unless stated otherwise | E9: 2021 | F9: =E9+1 -> 2022 | G9: =F9+1 -> 2023 | H9: =G9+1 -> 2024 | I9: =H9+1 -> 2025 | J9: =I9+1 -> 2026 | K9: =J9+1 -> 2027 | L9: =K9+1 -> 2028 | M9: =L9+1 -> 2029 | ... O9: =N9+1 -> 2031
B11: Liquidity Ratio
B13: Current Assets | E13: ='3 Statement Model'!D61 -> 208139.17 | F13: ='3 Statement Model'!E61 -> 202288.79 | G13: ='3 Statement Model'!F61 -> 261487.14 | H13: ='3 Statement Model'!G61 -> 358531 | I13: ='3 Statement Model'!H61 -> 507031 | J13: ='3 Statement Model'!I61 -> 579292 | K13: ='3 Statement Model'!J61 -> 659522.15 | L13: ='3 Statement Model'!K61 -> 803073.57 | ... O13: ='3 Statement Model'!N61 -> 1098728.4
B14: Current Liability | E14: ='3 Statement Model'!D85 -> 189236.92 | F14: ='3 Statement Model'!E85 -> 224171.4 | G14: ='3 Statement Model'!F85 -> 238511.46 | H14: ='3 Statement Model'!G85 -> 307982 | I14: ='3 Statement Model'!H85 -> 342178 | J14: ='3 Statement Model'!I85 -> 382710 | K14: ='3 Statement Model'!J85 -> 415715.16 | L14: ='3 Statement Model'!K85 -> 485944.6 | ... O14: ='3 Statement Model'!N85 -> 724452.04
B15: Liquidity Ratio | E15: =E13/E14 -> 1.0998867 | F15: =F13/F14 -> 0.90238447 | G15: =G13/G14 -> 1.0963295 | H15: =H13/H14 -> 1.1641297 | I15: =I13/I14 -> 1.4817756 | J15: =J13/J14 -> 1.5136579 | K15: =K13/K14 -> 1.586476 | L15: =L13/L14 -> 1.6526031 | ... O15: =O13/O14 -> 1.5166337
B17: Current Assets | E17: ='3 Statement Model'!D61 -> 208139.17 | F17: ='3 Statement Model'!E61 -> 202288.79 | G17: ='3 Statement Model'!F61 -> 261487.14 | H17: ='3 Statement Model'!G61 -> 358531 | I17: ='3 Statement Model'!H61 -> 507031 | J17: ='3 Statement Model'!I61 -> 579292 | K17: ='3 Statement Model'!J61 -> 659522.15 | L17: ='3 Statement Model'!K61 -> 803073.57 | ... O17: ='3 Statement Model'!N61 -> 1098728.4
B18: Inventory | E18: ='3 Statement Model'!D56 -> 3164.18 | F18: ='3 Statement Model'!E56 -> 4080.63 | G18: ='3 Statement Model'!F56 -> 5910.67 | H18: ='3 Statement Model'!G56 -> 6248 | I18: ='3 Statement Model'!H56 -> 8203 | J18: ='3 Statement Model'!I56 -> 9848 | K18: ='3 Statement Model'!J56 -> 11020.554 | L18: ='3 Statement Model'!K56 -> 13178.897 | ... O18: ='3 Statement Model'!N56 -> 22564.925
B19: Prepaid Expenses | E19: ='3 Statement Model'!D58 -> 390.93 | F19: ='3 Statement Model'!E58 -> 632.38 | G19: ='3 Statement Model'!F58 -> 669.73 | H19: ='3 Statement Model'!G58 -> 1029 | I19: ='3 Statement Model'!H58 -> 2138 | J19: ='3 Statement Model'!I58 -> 3399 | K19: ='3 Statement Model'!J58 -> 4692.9194 | L19: ='3 Statement Model'!K58 -> 5612.0136 | ... O19: ='3 Statement Model'!N58 -> 9608.8974
B20: Current Liability | E20: ='3 Statement Model'!D85 -> 189236.92 | F20: ='3 Statement Model'!E85 -> 224171.4 | G20: ='3 Statement Model'!F85 -> 238511.46 | H20: ='3 Statement Model'!G85 -> 307982 | I20: ='3 Statement Model'!H85 -> 342178 | J20: ='3 Statement Model'!I85 -> 382710 | K20: ='3 Statement Model'!J85 -> 415715.16 | L20: ='3 Statement Model'!K85 -> 485944.6 | ... O20: ='3 Statement Model'!N85 -> 724452.04
B21: Quick Ratio (Acid Ratio) | E21: =(E17-E18-E19)/E20 -> 1.0811001 | F21: =(F17-F18-F19)/F20 -> 0.88136033 | G21: =(G17-G18-G19)/G20 -> 1.06874 | H21: =(H17-H18-H19)/H20 -> 1.1405017 | I21: =(I17-I18-I19)/I20 -> 1.4515545 | J21: =(J17-J18-J19)/J20 -> 1.4790442 | K21: =(K17-K18-K19)/K20 -> 1.5486774 | L21: =(L17-L18-L19)/L20 -> 1.6139343 | ... O21: =(O17-O18-O19)/O20 -> 1.4722224
B23: Inventory Days | E23: ='Schedule Sheet'!D141 -> 12.223591 | F23: ='Schedule Sheet'!E141 -> 7.6613441 | G23: ='Schedule Sheet'!F141 -> 5.544663 | H23: ='Schedule Sheet'!G141 -> 5.6177362 | I23: ='Schedule Sheet'!H141 -> 6.2143552 | J23: ='Schedule Sheet'!I141 -> 4 | K23: ='Schedule Sheet'!J141 -> 6 | L23: ='Schedule Sheet'!K141 -> 6 | ... O23: ='Schedule Sheet'!N141 -> 6
B24: Debtor Days | E24: ='Schedule Sheet'!D135 -> 5.4592572 | F24: ='Schedule Sheet'!E135 -> 4.6861763 | G24: ='Schedule Sheet'!F135 -> 3.4853503 | H24: ='Schedule Sheet'!G135 -> 3.4034523 | I24: ='Schedule Sheet'!H135 -> 3.3413467 | J24: ='Schedule Sheet'!I135 -> 5 | K24: ='Schedule Sheet'!J135 -> 5 | L24: ='Schedule Sheet'!K135 -> 5 | ... O24: ='Schedule Sheet'!N135 -> 4
B25: Creditor Days | E25: ='Schedule Sheet'!D162 -> 59.929622 | F25: ='Schedule Sheet'!E162 -> 59.175121 | G25: ='Schedule Sheet'!F162 -> 30.102785 | H25: ='Schedule Sheet'!G162 -> 28.390787 | I25: ='Schedule Sheet'!H162 -> 31.633136 | J25: ='Schedule Sheet'!I162 -> 32.293927 | K25: ='Schedule Sheet'!J162 -> 30 | L25: ='Schedule Sheet'!K162 -> 30 | ... O25: ='Schedule Sheet'!N162 -> 25
B26: Cash Conversion Days | E26: =E23+E24-E25 -> -42.246774 | F26: =F23+F24-F25 -> -46.827601 | G26: =G23+G24-G25 -> -21.072771 | H26: =H23+H24-H25 -> -19.369599 | I26: =I23+I24-I25 -> -22.077434 | J26: =J23+J24-J25 -> -23.293927 | K26: =K23+K24-K25 -> -19 | L26: =L23+L24-L25 -> -19 | ... O26: =O23+O24-O25 -> -15
B28: Leverage Ratios (Solvency Ratios)
B30: Total Debt | E30: ='3 Statement Model'!D87+'3 Statement Model'!D81 -> 298596.54 | F30: ='3 Statement Model'!E87+'3 Statement Model'!E81 -> 368778.37 | G30: ='3 Statement Model'!F87+'3 Statement Model'!F81 -> 448542.13 | H30: ='3 Statement Model'!G87+'3 Statement Model'!G81 -> 512801 | I30: ='3 Statement Model'!H87+'3 Statement Model'!H81 -> 668098 | J30: ='3 Statement Model'!I87+'3 Statement Model'!I81 -> 777492 | K30: ='3 Statement Model'!J87+'3 Statement Model'!J81 -> 819149.93 | L30: ='3 Statement Model'!K87+'3 Statement Model'!K81 -> 880848.28 | ... O30: ='3 Statement Model'!N87+'3 Statement Model'!N81 -> 1067656.9
B31: Total Equity | E31: ='3 Statement Model'!D95+'3 Statement Model'!D96 -> 1108.59 | F31: ='3 Statement Model'!E95+'3 Statement Model'!E96 -> -59880.62 | G31: ='3 Statement Model'!F95+'3 Statement Model'!F96 -> -62465.16 | H31: ='3 Statement Model'!G95+'3 Statement Model'!G96 -> 19965 | I31: ='3 Statement Model'!H95+'3 Statement Model'!H96 -> 93682 | J31: ='3 Statement Model'!I95+'3 Statement Model'!I96 -> 69711 | K31: ='3 Statement Model'!J95+'3 Statement Model'!J96 -> 79150.954 | L31: ='3 Statement Model'!K95+'3 Statement Model'!K96 -> 113042.07 | ... O31: ='3 Statement Model'!N95+'3 Statement Model'!N96 -> 224809.65
B32: Debt to Equity | E32: =E30/E31 -> 269.34804 | F32: =F30/F31 -> -6.1585596 | G32: =G30/G31 -> -7.1806769 | H32: =H30/H31 -> 25.684999 | I32: =I30/I31 -> 7.1315514 | J32: =J30/J31 -> 11.153075 | K32: =K30/K31 -> 10.349211 | L32: =L30/L31 -> 7.7922166 | ... O32: =O30/O31 -> 4.7491597
B34: Total Debt | E34: ='3 Statement Model'!D87+'3 Statement Model'!D81 -> 298596.54 | F34: ='3 Statement Model'!E87+'3 Statement Model'!E81 -> 368778.37 | G34: ='3 Statement Model'!F87+'3 Statement Model'!F81 -> 448542.13 | H34: ='3 Statement Model'!G87+'3 Statement Model'!G81 -> 512801 | I34: ='3 Statement Model'!H87+'3 Statement Model'!H81 -> 668098 | J34: ='3 Statement Model'!I87+'3 Statement Model'!I81 -> 777492 | K34: ='3 Statement Model'!J87+'3 Statement Model'!J81 -> 819149.93 | L34: ='3 Statement Model'!K87+'3 Statement Model'!K81 -> 880848.28 | ... O34: ='3 Statement Model'!N87+'3 Statement Model'!N81 -> 1067656.9
B35: Total Assets | E35: ='3 Statement Model'!D74 -> 430511.53 | F35: ='3 Statement Model'!E74 -> 459625.98 | G35: ='3 Statement Model'!F74 -> 591698.19 | H35: ='3 Statement Model'!G74 -> 822245 | I35: ='3 Statement Model'!H74 -> 1158435 | J35: ='3 Statement Model'!I74 -> 1360021 | K35: ='3 Statement Model'!J74 -> 1496961.5 | L35: ='3 Statement Model'!K74 -> 1698774.7 | ... O35: ='3 Statement Model'!N74 -> 2163757.3
B36: Debt to Assets Ratio | E36: =E34/E35 -> 0.69358547 | F36: =F34/F35 -> 0.80234448 | G36: =G34/G35 -> 0.75805899 | H36: =H34/H35 -> 0.62365961 | I36: =I34/I35 -> 0.57672463 | J36: =J34/J35 -> 0.57167647 | K36: =K34/K35 -> 0.54720841 | L36: =L34/L35 -> 0.51851978 | ... O36: =O34/O35 -> 0.4934273
B38: Total Equity | E38: ='3 Statement Model'!D97 -> 1108.59 | F38: ='3 Statement Model'!E97 -> -59880.62 | G38: ='3 Statement Model'!F97 -> -62465.16 | H38: ='3 Statement Model'!G97 -> 19965 | I38: ='3 Statement Model'!H97 -> 93682 | J38: ='3 Statement Model'!I97 -> 69711 | K38: ='3 Statement Model'!J97 -> 79150.954 | L38: ='3 Statement Model'!K97 -> 113042.07 | ... O38: ='3 Statement Model'!N97 -> 224809.65
B39: Total Assets | E39: ='3 Statement Model'!D74 -> 430511.53 | F39: ='3 Statement Model'!E74 -> 459625.98 | G39: ='3 Statement Model'!F74 -> 591698.19 | H39: ='3 Statement Model'!G74 -> 822245 | I39: ='3 Statement Model'!H74 -> 1158435 | J39: ='3 Statement Model'!I74 -> 1360021 | K39: ='3 Statement Model'!J74 -> 1496961.5 | L39: ='3 Statement Model'!K74 -> 1698774.7 | ... O39: ='3 Statement Model'!N74 -> 2163757.3
B40: Equity Ratio | E40: =E38/E39 -> 0.002575053 | F40: =F38/F39 -> -0.13028119 | G40: =G38/G39 -> -0.10556929 | H40: =H38/H39 -> 0.024281084 | I40: =I38/I39 -> 0.080869449 | J40: =J38/J39 -> 0.051257297 | K40: =K38/K39 -> 0.052874408 | L40: =L38/L39 -> 0.066543296 | ... O40: =O38/O39 -> 0.10389781
B42: Profitability/Margin Ratios
B44: Gross Profit | E44: ='3 Statement Model'!D15 -> 51922.97 | F44: ='3 Statement Model'!E15 -> 64900.83 | G44: ='3 Statement Model'!F15 -> 155370.63 | H44: ='3 Statement Model'!G15 -> 283093 | I44: ='3 Statement Model'!H15 -> 326226 | J44: ='3 Statement Model'!I15 -> 285571 | K44: ='3 Statement Model'!J15 -> 345366.37 | L44: ='3 Statement Model'!K15 -> 413005.33 | ... O44: ='3 Statement Model'!N15 -> 707148.3
B45: Total Sales | E45: ='3 Statement Model'!D13 -> 146406.31 | F45: ='3 Statement Model'!E13 -> 259309.27 | G45: ='3 Statement Model'!F13 -> 544464.53 | H45: ='3 Statement Model'!G13 -> 689043 | I45: ='3 Statement Model'!H13 -> 808029 | J45: ='3 Statement Model'!I13 -> 849619 | K45: ='3 Statement Model'!J13 -> 1015783.4 | L45: ='3 Statement Model'!K13 -> 1214721.6 | ... O45: ='3 Statement Model'!N13 -> 2079847.9
B46: Gross Margin Ratios | E46: =E44/E45 -> 0.35464981 | F46: =F44/F45 -> 0.25028349 | G46: =G44/G45 -> 0.2853641 | H46: =H44/H45 -> 0.41084954 | I46: =I44/I45 -> 0.40373056 | J46: =J44/J45 -> 0.33611654 | K46: =K44/K45 -> 0.34 | L46: =L44/L45 -> 0.34 | ... O46: =O44/O45 -> 0.34
B48: EBITDA | E48: ='3 Statement Model'!D25 -> -136.05 | F48: ='3 Statement Model'!E25 -> 5473.33 | G48: ='3 Statement Model'!F25 -> 64953.5 | H48: ='3 Statement Model'!G25 -> 163175 | I48: ='3 Statement Model'!H25 -> 180583 | J48: ='3 Statement Model'!I25 -> 119834 | K48: ='3 Statement Model'!J25 -> 152367.51 | L48: ='3 Statement Model'!K25 -> 182208.23 | ... O48: ='3 Statement Model'!N25 -> 207984.79
B49: Total Sales | E49: ='3 Statement Model'!D13 -> 146406.31 | F49: ='3 Statement Model'!E13 -> 259309.27 | G49: ='3 Statement Model'!F13 -> 544464.53 | H49: ='3 Statement Model'!G13 -> 689043 | I49: ='3 Statement Model'!H13 -> 808029 | J49: ='3 Statement Model'!I13 -> 849619 | K49: ='3 Statement Model'!J13 -> 1015783.4 | L49: ='3 Statement Model'!K13 -> 1214721.6 | ... O49: ='3 Statement Model'!N13 -> 2079847.9
B50: EBITDA Margin Ratios | E50: =E48/E49 -> -0.00092926323 | F50: =F48/F49 -> 0.021107344 | G50: =G48/G49 -> 0.11929795 | H50: =H48/H49 -> 0.23681396 | I50: =I48/I49 -> 0.22348579 | J50: =J48/J49 -> 0.1410444 | K50: =K48/K49 -> 0.15 | L50: =L48/L49 -> 0.15 | ... O50: =O48/O49 -> 0.1
B52: EBIT | E52: ='3 Statement Model'!D31 -> -47130.51 | F52: ='3 Statement Model'!E31 -> -45212.67 | G52: ='3 Statement Model'!F31 -> 13923.81 | H52: ='3 Statement Model'!G31 -> 98918 | I52: ='3 Statement Model'!H31 -> 93781 | J52: ='3 Statement Model'!I31 -> 11752 | K52: ='3 Statement Model'!J31 -> 33789.378 | L52: ='3 Statement Model'!K31 -> 52452.003 | ... O52: ='3 Statement Model'!N31 -> 41077.777
B53: Total Sales | E53: ='3 Statement Model'!D13 -> 146406.31 | F53: ='3 Statement Model'!E13 -> 259309.27 | G53: ='3 Statement Model'!F13 -> 544464.53 | H53: ='3 Statement Model'!G13 -> 689043 | I53: ='3 Statement Model'!H13 -> 808029 | J53: ='3 Statement Model'!I13 -> 849619 | K53: ='3 Statement Model'!J13 -> 1015783.4 | L53: ='3 Statement Model'!K13 -> 1214721.6 | ... O53: ='3 Statement Model'!N13 -> 2079847.9
B54: EBIT Margin Ratios | E54: =E52/E53 -> -0.32191584 | F54: =F52/F53 -> -0.17435809 | G54: =G52/G53 -> 0.025573401 | H54: =H52/H53 -> 0.14355853 | I54: =I52/I53 -> 0.11606143 | J54: =J52/J53 -> 0.013832082 | K54: =K52/K53 -> 0.033264352 | L54: =L52/L53 -> 0.043180269 | ... O54: =O52/O53 -> 0.019750375
B56: Net Income | E56: ='3 Statement Model'!D42 -> -58064.27 | F56: ='3 Statement Model'!E42 -> -61618.45 | G56: ='3 Statement Model'!F42 -> -3057.89 | H56: ='3 Statement Model'!G42 -> 81725.46 | I56: ='3 Statement Model'!H42 -> 72584 | J56: ='3 Statement Model'!I42 -> -23936 | K56: ='3 Statement Model'!J42 -> 9439.9536 | L56: ='3 Statement Model'!K42 -> 33891.114 | ... O56: ='3 Statement Model'!N42 -> 46691.849
B57: Total Sales | E57: ='3 Statement Model'!D13 -> 146406.31 | F57: ='3 Statement Model'!E13 -> 259309.27 | G57: ='3 Statement Model'!F13 -> 544464.53 | H57: ='3 Statement Model'!G13 -> 689043 | I57: ='3 Statement Model'!H13 -> 808029 | J57: ='3 Statement Model'!I13 -> 849619 | K57: ='3 Statement Model'!J13 -> 1015783.4 | L57: ='3 Statement Model'!K13 -> 1214721.6 | ... O57: ='3 Statement Model'!N13 -> 2079847.9
B58: Net Profit Margin | E58: =E56/E57 -> -0.39659677 | F58: =F56/F57 -> -0.23762533 | G58: =G56/G57 -> -0.0056163255 | H58: =H56/H57 -> 0.1186072 | I58: =I56/I57 -> 0.089828459 | J58: =J56/J57 -> -0.028172628 | K58: =K56/K57 -> 0.0092932738 | L58: =L56/L57 -> 0.027900315 | ... O58: =O56/O57 -> 0.022449646
B60: Net Profit | E60: ='3 Statement Model'!D42 -> -58064.27 | F60: ='3 Statement Model'!E42 -> -61618.45 | G60: ='3 Statement Model'!F42 -> -3057.89 | H60: ='3 Statement Model'!G42 -> 81725.46 | I60: ='3 Statement Model'!H42 -> 72584 | J60: ='3 Statement Model'!I42 -> -23936 | K60: ='3 Statement Model'!J42 -> 9439.9536 | L60: ='3 Statement Model'!K42 -> 33891.114 | ... O60: ='3 Statement Model'!N42 -> 46691.849
B61: Total Assets | E61: ='3 Statement Model'!D74 -> 430511.53 | F61: ='3 Statement Model'!E74 -> 459625.98 | G61: ='3 Statement Model'!F74 -> 591698.19 | H61: ='3 Statement Model'!G74 -> 822245 | I61: ='3 Statement Model'!H74 -> 1158435 | J61: ='3 Statement Model'!I74 -> 1360021 | K61: ='3 Statement Model'!J74 -> 1496961.5 | L61: ='3 Statement Model'!K74 -> 1698774.7 | ... O61: ='3 Statement Model'!N74 -> 2163757.3
B62: Return on Assets | E62: =E60/E61 -> -0.13487274 | F62: =F60/F61 -> -0.13406216 | G62: =G60/G61 -> -0.0051679894 | H62: =H60/H61 -> 0.099393076 | I62: =I60/I61 -> 0.062656947 | J62: =J60/J61 -> -0.017599728 | K62: =K60/K61 -> 0.0063060763 | L62: =L60/L61 -> 0.019950329 | ... O62: =O60/O61 -> 0.02157906
B64: Net Profit | E64: ='3 Statement Model'!D42 -> -58064.27 | F64: ='3 Statement Model'!E42 -> -61618.45 | G64: ='3 Statement Model'!F42 -> -3057.89 | H64: ='3 Statement Model'!G42 -> 81725.46 | I64: ='3 Statement Model'!H42 -> 72584 | J64: ='3 Statement Model'!I42 -> -23936 | K64: ='3 Statement Model'!J42 -> 9439.9536 | L64: ='3 Statement Model'!K42 -> 33891.114 | ... O64: ='3 Statement Model'!N42 -> 46691.849
B65: Total Equity | E65: ='3 Statement Model'!D97 -> 1108.59 | F65: ='3 Statement Model'!E97 -> -59880.62 | G65: ='3 Statement Model'!F97 -> -62465.16 | H65: ='3 Statement Model'!G97 -> 19965 | I65: ='3 Statement Model'!H97 -> 93682 | J65: ='3 Statement Model'!I97 -> 69711 | K65: ='3 Statement Model'!J97 -> 79150.954 | L65: ='3 Statement Model'!K97 -> 113042.07 | ... O65: ='3 Statement Model'!N97 -> 224809.65
B66: Return on Equity | E66: =E64/E65 -> -52.376686 | F66: =F64/F65 -> 1.0290216 | G66: =G64/G65 -> 0.048953529 | H66: =H64/H65 -> 4.0934365 | I66: =I64/I65 -> 0.77479132 | J66: =J64/J65 -> -0.34336045 | K66: =K64/K65 -> 0.11926519 | L66: =L64/L65 -> 0.29980975 | ... O66: =O64/O65 -> 0.20769504
B68: Efficiency Ratios
B70: Revenue (Sales) | E70: ='3 Statement Model'!D13 -> 146406.31 | F70: ='3 Statement Model'!E13 -> 259309.27 | G70: ='3 Statement Model'!F13 -> 544464.53 | H70: ='3 Statement Model'!G13 -> 689043 | I70: ='3 Statement Model'!H13 -> 808029 | J70: ='3 Statement Model'!I13 -> 849619 | K70: ='3 Statement Model'!J13 -> 1015783.4 | L70: ='3 Statement Model'!K13 -> 1214721.6 | ... O70: ='3 Statement Model'!N13 -> 2079847.9
B71: Total Assets | E71: ='3 Statement Model'!D74 -> 430511.53 | F71: ='3 Statement Model'!E74 -> 459625.98 | G71: ='3 Statement Model'!F74 -> 591698.19 | H71: ='3 Statement Model'!G74 -> 822245 | I71: ='3 Statement Model'!H74 -> 1158435 | J71: ='3 Statement Model'!I74 -> 1360021 | K71: ='3 Statement Model'!J74 -> 1496961.5 | L71: ='3 Statement Model'!K74 -> 1698774.7 | ... O71: ='3 Statement Model'!N74 -> 2163757.3
B72: Assets Turnover Ratios | E72: =E70/E71 -> 0.34007524 | F72: =F70/F71 -> 0.56417453 | G72: =G70/G71 -> 0.92017272 | H72: =H70/H71 -> 0.83800206 | I72: =I70/I71 -> 0.69751777 | J72: =J70/J71 -> 0.62471021 | K72: =K70/K71 -> 0.67856349 | L72: =L70/L71 -> 0.71505748 | ... O72: =O70/O71 -> 0.96122052
B74: Change In Revenue | F74: ='3 Statement Model'!E13-'3 Statement Model'!D13 -> 112902.96 | G74: ='3 Statement Model'!F13-'3 Statement Model'!E13 -> 285155.26 | H74: ='3 Statement Model'!G13-'3 Statement Model'!F13 -> 144578.47 | I74: ='3 Statement Model'!H13-'3 Statement Model'!G13 -> 118986 | J74: ='3 Statement Model'!I13-'3 Statement Model'!H13 -> 41590 | K74: ='3 Statement Model'!J13-'3 Statement Model'!I13 -> 166164.43 | L74: ='3 Statement Model'!K13-'3 Statement Model'!J13 -> 198938.12 | M74: ='3 Statement Model'!L13-'3 Statement Model'!K13 -> 238207.52 | ... O74: ='3 Statement Model'!N13-'3 Statement Model'!M13 -> 341655.1
B75: Change In Total Assets | F75: ='3 Statement Model'!E74-'3 Statement Model'!D74 -> 29114.45 | G75: ='3 Statement Model'!F74-'3 Statement Model'!E74 -> 132072.21 | H75: ='3 Statement Model'!G74-'3 Statement Model'!F74 -> 230546.81 | I75: ='3 Statement Model'!H74-'3 Statement Model'!G74 -> 336190 | J75: ='3 Statement Model'!I74-'3 Statement Model'!H74 -> 201586 | K75: ='3 Statement Model'!J74-'3 Statement Model'!I74 -> 136940.51 | L75: ='3 Statement Model'!K74-'3 Statement Model'!J74 -> 201813.18 | M75: ='3 Statement Model'!L74-'3 Statement Model'!K74 -> 112574.96 | ... O75: ='3 Statement Model'!N74-'3 Statement Model'!M74 -> 206462.4
B76: Reinvestment Ratios | F76: =F74/F75 -> 3.8779012 | G76: =G74/G75 -> 2.159086 | H76: =H74/H75 -> 0.62711113 | I76: =I74/I75 -> 0.35392486 | J76: =J74/J75 -> 0.20631393 | K76: =K74/K75 -> 1.2134059 | L76: =L74/L75 -> 0.98575388 | M76: =M74/M75 -> 2.1159902 | ... O76: =O74/O75 -> 1.6548054
B78: COGS | E78: ='3 Statement Model'!D14*-1 -> 94483.34 | F78: ='3 Statement Model'!E14*-1 -> 194408.44 | G78: ='3 Statement Model'!F14*-1 -> 389093.9 | H78: ='3 Statement Model'!G14*-1 -> 405950 | I78: ='3 Statement Model'!H14*-1 -> 481803 | J78: ='3 Statement Model'!I14*-1 -> 564048 | K78: ='3 Statement Model'!J14*-1 -> 670417.06 | L78: ='3 Statement Model'!K14*-1 -> 801716.23 | ... O78: ='3 Statement Model'!N14*-1 -> 1372699.6
B79: Total Inventory | E79: ='3 Statement Model'!D56 -> 3164.18 | F79: ='3 Statement Model'!E56 -> 4080.63 | G79: ='3 Statement Model'!F56 -> 5910.67 | H79: ='3 Statement Model'!G56 -> 6248 | I79: ='3 Statement Model'!H56 -> 8203 | J79: ='3 Statement Model'!I56 -> 9848 | K79: ='3 Statement Model'!J56 -> 11020.554 | L79: ='3 Statement Model'!K56 -> 13178.897 | ... O79: ='3 Statement Model'!N56 -> 22564.925
B80: Inventory Turnover Ratios | E80: =E78/E79 -> 29.860292 | F80: =F78/F79 -> 47.641771 | G80: =G78/G79 -> 65.829068 | H80: =H78/H79 -> 64.972791 | I80: =I78/I79 -> 58.734975 | J80: =J78/J79 -> 57.275386 | K80: =K78/K79 -> 60.833333 | L80: =L78/L79 -> 60.833333 | ... O80: =O78/O79 -> 60.833333
B82: Coverage Ratios
B84: Total Debt | E84: ='3 Statement Model'!D81+'3 Statement Model'!D87 -> 298596.54 | F84: ='3 Statement Model'!E81+'3 Statement Model'!E87 -> 368778.37 | G84: ='3 Statement Model'!F81+'3 Statement Model'!F87 -> 448542.13 | H84: ='3 Statement Model'!G81+'3 Statement Model'!G87 -> 512801 | I84: ='3 Statement Model'!H81+'3 Statement Model'!H87 -> 668098 | J84: ='3 Statement Model'!I81+'3 Statement Model'!I87 -> 777492 | K84: ='3 Statement Model'!J81+'3 Statement Model'!J87 -> 819149.93 | L84: ='3 Statement Model'!K81+'3 Statement Model'!K87 -> 880848.28 | ... O84: ='3 Statement Model'!N81+'3 Statement Model'!N87 -> 1067656.9
B85: EBITDA | E85: ='3 Statement Model'!D25 -> -136.05 | F85: ='3 Statement Model'!E25 -> 5473.33 | G85: ='3 Statement Model'!F25 -> 64953.5 | H85: ='3 Statement Model'!G25 -> 163175 | I85: ='3 Statement Model'!H25 -> 180583 | J85: ='3 Statement Model'!I25 -> 119834 | K85: ='3 Statement Model'!J25 -> 152367.51 | L85: ='3 Statement Model'!K25 -> 182208.23 | ... O85: ='3 Statement Model'!N25 -> 207984.79
B86: Debt to EBITDA Coverage Ratio | E86: =E84/E85 -> -2194.7559 | F86: =F84/F85 -> 67.377332 | G86: =G84/G85 -> 6.9055883 | H86: =H84/H85 -> 3.1426444 | I86: =I84/I85 -> 3.6996727 | J86: =J84/J85 -> 6.4880752 | K86: =K84/K85 -> 5.3761455 | L86: =L84/L85 -> 4.8342946 | ... O86: =O84/O85 -> 5.1333413
B88: EBIT | E88: ='3 Statement Model'!D31 -> -47130.51 | F88: ='3 Statement Model'!E31 -> -45212.67 | G88: ='3 Statement Model'!F31 -> 13923.81 | H88: ='3 Statement Model'!G31 -> 98918 | I88: ='3 Statement Model'!H31 -> 93781 | J88: ='3 Statement Model'!I31 -> 11752 | K88: ='3 Statement Model'!J31 -> 33789.378 | L88: ='3 Statement Model'!K31 -> 52452.003 | ... O88: ='3 Statement Model'!N31 -> 41077.777
B89: Interest | E89: ='3 Statement Model'!D36 -> 21419.83 | F89: ='3 Statement Model'!E36 -> 23580.15 | G89: ='3 Statement Model'!F36 -> 31317.31 | H89: ='3 Statement Model'!G36 -> 41693.54 | I89: ='3 Statement Model'!H36 -> 50800 | J89: ='3 Statement Model'!I36 -> 58908 | K89: ='3 Statement Model'!J36 -> 63865.677 | L89: ='3 Statement Model'!K36 -> 67999.928 | ... O89: ='3 Statement Model'!N36 -> 103612.85
B90: Debt Repayment | E90: ='3 Statement Model'!D188*-1 -> 19967.92 | F90: ='3 Statement Model'!E188*-1 -> 24893.18 | G90: ='3 Statement Model'!F188*-1 -> 41137.71 | H90: ='3 Statement Model'!G188*-1 -> 62422 | I90: ='3 Statement Model'!H188*-1 -> 69011 | J90: ='3 Statement Model'!I188*-1 -> 161802 | K90: ='3 Statement Model'!J188*-1 -> 161802 | L90: ='3 Statement Model'!K188*-1 -> 161802 | ... O90: ='3 Statement Model'!N188*-1 -> 161802
B91: Debt Service Coverage Ratio | E91: =E88/SUM(E89:E90) -> -1.1387551 | F91: =F88/SUM(F89:F90) -> -0.93273291 | G91: =G88/SUM(G89:G90) -> 0.19217178 | H91: =H88/SUM(H89:H90) -> 0.95007911 | I91: =I88/SUM(I89:I90) -> 0.78274115 | J91: =J88/SUM(J89:J90) -> 0.053246341 | K91: =K88/SUM(K89:K90) -> 0.14973069 | L91: =L88/SUM(L89:L90) -> 0.22824875 | ... O91: =O88/SUM(O89:O90) -> 0.15476819
B93: EBIT | E93: ='3 Statement Model'!D31 -> -47130.51 | F93: ='3 Statement Model'!E31 -> -45212.67 | G93: ='3 Statement Model'!F31 -> 13923.81 | H93: ='3 Statement Model'!G31 -> 98918 | I93: ='3 Statement Model'!H31 -> 93781 | J93: ='3 Statement Model'!I31 -> 11752 | K93: ='3 Statement Model'!J31 -> 33789.378 | L93: ='3 Statement Model'!K31 -> 52452.003 | ... O93: ='3 Statement Model'!N31 -> 41077.777
B94: Interest Expenses | E94: ='3 Statement Model'!D36 -> 21419.83 | F94: ='3 Statement Model'!E36 -> 23580.15 | G94: ='3 Statement Model'!F36 -> 31317.31 | H94: ='3 Statement Model'!G36 -> 41693.54 | I94: ='3 Statement Model'!H36 -> 50800 | J94: ='3 Statement Model'!I36 -> 58908 | K94: ='3 Statement Model'!J36 -> 63865.677 | L94: ='3 Statement Model'!K36 -> 67999.928 | ... O94: ='3 Statement Model'!N36 -> 103612.85
B95: Interest Coverage Ratio | E95: =E93/E94 -> -2.2003214 | F95: =F93/F94 -> -1.9174038 | G95: =G93/G94 -> 0.44460428 | H95: =H93/H94 -> 2.3725018 | I95: =I93/I94 -> 1.8460827 | J95: =J93/J94 -> 0.19949752 | K95: =K93/K94 -> 0.52906944 | L95: =L93/L94 -> 0.7713538 | ... O95: =O93/O94 -> 0.39645445

Sheet Input
B3: Please provide the below inputs | E3: Yes
E4: No
B5: Name of the Company | C5: ='Control Sheet'!B2 -> InterGlobe Aviation | D5: Financial firm
D6: Non-financial firm
B7: WACC Inputs
B8: Country | C8: India
B9: Local Currency 10Yr. Government Bond Yield | C9: 0.06783
B10: =C8&"'s" & " Moodys Sovereign Rating" -> India's Moodys Sovereign Rating | C10: =VLOOKUP(C8,'Damodaran Data'!B3:C83,2,FALSE) -> Baa3
B11: Credit default spread as per Dr. Damodaran | C11: =VLOOKUP(Input!C8,'Damodaran Data'!B3:E83,4,FALSE) -> 0.0102
B12: Implied US Equity Risk Premium | C12: 0.0428
B13: Asset Beta | C13: =WACC!C81 -> 0.33116883
B14: Asset Beta Variation (+/-) | C14: 0.06
B15: Debt to Equity | C15: 11.1
B16: Debt to Capital (Gearing) | C16: =Assumptions!J124 -> 0.9177163
B17: Marginal Tax Rate | C17: 0.3
B18: Company Credit Rating Available? | C18: Yes
B19: Company is non-financial or financial firm? | C19: Non-financial firm
B20: Provide Credit Rating | C20: A1/A+
B21: Interest Coverage Ratio | C21: ='3 Statement Model'!I31/'3 Statement Model'!I36 -> 0.19949752
B22: ICR-Based Corporate Default Spread | C22: =IF(C19="Non-financial firm", VLOOKUP(C21,'Damodaran Data'!M7:P21,4,TRUE), VLOOKUP(Input!C21,'Damodaran Data'!H7:K21,4,TRUE)) -> 0.1261
B23: Small Size Premium | C23: 0
B24: Asset Specific Risk Premium | C24: 0

Sheet WACC
B2: ='Control Sheet'!B2 -> InterGlobe Aviation
B3: Weighted Average Cost of Capital
B5: Particulars | D5: Low | E5: Mid | F5: High | H5: Risk Free Rate
B6: Risk Free Rate | D6: =Input!$C$9-Input!$C$11 -> 0.05763 | E6: =Input!$C$9-Input!$C$11 -> 0.05763 | F6: =Input!$C$9-Input!$C$11 -> 0.05763 | H6: ="We have considered " &TEXT(E6,"0.0%")& " as the risk free rate in estimating the cost of equity of IndiGo " &TEXT(E11,"0.0%")& " . The risk free rate of India is calculated by considering local currency 10Yr. Government bond yield adjusted for default spread of India." -> We have considered 5.8% as the risk free rate in estimating the cost of equity of IndiGo 27.0% . The risk free rate of India is calculated by considering local currency 10Yr. Government bond yield adjusted for default spread of India.
B7: Equity Risk Premium | D7: =Input!$C$12+Input!$C$11 -> 0.053 | E7: =Input!$C$12+Input!$C$11 -> 0.053 | F7: =Input!$C$12+Input!$C$11 -> 0.053
B8: Asset Beta | D8: =Input!C13-Input!C14 -> 0.27116883 | E8: =Input!C13 -> 0.33116883 | F8: =Input!C13+Input!C14 -> 0.39116883
B9: D/E Ratio | D9: =Input!C15 -> 11.1 | E9: =D9 -> 11.1 | F9: =E9 -> 11.1
B10: Equity Beta | D10: =D8*(1+(D9*(1-Input!C17))) -> 2.3781506 | E10: =E8*(1+(E9*(1-Input!D17))) -> 4.0071429 | F10: =F8*(1+(F9*(1-Input!E17))) -> 4.7331429 | H10: Asset Beta
B11: CAPM Cost of Equity | D11: =D6+D7*D10 -> 0.18367198 | E11: =E6+E7*E10 -> 0.27000857 | F11: =F6+F7*F10 -> 0.30848657 | H11: ="We have estimated an asset beta range of " &TEXT(D8,"0.0%")& " to " &TEXT(F8,"0.0%")& " , with a mid point of " &TEXT(E8,"0.0%")& " based on observe median of 5 year monthly asset beta of benchmark listed companies adjusted for blume effect." -> We have estimated an asset beta range of 27.1% to 39.1% , with a mid point of 33.1% based on observe median of 5 year monthly asset beta of benchmark listed companies adjusted for blume effect.
B13: Small Size Premium | D13: =Input!$C$23 -> 0 | E13: =Input!$C$23 -> 0 | F13: =Input!$C$23 -> 0
B14: Asset Specific Premium | D14: =Input!$C$24 -> 0 | E14: =Input!$C$24 -> 0 | F14: =Input!$C$24 -> 0
B15: Modified Cost of Equity | D15: =D11+D13+D14 -> 0.18367198 | E15: =E11+E13+E14 -> 0.27000857 | F15: =F11+F13+F14 -> 0.30848657 | H15: Equity Risk Premium (ERP)
H16: ="An ERP of " &TEXT(D7,"0.0%")& " has been adopted for IndiGo based on the estimated market risk premium for India. The ERP represents the additional return investors require for investing in equities over the risk free rate." -> An ERP of 5.3% has been adopted for IndiGo based on the estimated market risk premium for India. The ERP represents the additional return investors require for investing in equities over the risk free rate.
B17: Pre Tax Cost of Debt | D17: =Input!$C$9+(IF(Input!$C$18="No",Input!$C$22,VLOOKUP(Input!$C$20,'Damodaran Data'!$O$7:$P$21,2,FALSE))) -> 0.07483 | E17: =Input!$C$9+(IF(Input!$C$18="No",Input!$C$22,VLOOKUP(Input!$C$20,'Damodaran Data'!$O$7:$P$21,2,FALSE))) -> 0.07483 | F17: =Input!$C$9+(IF(Input!$C$18="No",Input!$C$22,VLOOKUP(Input!$C$20,'Damodaran Data'!$O$7:$P$21,2,FALSE))) -> 0.07483
B18: Marginal Tax Rate | D18: =Input!$C$17 -> 0.3 | E18: =Input!$C$17 -> 0.3 | F18: =Input!$C$17 -> 0.3
B19: Post Tax Cost of Debt | D19: =D17*(1-D18) -> 0.052381 | E19: =E17*(1-E18) -> 0.052381 | F19: =F17*(1-F18) -> 0.052381
H20: Cost of debt
B21: Capital Gearing (D/D+E) | D21: =Input!$C$16 -> 0.9177163 | E21: =Input!$C$16 -> 0.9177163 | F21: =Input!$C$16 -> 0.9177163 | H21: ="For the purpose of assessing the cost of debt, we have used country's risk free rate, country's default spread and corporate default spread based on company's debt rating and interest coverage ratio. " -> For the purpose of assessing the cost of debt, we have used country's risk free rate, country's default spread and corporate default spread based on company's debt rating and interest coverage ratio.
B22: Weighted Average Cost of Capital | D22: =(D19*D21)+(D11*(1-D21)) -> 0.063184108 | E22: =(E21*E19)+(E11*(1-E21)) -> 0.070288202 | F22: =(F21*F19)+(F11*(1-F21)) -> 0.073454315
B23: Weighted Average Cost of Capital (Rounded) | D23: =ROUNDUP(D22,2) -> 0.07 | E23: =ROUNDUP(E22,2) -> 0.08 | F23: =ROUNDUP(F22,2) -> 0.08
B25: 1. Tax rate considered as the Marginal tax rate in India | H25: Small Size Premium & Asset Specific Premium
B26: 2. Asset Beta is considered as median of 5 years beta odf comps adjusted for blume effect. | H26: Emperically small sized assets have exceed the returns as compared to lare sized assets. We have used the study on size premium conducted by Incwert which is based on difference between actual returns and CAPM expected returns arranged in decline basis market capitalization of Indian Companies.
B27: 3. Equity Beta = Asset Beta*(1+(1-Tax Rate%)*Debt/Equity)
B38: =B2 -> InterGlobe Aviation
B39: Beta Analysis - 2 Years Weekly | J39: 0.25
B41: Comparable Company | D41: Ticker | E41: No. of weekly observation | F41: Market Cap | G41: Assset Beta | H41: 2 Year Avg. D/E | I41: Equity Beta | J41: 2 Year Avg. D/E+D | L41: Considered? | M41: Narroee Set
B43: Wizz Air Holdings | D43: WIZZ | E43: 104 | F43: 1.5 | G43: =I43/(1+H43*(1-$J$39)) -> 0.082456517 | H43: 14.19 | I43: 0.96 | J43: 0.9186 | L43: Yes | M43: =IF(L43="Yes","True","False") -> True
B44: Ryanair Holdings | D44: RYAAY | E44: 104 | F44: 34.87 | G44: =I44/(1+H44*(1-$J$39)) -> 0.86192469 | H44: 0.26 | I44: 1.03 | J44: 0.2022 | L44: Yes | M44: =IF(L44="Yes","True","False") -> True
B45: Singapore Airlines | D45: C6L / SIA | E45: 104 | F45: 18.54 | G45: =I45/(1+H45*(1-$J$39)) -> 0.82467532 | H45: 0.72 | I45: 1.27 | J45: 0.4165 | L45: Yes | M45: =IF(L45="Yes","True","False") -> True
B47: Average Broad Set | G47: =AVERAGE(G43:G45) -> 0.58968551 | H47: =AVERAGE(H43:H45) -> 5.0566667 | I47: =AVERAGE(I43:I45) -> 1.0866667 | J47: =AVERAGE(J43:J45) -> 0.51243333
B48: Median Broad Set | G48: =MEDIAN(G43:G45) -> 0.82467532 | H48: =MEDIAN(H43:H45) -> 0.72 | I48: =MEDIAN(I43:I45) -> 1.03 | J48: =MEDIAN(J43:J45) -> 0.4165
B50: Average Considered Set | G50: {=AVERAGE(IF(M43:$M$45,G43:G45))} -> 0.58968551 | H50: {=AVERAGE(IF(M43:$M$45,H43:H45))} -> 5.0566667 | I50: {=AVERAGE(IF(M43:$N$45,I43:I45))} -> 1.0866667 | J50: {=AVERAGE(IF(M43:$O$45,J43:J45))} -> 0.51243333
B51: Median Considered Set | G51: {=MEDIAN(IF(M43:$M$45,G43:G45))} -> 0.82467532 | H51: {=MEDIAN(IF(M43:$M$45,H43:H45))} -> 0.72 | I51: {=MEDIAN(IF($M43:N$45,I43:I45))} -> 1.03 | J51: {=MEDIAN(IF($M43:O$45,J43:J45))} -> 0.4165
B53: Beta Analysis - 5 Years Monthly
B55: Comparable Company | D55: Ticker | E55: No. of weekly observation | F55: Market Cap | G55: Assset Beta | H55: 2 Year Avg. D/E | I55: Equity Beta | J55: 2 Year Avg. D/E+D | L55: Considered? | M55: Narroee Set
B57: Wizz Air Holdings | D57: WIZZ | E57: 60 | F57: 1.5 | G57: =I57/(1+H57*(1-$J$39)) -> 0.1520292 | H57: 14.19 | I57: 1.77 | J57: 0.9186 | L57: Yes | M57: =IF(L57="Yes","True","False") -> True
B58: Ryanair Holdings | D58: RYAAY | E58: 60 | F58: 34.87 | G58: =I58/(1+H58*(1-$J$39)) -> 0.84518828 | H58: 0.26 | I58: 1.01 | J58: 0.2022 | L58: Yes | M58: =IF(L58="Yes","True","False") -> True
B59: Singapore Airlines | D59: C6L / SIA | E59: 60 | F59: 18.54 | G59: =I59/(1+H59*(1-$J$39)) -> 0.33116883 | H59: 0.72 | I59: 0.51 | J59: 0.4165 | L59: Yes | M59: =IF(L59="Yes","True","False") -> True
B61: Average Broad Set | G61: =AVERAGE(G57:G59) -> 0.44279544 | H61: =AVERAGE(H57:H59) -> 5.0566667 | I61: =AVERAGE(I57:I59) -> 1.0966667 | J61: =AVERAGE(J57:J59) -> 0.51243333
B62: Median Broad Set | G62: =MEDIAN(G57:G59) -> 0.33116883 | H62: =MEDIAN(H57:H59) -> 0.72 | I62: =MEDIAN(I57:I59) -> 1.01 | J62: =MEDIAN(J57:J59) -> 0.4165
B64: Average Considered Set | G64: {=AVERAGE(IF(M$57:$M59,G57:G59))} -> 0.44279544 | H64: {=AVERAGE(IF($M$57:N59,H57:H59))} -> 5.0566667 | I64: {=AVERAGE(IF($M$57:O59,I57:I59))} -> 1.0966667 | J64: {=AVERAGE(IF($M$57:P59,J57:J59))} -> 0.51243333
B65: Median Considered Set | G65: {=MEDIAN(IF(M$57:$M59,G57:G59))} -> 0.33116883 | H65: {=MEDIAN(IF($M$57:N59,H57:H59))} -> 0.72 | I65: {=MEDIAN(IF($M$57:O59,I57:I59))} -> 1.01 | J65: {=MEDIAN(IF($M$57:P59,J57:J59))} -> 0.4165
B67: Blume Beta Analysis - 5 Years Monthly | D67: 2/3 Beta + 1/3 * Material Beta
B69: Comparable Company | D69: Ticker | E69: No. of weekly observation | F69: Market Cap | G69: Assset Beta | H69: 2 Year Avg. D/E | I69: Equity Beta | J69: 2 Year Avg. D/E+D | L69: Considered? | M69: Narroee Set
B71: Wizz Air Holdings | D71: WIZZ | E71: 60 | F71: 1.5 | G71: =I71/(1+H71*(1-$J$39)) -> 0.1520292 | H71: 14.19 | I71: 1.77 | J71: 0.9186 | L71: Yes | M71: =IF(L71="Yes","True","False") -> True
B72: Ryanair Holdings | D72: RYAAY | E72: 60 | F72: 34.87 | G72: =I72/(1+H72*(1-$J$39)) -> 0.84518828 | H72: 0.26 | I72: 1.01 | J72: 0.2022 | L72: Yes | M72: =IF(L72="Yes","True","False") -> True
B73: Singapore Airlines | D73: C6L / SIA | E73: 60 | F73: 18.54 | G73: =I73/(1+H73*(1-$J$39)) -> 0.33116883 | H73: 0.72 | I73: 0.51 | J73: 0.4165 | L73: Yes | M73: =IF(L73="Yes","True","False") -> True
B75: Average Broad Set | G75: =AVERAGE(G71:G73) -> 0.44279544 | H75: =AVERAGE(H71:H73) -> 5.0566667 | I75: =AVERAGE(I71:I73) -> 1.0966667 | J75: =AVERAGE(J71:J73) -> 0.51243333
B76: Median Broad Set | G76: =MEDIAN(G71:G73) -> 0.33116883 | H76: =MEDIAN(H71:H73) -> 0.72 | I76: =MEDIAN(I71:I73) -> 1.01 | J76: =MEDIAN(J71:J73) -> 0.4165
B78: Average Considered Set | G78: {=AVERAGE(IF(M$71:$M73,G71:G73))} -> 0.44279544 | H78: {=AVERAGE(IF($M$71:N73,H71:H73))} -> 5.0566667 | I78: {=AVERAGE(IF($M$71:O73,I71:I73))} -> 1.0966667 | J78: {=AVERAGE(IF($M$71:P73,J71:J73))} -> 0.51243333
B79: Median Considered Set | G79: {=MEDIAN(IF(M$71:$M73,G71:G73))} -> 0.33116883 | H79: {=MEDIAN(IF($M$71:N73,H71:H73))} -> 0.72 | I79: {=MEDIAN(IF($M$71:O73,I71:I73))} -> 1.01 | J79: {=MEDIAN(IF($M$71:P73,J71:J73))} -> 0.4165
B81: Asset Beta - | C81: =G79 -> 0.33116883

Sheet Options Working
B2: Valuing Options or Warrants
B3: Enter the current stock price = | E3: 5334 | J3: Grant Date | K3: No. of options | L3: Exercise Price | M3: Contractual Period | N3: Expected Volatility
B4: Enter the strike price on the option = | E4: 740.76 | I4: 1 | J4: 45232 | K4: 104500 | L4: 10 | M4: 6.67 | N4: 0.405 | O4: 0.0019
B5: Enter the expiration of the option = | E5: 8.04 | I5: 2 | J5: 45383 | K5: 70480 | L5: 10 | M5: 7.25 | N5: 0.405 | O5: 0.0019
B6: Enter the standard deviation in stock prices = | E6: 0.405 | F6: (volatility) | I6: 3 | J6: 45435 | K6: 119500 | L6: 10 | M6: 7.11 | N6: 0.405 | O6: 0.0019
B7: Enter the annualized dividend yield on stock = | E7: 0.0019 | I7: 4 | J7: 45748 | K7: 50141 | L7: 10 | M7: 7.17 | N7: 0.405 | O7: 0.0019
B8: Enter the Risk Free rate = | E8: =WACC!E6 -> 0.05763 | I8: 5 | J8: 45797 | K8: 107000 | L8: 10 | M8: 7.12 | N8: 0.405 | O8: 0.0019
B9: Enter the number of options outstanding = | E9: 0.0296153 | I9: 6 | J9: 45875 | K9: 1500 | L9: 10 | M9: 6.9 | N9: 0.405 | O9: 0.0019
B10: Enter the number of shares outstanding = | E10: 38.6613
K11: Wighted Average | L11: =SUMPRODUCT(L4:L12,$K$4:$K$12)/SUM($K$4:$K$12) -> 10 | M11: =SUMPRODUCT(M4:M12,$K$4:$K$12)/SUM($K$4:$K$12) -> 7.0386077 | N11: =SUMPRODUCT(N4:N12,$K$4:$K$12)/SUM($K$4:$K$12) -> 0.405 | O11: =SUMPRODUCT(O4:O12,$K$4:$K$12)/SUM($K$4:$K$12) -> 0.0019
B12: Do not input any numbers below this line
B13: VALUING OPTIONS WHEN THERE IS DILUTION
B14: Stock Price= | D14: =E3 -> 5334 | E14: # Options issued= | G14: =E9 -> 0.0296153
B15: Strike Price= | D15: =E4 -> 740.76 | E15: # Shares outstanding= | G15: =E10 -> 38.6613
B16: Adjusted S = | D16: =(D14*G15+D27*G14)/(G15+G14) -> 5333.5887 | E16: T.Bond rate= | G16: =E8 -> 0.05763
B17: Adjusted K = | D17: =D15 -> 740.76 | E17: Variance= | G17: =E6^2 -> 0.164025
B18: Expiration (in years) = | D18: =E5 -> 8.04 | E18: Annualized dividend yield= | G18: =E7 -> 0.0019
E19: Div. Adj. interest rate= | G19: =G16-G18 -> 0.05573
B21: d1 = | C21: =(LN(D16/D17)+(G19+(G17/2))*D18)/(((G17)^(0.5))*(D18^0.5)) -> 2.6834069
B22: N (d1) = | C22: =NORMSDIST(C21) -> 0.99635619
B24: d2 = | C24: =C21-((G17^0.5)*(D18^(0.5))) -> 1.5350337
B25: N (d2) = | C25: =NORMSDIST(C24) -> 0.93761223
B27: Value per option = | D27: =((EXP((0-G18)*D18))*D16*C22-D17*(EXP((0-G16)*D18))*C25) -> 4796.6009
B28: Value of all options outstanding = | E28: =D27*E9 -> 142.05277

Sheet DCF Valuation
B2: ='Control Sheet'!B2 -> InterGlobe Aviation
B3: DCF Valuation | M3: Mid Year Conviction
M4: Yes
M5: No
E8: Actual | K8: Explicit Forecast Period
B9: In INR million unless stated otherwise | E9: 2021 | F9: =E9+1 -> 2022 | G9: =F9+1 -> 2023 | H9: =G9+1 -> 2024 | I9: =H9+1 -> 2025 | J9: =I9+1 -> 2026 | K9: =J9+1 -> 2027 | L9: =K9+1 -> 2028 | M9: =L9+1 -> 2029 | ... O9: =N9+1 -> 2031
B11: Free Cash Flow to Firm
B13: EBITDA | E13: ='3 Statement Model'!D25 -> -136.05 | F13: ='3 Statement Model'!E25 -> 5473.33 | G13: ='3 Statement Model'!F25 -> 64953.5 | H13: ='3 Statement Model'!G25 -> 163175 | I13: ='3 Statement Model'!H25 -> 180583 | J13: ='3 Statement Model'!I25 -> 119834 | K13: ='3 Statement Model'!J25 -> 152367.51 | L13: ='3 Statement Model'!K25 -> 182208.23 | ... O13: ='3 Statement Model'!N25 -> 207984.79
B14: Less: Depreciation & Amortization | E14: ='3 Statement Model'!D30 -> -46994.46 | F14: ='3 Statement Model'!E30 -> -50686 | G14: ='3 Statement Model'!F30 -> -51029.69 | H14: ='3 Statement Model'!G30 -> -64257 | I14: ='3 Statement Model'!H30 -> -86802 | J14: ='3 Statement Model'!I30 -> -108082 | K14: ='3 Statement Model'!J30 -> -118578.14 | L14: ='3 Statement Model'!K30 -> -129756.23 | ... O14: ='3 Statement Model'!N30 -> -166907.02
B15: EBIT | E15: =E13+E14 -> -47130.51 | F15: =F13+F14 -> -45212.67 | G15: =G13+G14 -> 13923.81 | H15: =H13+H14 -> 98918 | I15: =I13+I14 -> 93781 | J15: =J13+J14 -> 11752 | K15: =K13+K14 -> 33789.378 | L15: =L13+L14 -> 52452.003 | ... O15: =O13+O14 -> 41077.777
B16: Less: Tax | E16: ='3 Statement Model'!D41 -> -116.43 | F16: ='3 Statement Model'!E41 -> 81.61 | G16: ='3 Statement Model'!F41 -> 14.04 | H16: ='3 Statement Model'!G41 -> -1232 | I16: ='3 Statement Model'!H41 -> 3350 | J16: ='3 Statement Model'!I41 -> 4331 | K16: ='3 Statement Model'!J41 -> -3146.6512 | L16: ='3 Statement Model'!K41 -> -11297.038 | ... O16: ='3 Statement Model'!N41 -> -15563.95
B17: EBIT (1-T) | E17: =E15-E16 -> -47014.08 | F17: =F15-F16 -> -45294.28 | G17: =G15-G16 -> 13909.77 | H17: =H15-H16 -> 100150 | I17: =I15-I16 -> 90431 | J17: =J15-J16 -> 7421 | K17: =K15-K16 -> 36936.029 | L17: =L15-L16 -> 63749.041 | ... O17: =O15-O16 -> 56641.727
B18: Add: Depreciation & Amortization | E18: =E14*-1 -> 46994.46 | F18: =F14*-1 -> 50686 | G18: =G14*-1 -> 51029.69 | H18: =H14*-1 -> 64257 | I18: =I14*-1 -> 86802 | J18: =J14*-1 -> 108082 | K18: =K14*-1 -> 118578.14 | L18: =L14*-1 -> 129756.23 | ... O18: =O14*-1 -> 166907.02
B19: CASH NOPAT | E19: =E17+E18 -> -19.62 | F19: =F17+F18 -> 5391.72 | G19: =G17+G18 -> 64939.46 | H19: =H17+H18 -> 164407 | I19: =I17+I18 -> 177233 | J19: =J17+J18 -> 115503 | K19: =K17+K18 -> 155514.17 | L19: =L17+L18 -> 193505.27 | ... O19: =O17+O18 -> 223548.74
B20: Less: Reinvestments
B21: Change in Working Capital | E21: ='3 Statement Model'!D170*-1 -> 10927.53 | F21: ='3 Statement Model'!E170*-1 -> -7615.53 | G21: ='3 Statement Model'!F170*-1 -> -31326.44 | H21: ='3 Statement Model'!G170*-1 -> -43503 | I21: ='3 Statement Model'!H170*-1 -> -45177 | J21: ='3 Statement Model'!I170*-1 -> -20473 | K21: ='3 Statement Model'!J170*-1 -> 2600.3344 | L21: ='3 Statement Model'!K170*-1 -> -30607.343 | ... O21: ='3 Statement Model'!N170*-1 -> -40048.39
B22: Capex during the year | E22: ='3 Statement Model'!D183 -> -4368.87 | F22: ='3 Statement Model'!E183 -> -3468.81 | G22: ='3 Statement Model'!F183 -> -5698.04 | H22: ='3 Statement Model'!G183 -> -11026 | I22: ='3 Statement Model'!H183 -> -16048 | J22: ='3 Statement Model'!I183 -> -17101 | K22: ='3 Statement Model'!J183 -> -27717.75 | L22: ='3 Statement Model'!K183 -> -29441.831 | ... O22: ='3 Statement Model'!N183 -> -34076.418
B23: Free Cash Flow to Firm | E23: =E19+E21+E22 -> 6539.04 | F23: =F19+F21+F22 -> -5692.62 | G23: =G19+G21+G22 -> 27914.98 | H23: =H19+H21+H22 -> 109878 | I23: =I19+I21+I22 -> 116008 | J23: =J19+J21+J22 -> 77929 | K23: =K19+K21+K22 -> 130396.75 | L23: =L19+L21+L22 -> 133456.1 | ... O23: =O19+O21+O22 -> 149423.93
B25: Discount Period (Year) | C25: Mid Year Conviction? | D25: Yes | K25: =IF(D25="Yes",(K9-J9)/2,K9-J9) -> 0.5 | L25: =K25+1 -> 1.5 | M25: =L25+1 -> 2.5 | N25: =M25+1 -> 3.5 | O25: =N25+1 -> 4.5
B26: Discount Rate (WACC) | C26: =WACC!E23 -> 0.08
B27: Present Value Factor | K27: =1/(1+$C$26)^K25 -> 0.96225045 | L27: =1/(1+$C$26)^L25 -> 0.89097264 | M27: =1/(1+$C$26)^M25 -> 0.82497466 | N27: =1/(1+$C$26)^N25 -> 0.76386543 | O27: =1/(1+$C$26)^O25 -> 0.70728281
B29: Present Value of Free Cash Flow to Firm | K29: =K23*K27 -> 125474.33 | L29: =L23*L27 -> 118905.73 | M29: =M23*M27 -> 120369.87 | N29: =N23*N27 -> 98026.061 | O29: =O23*O27 -> 105684.98
B31: DCF Calculation - Perpetuity Growth
B33: Perpetuity Growth Rate | C33: 0.03
B34: Terminal Year FCFF *(1+PGR) | C34: =O23*(1+C33) -> 153906.65
B35: Terminal Value | C35: =C34/(C26-C33) -> 3078133
B36: Present Value of Terminal Factor | C36: =C35*O27 -> 2177110.6
B37: Present Value of FCFFs | C37: =SUM(K29:O29) -> 568460.97
B38: Enterprise Value | C38: =SUM(C36:C37) -> 2745571.6
B39: Implied Exit Multiple | C39: =C35/O13 -> 14.799799
B40: Implied EV/EBITDA | C40: =C38/O13 -> 13.200828
B41: Less: Debt | C41: ='3 Statement Model'!I81+'3 Statement Model'!I87 -> 777492
B42: Add: Cash | C42: ='3 Statement Model'!I54+'3 Statement Model'!I55 -> 239993
B43: Add: Non Operating Assets | C43: ='3 Statement Model'!N67 -> 139094.34
B44: Equity Value | C44: =C38-C41+C42+C43 -> 2347166.9
B45: Less: Value of Options | C45: ='Options Working'!E28*-1 -> -142.05277
B46: Equity Value for Shareholders | C46: =C44+C45 -> 2347024.8
B48: DCF Calculation - Exit Multiple
B50: Exit Multiple | C50: 16
B51: Terminal Year EBITDA | C51: =O13 -> 207984.79
B52: Terminal Value | C52: =C51*C50 -> 3327756.7
B53: Present Value of Terminal Factor | C53: =C52*O27 -> 2353665.1
B54: Present Value of FCFFs | C54: =C37 -> 568460.97
B55: Enterprose Value | C55: =SUM(C53:C54) -> 2922126.1
B56: Implied Exit Multiple | C56: =C52/O13 -> 16
B57: Implied EV/EBITDA | C57: =C55/O13 -> 14.04971
B58: Less: Debt | C58: =$C$41 -> 777492
B59: Add: Cash | C59: =$C$42 -> 239993
B60: Add: Non Operating Assets | C60: =$C$43 -> 139094.34
B61: Equity Value | C61: =C55-C58+C59++C60 -> 2523721.4
B62: Less: Value of Options | C62: ='Options Working'!E28*-1 -> -142.05277
B63: Equity Value for Shareholders | C63: =C61+C62 -> 2523579.4
B66: Sensitivity Analysis
E68: WACC
C69: Terminal Growth % | D69: =C46 -> 2347024.8 | E69: 0.07 | F69: 0.08 | G69: 0.09 | H69: 0.1 | I69: 0.11
D70: 0.02 | E70: 2430904.1 | F70: 1966558.9 | G70: 1634974.6 | H70: 1386359.7 | I70: 1193053
D71: 0.03 | E71: 3020489.8 | F71: 2347024.8 | G71: 1898109.3 | H71: 1577502.5 | I71: 1337084.4
D72: 0.04 | E72: 4003132.7 | F72: 2917723.7 | G72: 2266497.9 | H72: 1832359.4 | I72: 1522267.7
D73: 0.05 | E73: 5968418.4 | F73: 3868888.5 | G73: 2819080.7 | H73: 2189159.1 | I73: 1769178.7
D74: 0.06 | E74: 11864275 | F74: 5771218.2 | G74: 3740052.2 | H74: 2724358.7 | I74: 2114854.1
E77: WACC
C78: Exit Multiple | D78: =C63 -> 2523579.4 | E78: 0.07 | F78: 0.08 | G78: 0.09 | H78: 0.1 | I78: 0.11
D79: 14 | E79: 2330261.5 | F79: 2229371.2 | G79: 2133345.8 | H79: 2041906.4 | I79: 1954792.5
D80: 15 | E80: 2483654.1 | F80: 2376475.3 | G80: 2274473.6 | H80: 2177351.9 | I80: 2084832.9
D81: 16 | E81: 2637046.8 | F81: 2523579.4 | G81: 2415601.3 | H81: 2312797.4 | I81: 2214873.2
D82: 17 | E82: 2790439.4 | F82: 2670683.4 | G82: 2556729 | H82: 2448242.9 | I82: 2344913.6
D83: 18 | E83: 2943832.1 | F83: 2817787.5 | G83: 2697856.7 | H83: 2583688.3 | I83: 2474954

Sheet Relative Valuation
B2: $m (until stated otherwise)
C4: Market Data | I4: Financial Data | S4: Multiples
I5: 2026 | J5: =I5+1 -> 2027 | K5: =J5+1 -> 2028 | L5: =I5 -> 2026 | M5: =J5 -> 2027 | N5: =K5 -> 2028 | O5: =I5 -> 2026 | P5: =J5 -> 2027 | Q5: =K5 -> 2028 | S5: 2026 | T5: =S5+1 -> 2027 | U5: =T5+1 -> 2028 | V5: =S5 -> 2026 | W5: =T5 -> 2027 | X5: =U5 -> 2028 | Y5: =S5 -> 2026 | Z5: =T5 -> 2027 | AA5: =U5 -> 2028
B6: Relative Valuation | C6: Ticker | D6: Share Price | E6: Market Cap. | F6: Debt | G6: Cash | H6: Enterprice Value | I6: Sales | J6: Sales | K6: Sales | L6: EBITDA | M6: EBITDA | N6: EBITDA | O6: PAT | P6: PAT | Q6: PAT | S6: EV/Sales | T6: EV/Sales | U6: EV/Sales | V6: EV/EBITDA | W6: EV/EBITDA | X6: EV/EBITDA | Y6: Price/Earnings | Z6: Price/Earnings | AA6: Price/Earnings | AB6: EV/Sales
AB7: EV/EBITDA
B8: InterGlobe Aviation | C8: INDIGO | D8: 5315 | E8: 197587 | F8: 77749.2 | G8: 52885 | H8: =E8+F8-G8 -> 222451.2 | I8: ='3 Statement Model'!I13 -> 849619 | J8: ='3 Statement Model'!J13 -> 1015783.4 | K8: ='3 Statement Model'!K13 -> 1214721.6 | L8: ='3 Statement Model'!I25 -> 119834 | M8: ='3 Statement Model'!J25 -> 152367.51 | N8: ='3 Statement Model'!K25 -> 182208.23 | O8: ='3 Statement Model'!I42 -> -23936 | P8: ='3 Statement Model'!J42 -> 9439.9536 | Q8: ='3 Statement Model'!K42 -> 33891.114 | S8: =$H8/I8 -> 0.26182465 | T8: =$H8/J8 -> 0.21899471 | U8: =$H8/K8 -> 0.18312938 | V8: =$H8/L8 -> 1.8563279 | W8: =$H8/M8 -> 1.4599647 | X8: =$H8/N8 -> 1.2208625 | Y8: =$H8/O8 -> -9.2935829 | Z8: =$H8/P8 -> 23.564862 | AA8: =$H8/Q8 -> 6.5637028 | AB8: Price/Earnings
B9: Wizz Air Holdings | C9: WIZZ | D9: 44.87 | E9: 21951 | F9: 6400 | G9: 3791 | H9: =E9+F9-G9 -> 24560 | I9: ='Comparable Companies'!J9 -> 6602.024 | J9: =6600*1.16 -> 7656 | K9: =7564*1.16 -> 8774.24 | L9: ='Comparable Companies'!I11 -> 1350.588 | M9: =1071*1.16 -> 1242.36 | N9: =1541*1.16 -> 1787.56 | O9: ='Comparable Companies'!I20 -> 248.124 | P9: =-405.7*1.16 -> -470.612 | Q9: =56.21*1.16 -> 65.2036 | S9: =$H9/I9 -> 3.7200713 | T9: =$H9/J9 -> 3.2079415 | U9: =$H9/K9 -> 2.7991028 | V9: =$H9/L9 -> 18.184672 | W9: =$H9/M9 -> 19.768827 | X9: =$H9/N9 -> 13.739399 | Y9: =$H9/O9 -> 98.982767 | Z9: =$H9/P9 -> -52.187365 | AA9: =$H9/Q9 -> 376.66632
B10: Ryanair Holdings | C10: RYA | D10: 59.17 | E10: 30671.6 | F10: 17240.6 | G10: 3756.7 | H10: =E10+F10-G10 -> 44155.5 | I10: ='Comparable Companies'!J23 -> 18031.388 | J10: =15942*1.16 -> 18492.72 | K10: =17220*1.16 -> 19975.2 | L10: ='Comparable Companies'!I25 -> 3215.984 | M10: =3545*1.16 -> 4112.2 | N10: =17220*1.16 -> 19975.2 | O10: ='Comparable Companies'!I34 -> 1869.456 | P10: =1809*1.16 -> 2098.44 | Q10: =2085*1.16 -> 2418.6 | S10: =$H10/I10 -> 2.4488131 | T10: =$H10/J10 -> 2.3877234 | U10: =$H10/K10 -> 2.210516 | V10: =$H10/L10 -> 13.730012 | W10: =$H10/M10 -> 10.737683 | X10: =$H10/N10 -> 2.210516 | Y10: =$H10/O10 -> 23.619438 | Z10: =$H10/P10 -> 21.04206 | AA10: =$H10/Q10 -> 18.256636
B11: Singapore Airlines | C11: C6L / SIA | D11: 7.05 | E11: 17400 | F11: 8280 | G11: 6620 | H11: =E11+F11-G11 -> 19060 | I11: ='Comparable Companies'!J37 -> 20522 | J11: 22098 | K11: 22312 | L11: 4916 | M11: 4206 | N11: 4606 | O11: 1184 | P11: 753.3 | Q11: 1189 | S11: =$H11/I11 -> 0.92875938 | T11: =$H11/J11 -> 0.8625215 | U11: =$H11/K11 -> 0.85424883 | V11: =$H11/L11 -> 3.8771359 | W11: =$H11/M11 -> 4.5316215 | X11: =$H11/N11 -> 4.1380808 | Y11: =$H11/O11 -> 16.097973 | Z11: =$H11/P11 -> 25.302005 | AA11: =$H11/Q11 -> 16.030278
B12: High | S12: =MAX(S9:S11) -> 3.7200713 | T12: =MAX(T9:T11) -> 3.2079415 | U12: =MAX(U9:U11) -> 2.7991028 | V12: =MAX(V9:V11) -> 18.184672 | W12: =MAX(W9:W11) -> 19.768827 | X12: =MAX(X9:X11) -> 13.739399 | Y12: =MAX(Y9:Y11) -> 98.982767 | Z12: =MAX(Z9:Z11) -> 25.302005 | AA12: =MAX(AA9:AA11) -> 376.66632
B13: 75th Percentile | S13: =QUARTILE(S9:S11,3) -> 3.0844422 | T13: =QUARTILE(T9:T11,3) -> 2.7978324 | U13: =QUARTILE(U9:U11,3) -> 2.5048094 | V13: =QUARTILE(V9:V11,3) -> 15.957342 | W13: =QUARTILE(W9:W11,3) -> 15.253255 | X13: =QUARTILE(X9:X11,3) -> 8.9387399 | Y13: =QUARTILE(Y9:Y11,3) -> 61.301102 | Z13: =QUARTILE(Z9:Z11,3) -> 23.172032 | AA13: =QUARTILE(AA9:AA11,3) -> 197.46148
B14: Average | S14: =AVERAGE(S9:S11) -> 2.3658813 | T14: =AVERAGE(T9:T11) -> 2.1527288 | U14: =AVERAGE(U9:U11) -> 1.9546226 | V14: =AVERAGE(V9:V11) -> 11.930607 | W14: =AVERAGE(W9:W11) -> 11.679377 | X14: =AVERAGE(X9:X11) -> 6.6959986 | Y14: =AVERAGE(Y9:Y11) -> 46.233393 | Z14: =AVERAGE(Z9:Z11) -> -1.9477667 | AA14: =AVERAGE(AA9:AA11) -> 136.98441
B15: Median | S15: =MEDIAN(S9:S11) -> 2.4488131 | T15: =MEDIAN(T9:T11) -> 2.3877234 | U15: =MEDIAN(U9:U11) -> 2.210516 | V15: =MEDIAN(V9:V11) -> 13.730012 | W15: =MEDIAN(W9:W11) -> 10.737683 | X15: =MEDIAN(X9:X11) -> 4.1380808 | Y15: =MEDIAN(Y9:Y11) -> 23.619438 | Z15: =MEDIAN(Z9:Z11) -> 21.04206 | AA15: =MEDIAN(AA9:AA11) -> 18.256636
B16: 25th Percentile | S16: =QUARTILE(S9:S11,1) -> 1.6887863 | T16: =QUARTILE(T9:T11,1) -> 1.6251224 | U16: =QUARTILE(U9:U11,1) -> 1.5323824 | V16: =QUARTILE(V9:V11,1) -> 8.8035741 | W16: =QUARTILE(W9:W11,1) -> 7.6346522 | X16: =QUARTILE(X9:X11,1) -> 3.1742984 | Y16: =QUARTILE(Y9:Y11,1) -> 19.858705 | Z16: =QUARTILE(Z9:Z11,1) -> -15.572652 | AA16: =QUARTILE(AA9:AA11,1) -> 17.143457
B17: Low | S17: =MIN(S9:S11) -> 0.92875938 | T17: =MIN(T9:T11) -> 0.8625215 | U17: =MIN(U9:U11) -> 0.85424883 | V17: =MIN(V9:V11) -> 3.8771359 | W17: =MIN(W9:W11) -> 4.5316215 | X17: =MIN(X9:X11) -> 2.210516 | Y17: =MIN(Y9:Y11) -> 16.097973 | Z17: =MIN(Z9:Z11) -> -52.187365 | AA17: =MIN(AA9:AA11) -> 16.030278
B19: Relative Valuation
B20: Sales | C20: =I8 -> 849619
B21: EBITDA | C21: =L8 -> 119834
B22: Earnings | C22: =O8 -> -23936
B23: Valuation Multiples | C23: EV/Sales
B24: =C23 -> EV/Sales | C24: =IF(B24=AB6,S15,IF(B24=AB7,V15,Y15)) -> 2.4488131
B25: =IF(C23=AB8,"Equity Value","EnterpriceValue") -> EnterpriceValue | C25: =IF(C23=AB6,C24*C20,IF(C23=AB7,C24*C21,C24*C22)) -> 2080558.2
B26: ='DCF Valuation'!B41 -> Less: Debt | C26: =IF($C$23=$AB$8,0,'DCF Valuation'!C41) -> 777492
B27: ='DCF Valuation'!B42 -> Add: Cash | C27: =IF($C$23=$AB$8,0,'DCF Valuation'!C42) -> 239993
B28: ='DCF Valuation'!B43 -> Add: Non Operating Assets | C28: =IF($C$23=$AB$8,0,'DCF Valuation'!C43) -> 139094.34
B29: ='DCF Valuation'!B44 -> Equity Value | C29: =C25-C26+C27+C28 -> 1682153.5
B30: ='DCF Valuation'!B45 -> Less: Value of Options | C30: =IF($C$23=$AB$8,0,'DCF Valuation'!C45) -> -142.05277
B31: ='DCF Valuation'!B46 -> Equity Value for Shareholders | C31: =C29+C30 -> 1682011.5

Sheet Summary
B2: Valuation Summary
B4: Valuation Method | C4: Enterprise Value | D4: Equity Value Available for Shareholders | E4: Number of Equity Share | F4: Equity Value Per Share | G4: Current Market Price | H4: Discount/Premium | I4: Discount/Premium % | J4: Company Status
B6: DCF - Perpetuity Growth | C6: ='DCF Valuation'!C38 -> 2745571.6 | D6: ='DCF Valuation'!C46 -> 2347024.8 | E6: 386.6 | F6: =D6/E6 -> 6070.9385 | G6: 5087 | H6: =F6-G6 -> 983.93855 | I6: =H6/G6 -> 0.19342216 | J6: Undervalued
B7: DCF - Exit Multiple | C7: ='DCF Valuation'!C55 -> 2922126.1 | D7: ='DCF Valuation'!C63 -> 2523579.4 | E7: 386.6 | F7: =D7/E7 -> 6527.6238 | G7: 5087 | H7: =F7-G7 -> 1440.6238 | I7: =H7/G7 -> 0.28319713 | J7: Undervalued
B8: Relative Valuation - EV/Sales | C8: 2080558.2 | D8: 1682011.5 | E8: 386.6 | F8: =D8/E8 -> 4350.7798 | G8: 5087 | H8: =F8-G8 -> -736.2202 | I8: =H8/G8 -> -0.14472581 | J8: Overvalued
B9: Relative Valuation - EV/EBITDA | C9: 1645322.3 | D9: 1246775.6 | E9: 386.6 | F9: =D9/E9 -> 3224.9757 | G9: 5087 | H9: =F9-G9 -> -1862.0243 | I9: =H9/G9 -> -0.36603584 | J9: Overvalued
B10: Relative Valuation - P/E | C10: - | D10: 565354.87 | E10: 386.6 | F10: =D10/E10 -> 1462.3768 | G10: 5087 | H10: =F10-G10 -> -3624.6232 | I10: =H10/G10 -> -0.71252668 | J10: Overvalued

Sheet Growth-Margin Analysis
B2: Revenue Growth % | D2: 2020 | E2: =D2+1 -> 2021 | F2: =E2+1 -> 2022 | G2: =F2+1 -> 2023 | H2: =G2+1 -> 2024 | I2: =H2+1 -> 2025 | J2: =I2+1 -> 2026
B3: Wizz Air Holdings | D3: NA | E3: =('Comparable Companies'!E9-'Comparable Companies'!D9)/'Comparable Companies'!D9 -> -0.73237243 | F3: =('Comparable Companies'!F9-'Comparable Companies'!E9)/'Comparable Companies'!E9 -> 1.2508796 | G3: =('Comparable Companies'!G9-'Comparable Companies'!F9)/'Comparable Companies'!F9 -> 1.3420103 | H3: =('Comparable Companies'!H9-'Comparable Companies'!G9)/'Comparable Companies'!G9 -> 0.30223066 | I3: =('Comparable Companies'!I9-'Comparable Companies'!H9)/'Comparable Companies'!H9 -> 0.038339477 | J3: =('Comparable Companies'!J9-'Comparable Companies'!I9)/'Comparable Companies'!I9 -> 0.080454097
B4: Ryanair Holdings | D4: NA | E4: ='Comparable Companies'!E23/'Comparable Companies'!D23-1 -> -0.80743514 | F4: ='Comparable Companies'!F23/'Comparable Companies'!E23-1 -> 1.9348942 | G4: ='Comparable Companies'!G23/'Comparable Companies'!F23-1 -> 1.2444125 | H4: ='Comparable Companies'!H23/'Comparable Companies'!G23-1 -> 0.2476613 | I4: ='Comparable Companies'!I23/'Comparable Companies'!H23-1 -> 0.037541469 | J4: ='Comparable Companies'!J23/'Comparable Companies'!I23-1 -> 0.11440657
B5: Singapore Airlines | D5: NA | E5: ='Comparable Companies'!E37/'Comparable Companies'!D37-1 -> -0.76114648 | F5: ='Comparable Companies'!F37/'Comparable Companies'!E37-1 -> 0.99554496 | G5: ='Comparable Companies'!G37/'Comparable Companies'!F37-1 -> 1.3342438 | H5: ='Comparable Companies'!H37/'Comparable Companies'!G37-1 -> 0.06964354 | I5: ='Comparable Companies'!I37/'Comparable Companies'!H37-1 -> 0.027723574 | J5: ='Comparable Companies'!J37/'Comparable Companies'!I37-1 -> 0.050266635
B6: Mean | E6: =AVERAGE(E3:E5) -> -0.76698468 | F6: =AVERAGE(F3:F5) -> 1.3937729 | G6: =AVERAGE(G3:G5) -> 1.3068889 | H6: =AVERAGE(H3:H5) -> 0.20651183 | I6: =AVERAGE(I3:I5) -> 0.03453484 | J6: =AVERAGE(J3:J5) -> 0.0817091
B7: Median | E7: =MEDIAN(E3:E5) -> -0.76114648 | F7: =MEDIAN(F3:F5) -> 1.2508796 | G7: =MEDIAN(G3:G5) -> 1.3342438 | H7: =MEDIAN(H3:H5) -> 0.2476613 | I7: =MEDIAN(I3:I5) -> 0.037541469 | J7: =MEDIAN(J3:J5) -> 0.080454097
B9: EBITDA Margin % | D9: 2020 | E9: =D9+1 -> 2021 | F9: =E9+1 -> 2022 | G9: =F9+1 -> 2023 | H9: =G9+1 -> 2024 | I9: =H9+1 -> 2025 | J9: =I9+1 -> 2026 | L9: EBITDA Growth % | M9: 2020 | N9: =M9+1 -> 2021 | O9: =N9+1 -> 2022 | P9: =O9+1 -> 2023 | Q9: =P9+1 -> 2024 | R9: =Q9+1 -> 2025 | S9: =R9+1 -> 2026
B10: Wizz Air Holdings | D10: NA | E10: =('Comparable Companies'!D11/'Comparable Companies'!D9) -> 0.26063811 | F10: =('Comparable Companies'!E11/'Comparable Companies'!E9) -> -0.2473613 | G10: =('Comparable Companies'!F11/'Comparable Companies'!F9) -> -0.011422388 | H10: =('Comparable Companies'!G11/'Comparable Companies'!G9) -> 0.034473907 | I10: =('Comparable Companies'!H11/'Comparable Companies'!H9) -> 0.23520136 | J10: =('Comparable Companies'!I11/'Comparable Companies'!I9) -> 0.22103045 | L10: Wizz Air Holdings | M10: NA | N10: ='Comparable Companies'!E11/'Comparable Companies'!D11-1 -> -1.2539947 | O10: ='Comparable Companies'!F11/'Comparable Companies'!E11-1 -> -0.89606127 | P10: ='Comparable Companies'!G11/'Comparable Companies'!F11-1 -> -8.0684211 | Q10: ='Comparable Companies'!H11/'Comparable Companies'!G11-1 -> 7.8845867 | R10: ='Comparable Companies'!I11/'Comparable Companies'!H11-1 -> -0.024220583 | S10: NA
B11: Ryanair Holdings | D11: NA | E11: ='Comparable Companies'!D25/'Comparable Companies'!D23 -> 0.22085276 | F11: ='Comparable Companies'!E25/'Comparable Companies'!E23 -> -0.16407874 | G11: ='Comparable Companies'!F25/'Comparable Companies'!F23 -> 0.079110167 | H11: ='Comparable Companies'!G25/'Comparable Companies'!G23 -> 0.21955973 | I11: ='Comparable Companies'!H25/'Comparable Companies'!H23 -> 0.23209212 | J11: ='Comparable Companies'!I25/'Comparable Companies'!I23 -> 0.19875972 | L11: Ryanair Holdings | M11: NA | N11: ='Comparable Companies'!E25/'Comparable Companies'!D25-1 -> -1.1430627 | O11: ='Comparable Companies'!F25/'Comparable Companies'!E25-1 -> -2.4150522 | P11: ='Comparable Companies'!G25/'Comparable Companies'!F25-1 -> 5.2290679 | Q11: ='Comparable Companies'!H25/'Comparable Companies'!G25-1 -> 0.31887734 | R11: ='Comparable Companies'!I25/'Comparable Companies'!H25-1 -> -0.11146721 | S11: ='Comparable Companies'!J25/'Comparable Companies'!I25-1 -> 0.35175299
B12: Singapore Airlines | D12: NA | E12: ='Comparable Companies'!D39/'Comparable Companies'!D37 -> 0.14088721 | F12: ='Comparable Companies'!E39/'Comparable Companies'!E37 -> -0.097172358 | G12: ='Comparable Companies'!F39/'Comparable Companies'!F37 -> 0.18252613 | H12: ='Comparable Companies'!G39/'Comparable Companies'!G37 -> 0.26850372 | I12: ='Comparable Companies'!H39/'Comparable Companies'!H37 -> 0.258422 | J12: ='Comparable Companies'!I39/'Comparable Companies'!I37 -> 0.23852854 | L12: Singapore Airlines | M12: NA | N12: ='Comparable Companies'!E39/'Comparable Companies'!D39-1 -> -1.1647414 | O12: ='Comparable Companies'!F39/'Comparable Companies'!E39-1 -> -4.7483819 | P12: ='Comparable Companies'!G39/'Comparable Companies'!F39-1 -> 2.4337722 | Q12: ='Comparable Companies'!H39/'Comparable Companies'!G39-1 -> 0.029480786 | R12: ='Comparable Companies'!I39/'Comparable Companies'!H39-1 -> -0.051391122 | S12: ='Comparable Companies'!J39/'Comparable Companies'!I39-1 -> 0.21610024
B13: Mean | E13: =AVERAGE(E10:E12) -> 0.20745936 | F13: =AVERAGE(F10:F12) -> -0.16953747 | G13: =AVERAGE(G10:G12) -> 0.083404637 | H13: =AVERAGE(H10:H12) -> 0.17417912 | I13: =AVERAGE(I10:I12) -> 0.24190516 | J13: =AVERAGE(J10:J12) -> 0.21943957 | L13: Mean | N13: =AVERAGE(N10:N12) -> -1.1872663 | O13: =AVERAGE(O10:O12) -> -2.6864984 | P13: =AVERAGE(P10:P12) -> -0.13519364 | Q13: =AVERAGE(Q10:Q12) -> 2.744315 | R13: =AVERAGE(R10:R12) -> -0.06235964 | S13: =AVERAGE(S10:S12) -> 0.28392662
B14: Median | E14: =MEDIAN(E10:E12) -> 0.22085276 | F14: =MEDIAN(F10:F12) -> -0.16407874 | G14: =MEDIAN(G10:G12) -> 0.079110167 | H14: =MEDIAN(H10:H12) -> 0.21955973 | I14: =MEDIAN(I10:I12) -> 0.23520136 | J14: =MEDIAN(J10:J12) -> 0.22103045 | L14: Median | N14: =MEDIAN(N10:N12) -> -1.1647414 | O14: =MEDIAN(O10:O12) -> -2.4150522 | P14: =MEDIAN(P10:P12) -> 2.4337722 | Q14: =MEDIAN(Q10:Q12) -> 0.31887734 | R14: =MEDIAN(R10:R12) -> -0.051391122 | S14: =MEDIAN(S10:S12) -> 0.28392662
B16: EBIT Margin % | D16: 2020 | E16: =D16+1 -> 2021 | F16: =E16+1 -> 2022 | G16: =F16+1 -> 2023 | H16: =G16+1 -> 2024 | I16: =H16+1 -> 2025 | J16: =I16+1 -> 2026 | L16: EBIT Growth % | M16: 2020 | N16: =M16+1 -> 2021 | O16: =N16+1 -> 2022 | P16: =O16+1 -> 2023 | Q16: =P16+1 -> 2024 | R16: =Q16+1 -> 2025 | S16: =R16+1 -> 2026
B17: Wizz Air Holdings | D17: NA | E17: ='Comparable Companies'!E14/'Comparable Companies'!E9 -> -0.71461434 | F17: ='Comparable Companies'!F14/'Comparable Companies'!F9 -> -0.27972827 | G17: ='Comparable Companies'!G14/'Comparable Companies'!G9 -> -0.11982442 | H17: ='Comparable Companies'!H14/'Comparable Companies'!H9 -> 0.08631803 | I17: ='Comparable Companies'!I14/'Comparable Companies'!I9 -> 0.031798162 | J17: ='Comparable Companies'!J14/'Comparable Companies'!J9 -> 0.024545806 | L17: Wizz Air Holdings | M17: NA | N17: ='Comparable Companies'!E14/'Comparable Companies'!D14-1 -> -2.5610405 | O17: ='Comparable Companies'!F14/'Comparable Companies'!E14-1 -> -0.11891687 | P17: ='Comparable Companies'!G14/'Comparable Companies'!F14-1 -> 0.0032237266 | Q17: ='Comparable Companies'!H14/'Comparable Companies'!G14-1 -> -1.9380891 | R17: ='Comparable Companies'!I14/'Comparable Companies'!H14-1 -> -0.61749258 | S17: NA
B18: Ryanair Holdings | D18: NA | E18: ='Comparable Companies'!E28/'Comparable Companies'!E23 -> -0.51314342 | F18: ='Comparable Companies'!F28/'Comparable Companies'!F23 -> -0.070736737 | G18: ='Comparable Companies'!G28/'Comparable Companies'!G23 -> 0.13388151 | H18: ='Comparable Companies'!H28/'Comparable Companies'!H23 -> 0.15328255 | I18: ='Comparable Companies'!I28/'Comparable Companies'!I23 -> 0.1116966 | J18: ='Comparable Companies'!J28/'Comparable Companies'!J23 -> 0.15273766 | L18: Ryanair Holdings | M18: NA | N18: ='Comparable Companies'!E28/'Comparable Companies'!D28-1 -> -1.744545 | O18: ='Comparable Companies'!F28/'Comparable Companies'!E28-1 -> -0.5954253 | P18: ='Comparable Companies'!G28/'Comparable Companies'!F28-1 -> -5.2479388 | Q18: ='Comparable Companies'!H28/'Comparable Companies'!G28-1 -> 0.4284625 | R18: ='Comparable Companies'!I28/'Comparable Companies'!H28-1 -> -0.24394623 | S18: ='Comparable Companies'!J28/'Comparable Companies'!I28-1 -> 0.52387677
B19: Singapore Airlines | D19: NA | E19: ='Comparable Companies'!E42/'Comparable Companies'!E37 -> -0.6584292 | F19: ='Comparable Companies'!F42/'Comparable Companies'!F37 -> -0.080067763 | G19: ='Comparable Companies'!G42/'Comparable Companies'!G37 -> 0.15145599 | H19: ='Comparable Companies'!H42/'Comparable Companies'!H37 -> 0.14345674 | I19: ='Comparable Companies'!I42/'Comparable Companies'!I37 -> 0.08746763 | J19: ='Comparable Companies'!J42/'Comparable Companies'!J37 -> 0.11574408 | L19: Singapore Airlines | M19: NA | N19: NM | O19: ='Comparable Companies'!F42/'Comparable Companies'!E42-1 -> -0.75733333 | P19: NM | Q19: ='Comparable Companies'!H42/'Comparable Companies'!G42-1 -> 0.013149586 | R19: ='Comparable Companies'!I42/'Comparable Companies'!H42-1 -> -0.37338222 | S19: ='Comparable Companies'!J42/'Comparable Companies'!I42-1 -> 0.3897958
B20: Mean | E20: =AVERAGE(E17:E19) -> -0.62872899 | F20: =AVERAGE(F17:F19) -> -0.14351092 | G20: =AVERAGE(G17:G19) -> 0.055171026 | H20: =AVERAGE(H17:H19) -> 0.12768578 | I20: =AVERAGE(I17:I19) -> 0.076987464 | J20: =AVERAGE(J17:J19) -> 0.097675848 | L20: Mean | N20: =AVERAGE(N17:N19) -> -2.1527927 | O20: =AVERAGE(O17:O19) -> -0.4905585 | P20: =AVERAGE(P17:P19) -> -2.6223575 | Q20: =AVERAGE(Q17:Q19) -> -0.49882568 | R20: =AVERAGE(R17:R19) -> -0.41160701 | S20: =AVERAGE(S17:S19) -> 0.45683628
B21: Median | E21: =MEDIAN(E17:E19) -> -0.6584292 | F21: =MEDIAN(F17:F19) -> -0.080067763 | G21: =MEDIAN(G17:G19) -> 0.13388151 | H21: =MEDIAN(H17:H19) -> 0.14345674 | I21: =MEDIAN(I17:I19) -> 0.08746763 | J21: =MEDIAN(J17:J19) -> 0.11574408 | L21: Median | N21: =MEDIAN(N17:N19) -> -2.1527927 | O21: =MEDIAN(O17:O19) -> -0.5954253 | P21: =MEDIAN(P17:P19) -> -2.6223575 | Q21: =MEDIAN(Q17:Q19) -> 0.013149586 | R21: =MEDIAN(R17:R19) -> -0.37338222 | S21: =MEDIAN(S17:S19) -> 0.45683628
B23: EBT Margin % | D23: 2020 | E23: =D23+1 -> 2021 | F23: =E23+1 -> 2022 | G23: =F23+1 -> 2023 | H23: =G23+1 -> 2024 | I23: =H23+1 -> 2025 | J23: =I23+1 -> 2026 | L23: EBT Growth % | M23: 2020 | N23: =M23+1 -> 2021 | O23: =N23+1 -> 2022 | P23: =O23+1 -> 2023 | Q23: =P23+1 -> 2024 | R23: =Q23+1 -> 2025 | S23: =R23+1 -> 2026
B24: Wizz Air Holdings | D24: NA | E24: ='Comparable Companies'!E17/'Comparable Companies'!E9 -> -0.76657645 | F24: ='Comparable Companies'!F17/'Comparable Companies'!F9 -> -0.38565589 | G24: ='Comparable Companies'!G17/'Comparable Companies'!G9 -> -0.14495469 | H24: ='Comparable Companies'!H17/'Comparable Companies'!H9 -> 0.067236995 | I24: ='Comparable Companies'!I17/'Comparable Companies'!I9 -> 0.0037398436 | J24: ='Comparable Companies'!J17/'Comparable Companies'!J9 -> 0.0047439997 | L24: Wizz Air Holdings | M24: NA | N24: ='Comparable Companies'!E17/'Comparable Companies'!D17-1 -> -2.9262156 | O24: ='Comparable Companies'!F17/'Comparable Companies'!E17-1 -> 0.13239188 | P24: ='Comparable Companies'!G17/'Comparable Companies'!F17-1 -> -0.11971941 | Q24: ='Comparable Companies'!H17/'Comparable Companies'!G17-1 -> -1.6040375 | R24: ='Comparable Companies'!I17/'Comparable Companies'!H17-1 -> -0.94224568 | S24: NA
B25: Ryanair Holdings | D25: NA | E25: ='Comparable Companies'!E31/'Comparable Companies'!E23 -> -0.67777234 | F25: ='Comparable Companies'!F31/'Comparable Companies'!F23 -> -0.089524881 | G25: ='Comparable Companies'!G31/'Comparable Companies'!G23 -> 0.13387223 | H25: ='Comparable Companies'!H31/'Comparable Companies'!H23 -> 0.15828858 | I25: ='Comparable Companies'!I31/'Comparable Companies'!I23 -> 0.12792773 | J25: ='Comparable Companies'!J31/'Comparable Companies'!J23 -> 0.15589637 | L25: Ryanair Holdings | M25: NA | N25: ='Comparable Companies'!E31/'Comparable Companies'!D31-1 -> -2.6540355 | O25: ='Comparable Companies'!F31/'Comparable Companies'!E31-1 -> -0.61233878 | P25: ='Comparable Companies'!G31/'Comparable Companies'!F31-1 -> -4.3562122 | Q25: ='Comparable Companies'!H31/'Comparable Companies'!G31-1 -> 0.47521664 | R25: ='Comparable Companies'!I31/'Comparable Companies'!H31-1 -> -0.16146617 | S25: ='Comparable Companies'!J31/'Comparable Companies'!I31-1 -> 0.35804752
B26: Singapore Airlines | D26: NA | E26: ='Comparable Companies'!E45/'Comparable Companies'!E37 -> -1.2990906 | F26: ='Comparable Companies'!F45/'Comparable Companies'!F37 -> -0.1431423 | G26: ='Comparable Companies'!G45/'Comparable Companies'!G37 -> 0.14834485 | H26: ='Comparable Companies'!H45/'Comparable Companies'!H37 -> 0.15974059 | I26: ='Comparable Companies'!I45/'Comparable Companies'!I37 -> 0.15173134 | J26: ='Comparable Companies'!J45/'Comparable Companies'!J37 -> 0.078817854 | L26: Singapore Airlines | M26: NA | N26: NM | O26: ='Comparable Companies'!F45/'Comparable Companies'!E45-1 -> -0.78011781 | P26: ='Comparable Companies'!G45/'Comparable Companies'!F45-1 -> -3.4190826 | Q26: ='Comparable Companies'!H45/'Comparable Companies'!G45-1 -> 0.1518128 | R26: ='Comparable Companies'!I45/'Comparable Companies'!H45-1 -> -0.023805604 | S26: ='Comparable Companies'!J45/'Comparable Companies'!I45-1 -> -0.454432
B27: Mean | E27: =AVERAGE(E24:E26) -> -0.91447982 | F27: =AVERAGE(F24:F26) -> -0.20610769 | G27: =AVERAGE(G24:G26) -> 0.045754126 | H27: =AVERAGE(H24:H26) -> 0.12842206 | I27: =AVERAGE(I24:I26) -> 0.094466305 | J27: =AVERAGE(J24:J26) -> 0.079819409 | L27: Mean | N27: =AVERAGE(N24:N26) -> -2.7901255 | O27: =AVERAGE(O24:O26) -> -0.42002157 | P27: =AVERAGE(P24:P26) -> -2.6316714 | Q27: =AVERAGE(Q24:Q26) -> -0.32566937 | R27: =AVERAGE(R24:R26) -> -0.37583915 | S27: =AVERAGE(S24:S26) -> -0.04819224
B28: Median | E28: =MEDIAN(E24:E26) -> -0.76657645 | F28: =MEDIAN(F24:F26) -> -0.1431423 | G28: =MEDIAN(G24:G26) -> 0.13387223 | H28: =MEDIAN(H24:H26) -> 0.15828858 | I28: =MEDIAN(I24:I26) -> 0.12792773 | J28: =MEDIAN(J24:J26) -> 0.078817854 | L28: Median | N28: =MEDIAN(N24:N26) -> -2.7901255 | O28: =MEDIAN(O24:O26) -> -0.61233878 | P28: =MEDIAN(P24:P26) -> -3.4190826 | Q28: =MEDIAN(Q24:Q26) -> 0.1518128 | R28: =MEDIAN(R24:R26) -> -0.16146617 | S28: =MEDIAN(S24:S26) -> -0.04819224
B30: Net Income Margin % | D30: 2020 | E30: =D30+1 -> 2021 | F30: =E30+1 -> 2022 | G30: =F30+1 -> 2023 | H30: =G30+1 -> 2024 | I30: =H30+1 -> 2025 | J30: =I30+1 -> 2026 | L30: Net Income Growth % | M30: 2020 | N30: =M30+1 -> 2021 | O30: =N30+1 -> 2022 | P30: =O30+1 -> 2023 | Q30: =P30+1 -> 2024 | R30: =Q30+1 -> 2025 | S30: =R30+1 -> 2026
B31: Wizz Air Holdings | D31: NA | E31: ='Comparable Companies'!E20/'Comparable Companies'!E9 -> -0.77943166 | F31: ='Comparable Companies'!F20/'Comparable Companies'!F9 -> -0.38619695 | G31: ='Comparable Companies'!G20/'Comparable Companies'!G9 -> -0.13738224 | H31: ='Comparable Companies'!H20/'Comparable Companies'!H9 -> 0.071987542 | I31: ='Comparable Companies'!I20/'Comparable Companies'!I9 -> 0.040606728 | J31: ='Comparable Companies'!J20/'Comparable Companies'!J9 -> 0.0002284148 | L31: Wizz Air Holdings | M31: NA | N31: ='Comparable Companies'!E20/'Comparable Companies'!D20-1 -> -3.0498221 | O31: ='Comparable Companies'!F20/'Comparable Companies'!E20-1 -> 0.11527778 | P31: ='Comparable Companies'!G20/'Comparable Companies'!F20-1 -> -0.16687422 | Q31: ='Comparable Companies'!H20/'Comparable Companies'!G20-1 -> -1.6823617 | R31: ='Comparable Companies'!I20/'Comparable Companies'!H20-1 -> -0.41429354 | S31: NA
B32: Ryanair Holdings | D32: NA | E32: ='Comparable Companies'!E34/'Comparable Companies'!E23 -> -0.62055263 | F32: ='Comparable Companies'!F34/'Comparable Companies'!F23 -> -0.050157262 | G32: ='Comparable Companies'!G34/'Comparable Companies'!G23 -> 0.12192813 | H32: ='Comparable Companies'!H34/'Comparable Companies'!H23 -> 0.14260105 | I32: ='Comparable Companies'!I34/'Comparable Companies'!I23 -> 0.11553931 | J32: ='Comparable Companies'!J34/'Comparable Companies'!J23 -> 0.13983904 | L32: Ryanair Holdings | M32: NA | N32: ='Comparable Companies'!E34/'Comparable Companies'!D34-1 -> -2.564822 | O32: ='Comparable Companies'!F34/'Comparable Companies'!E34-1 -> -0.76278199 | P32: ='Comparable Companies'!G34/'Comparable Companies'!F34-1 -> -6.4559801 | Q32: ='Comparable Companies'!H34/'Comparable Companies'!G34-1 -> 0.45920231 | R32: ='Comparable Companies'!I34/'Comparable Companies'!H34-1 -> -0.15935528 | S32: ='Comparable Companies'!J34/'Comparable Companies'!I34-1 -> 0.34878382
B33: Singapore Airlines | D33: NA | E33: ='Comparable Companies'!E48/'Comparable Companies'!E37 -> -1.1225137 | F33: ='Comparable Companies'!F48/'Comparable Companies'!F37 -> -0.12450754 | G33: ='Comparable Companies'!G48/'Comparable Companies'!G37 -> 0.12170601 | H33: ='Comparable Companies'!H48/'Comparable Companies'!H37 -> 0.14175262 | I33: ='Comparable Companies'!I48/'Comparable Companies'!I37 -> 0.14392164 | J33: ='Comparable Companies'!J48/'Comparable Companies'!J37 -> 0.059594581 | L33: Singapore Airlines | M33: NA | N33: NM | O33: ='Comparable Companies'!F48/'Comparable Companies'!E48-1 -> -0.77865714 | P33: ='Comparable Companies'!G48/'Comparable Companies'!F48-1 -> -3.2817213 | Q33: ='Comparable Companies'!H48/'Comparable Companies'!G48-1 -> 0.24582813 | R33: ='Comparable Companies'!I48/'Comparable Companies'!H48-1 -> 0.043449223 | S33: ='Comparable Companies'!J48/'Comparable Companies'!I48-1 -> -0.56510917
B34: Mean | E34: =AVERAGE(E31:E33) -> -0.84083266 | F34: =AVERAGE(F31:F33) -> -0.18695392 | G34: =AVERAGE(G31:G33) -> 0.0354173 | H34: =AVERAGE(H31:H33) -> 0.1187804 | I34: =AVERAGE(I31:I33) -> 0.10002256 | J34: =AVERAGE(J31:J33) -> 0.066554012 | L34: Mean | N34: =AVERAGE(N31:N33) -> -2.807322 | O34: =AVERAGE(O31:O33) -> -0.47538712 | P34: =AVERAGE(P31:P33) -> -3.3015252 | Q34: =AVERAGE(Q31:Q33) -> -0.3257771 | R34: =AVERAGE(R31:R33) -> -0.1767332 | S34: =AVERAGE(S31:S33) -> -0.10816267
B35: Median | E35: =MEDIAN(E31:E33) -> -0.77943166 | F35: =MEDIAN(F31:F33) -> -0.12450754 | G35: =MEDIAN(G31:G33) -> 0.12170601 | H35: =MEDIAN(H31:H33) -> 0.14175262 | I35: =MEDIAN(I31:I33) -> 0.11553931 | J35: =MEDIAN(J31:J33) -> 0.059594581 | L35: Median | N35: =MEDIAN(N31:N33) -> -2.807322 | O35: =MEDIAN(O31:O33) -> -0.76278199 | P35: =MEDIAN(P31:P33) -> -3.2817213 | Q35: =MEDIAN(Q31:Q33) -> 0.24582813 | R35: =MEDIAN(R31:R33) -> -0.15935528 | S35: =MEDIAN(S31:S33) -> -0.10816267

Sheet Comparable Companies
B2: Comparable Companies | Q2: Revenue
B3: Wizz Air Holdings | Q3: EBITDA
B4: Ryanair Holdings
B5: Singapore Airlines
B7: $ (in millions, except per share data)
B8: Wizz Air Holdings | D8: 2020 | E8: =D8+1 -> 2021 | F8: =E8+1 -> 2022 | G8: =F8+1 -> 2023 | H8: =G8+1 -> 2024 | I8: =H8+1 -> 2025 | J8: =I8+1 -> 2026
B9: Revenue | D9: 3203.108 | E9: 857.24 | F9: 1929.544 | G9: 4519.012 | H9: 5884.796 | I9: =(5267.6)*1.16 -> 6110.416 | J9: 6602.024
B10: Operating Expenses | D10: -2368.256 | E10: -1069.288 | F10: -1951.584 | G10: -4363.224 | H10: -4500.684 | I10: -4759.828 | J10: -5072.796
B11: EBITDA | D11: =D9+D10 -> 834.852 | E11: =E9+E10 -> -212.048 | F11: =F9+F10 -> -22.04 | G11: =G9+G10 -> 155.788 | H11: =H9+H10 -> 1384.112 | I11: =I9+I10 -> 1350.588 | J11: =J9+J10 -> 1529.228
B13: Depreciation & Amortization | D13: -442.424 | E13: -400.548 | F13: -517.708 | G13: -697.276 | H13: -876.148 | I13: =(996.8*-1)*1.16 -> -1156.288 | J13: -1367.176
B14: EBIT | D14: =D11+D13 -> 392.428 | E14: =E11+E13 -> -612.596 | F14: =F11+F13 -> -539.748 | G14: =G11+G13 -> -541.488 | H14: =H11+H13 -> 507.964 | I14: =I11+I13 -> 194.3 | J14: =J11+J13 -> 162.052
B16: Non-Operating Expenses | D16: -51.272 | E16: -44.544 | F16: -204.392 | G16: -113.564 | H16: -112.288 | I16: -171.448 | J16: -130.732
B17: EBT | D17: =D14+D16 -> 341.156 | E17: =E14+E16 -> -657.14 | F17: =F14+F16 -> -744.14 | G17: =G14+G16 -> -655.052 | H17: =H14+H16 -> 395.676 | I17: =I14+I16 -> 22.852 | J17: =J14+J16 -> 31.32
B19: Tax | D19: -15.196 | E19: -11.02 | F19: -1.044 | G19: 34.22 | H19: 27.956 | I19: 225.272 | J19: -29.812
B20: Net Income | D20: =D17+D19 -> 325.96 | E20: =E17+E19 -> -668.16 | F20: =F17+F19 -> -745.184 | G20: =G17+G19 -> -620.832 | H20: =H17+H19 -> 423.632 | I20: =I17+I19 -> 248.124 | J20: =J17+J19 -> 1.508
B22: Ryanair Holdings | D22: 2020 | E22: =D22+1 -> 2021 | F22: =E22+1 -> 2022 | G22: =F22+1 -> 2023 | H22: =G22+1 -> 2024 | I22: =H22+1 -> 2025 | J22: =I22+1 -> 2026
B23: Revenue | D23: =(8494.8)*1.16 -> 9853.968 | E23: 1897.528 | F23: 5569.044 | G23: 12499.232 | H23: 15594.808 | I23: 16180.26 | J23: 18031.388
B24: Operating Expenses | D24: =(6618.7*-1)*1.16 -> -7677.692 | E24: =(1904.2*-1)*1.16 -> -2208.872 | F24: =(4421.1*-1)*1.16 -> -5128.476 | G24: =(8409.4*-1)*1.16 -> -9754.904 | H24: =(10323.6*-1)*1.16 -> -11975.376 | I24: =(11176.1*-1)*1.16 -> -12964.276 | J24: =(11796.7*-1)*1.16 -> -13684.172 | K24: 1.16
B25: EBITDA | D25: =D23+D24 -> 2176.276 | E25: =E23+E24 -> -311.344 | F25: =F23+F24 -> 440.568 | G25: =G23+G24 -> 2744.328 | H25: =H23+H24 -> 3619.432 | I25: =I23+I24 -> 3215.984 | J25: =J23+J24 -> 4347.216
B27: Depreciation & Amortization | D27: =(748.7*-1)*1.16 -> -868.492 | E27: =(571*-1)*1.16 -> -662.36 | F27: =(719.4*-1)*1.16 -> -834.504 | G27: =(923.2*-1)*1.16 -> -1070.912 | H27: =(1059.5*-1)*1.16 -> -1229.02 | I27: =(1214.4*-1)*1.16 -> -1408.704 | J27: =(1373.4*-1)*1.16 -> -1593.144
B28: EBIT | D28: =D25+D27 -> 1307.784 | E28: =E25+E27 -> -973.704 | F28: =F25+F27 -> -393.936 | G28: =G25+G27 -> 1673.416 | H28: =H25+H27 -> 2390.412 | I28: =I25+I27 -> 1807.28 | J28: =J25+J27 -> 2754.072
B30: Non-Operating Expenses | D30: =(457.1*-1)*1.16 -> -530.236 | E30: =(269.3*-1)*1.16 -> -312.388 | F30: =(90.2*-1)*1.16 -> -104.632 | G30: =(0.1*-1)*1.16 -> -0.116 | H30: 78.068 | I30: 262.624 | J30: 56.956
B31: EBT | D31: =D28+D30 -> 777.548 | E31: =E28+E30 -> -1286.092 | F31: =F28+F30 -> -498.568 | G31: =G28+G30 -> 1673.3 | H31: =H28+H30 -> 2468.48 | I31: =I28+I30 -> 2069.904 | J31: =J28+J30 -> 2811.028
B33: Tax | D33: =(21.6*-1)*1.16 -> -25.056 | E33: =(93.6)*1.16 -> 108.576 | F33: =(189)*1.16 -> 219.24 | G33: =(128.7*-1)*1.16 -> -149.292 | H33: =(210.9*-1)*1.16 -> -244.644 | I33: =(172.8*-1)*1.16 -> -200.448 | J33: =(249.6*-1)*1.16 -> -289.536
B34: Net Income | D34: =D31+D33 -> 752.492 | E34: =E31+E33 -> -1177.516 | F34: =F31+F33 -> -279.328 | G34: =G31+G33 -> 1524.008 | H34: =H31+H33 -> 2223.836 | I34: =I31+I33 -> 1869.456 | J34: =J31+J33 -> 2521.492
B36: Singapore Airlines | D36: 2020 | E36: =D36+1 -> 2021 | F36: =E36+1 -> 2022 | G36: =F36+1 -> 2023 | H36: =G36+1 -> 2024 | I36: =H36+1 -> 2025 | J36: =I36+1 -> 2026
B37: Revenue | D37: 15975.9 | E37: 3815.9 | F37: 7614.8 | G37: 17774.8 | H37: 19012.7 | I37: 19539.8 | J37: 20522
B38: Operating Expenses | D38: =13725.1*-1 -> -13725.1 | E38: =4186.7*-1 -> -4186.7 | F38: =6224.9*-1 -> -6224.9 | G38: =13002.2*-1 -> -13002.2 | H38: =14099.4*-1 -> -14099.4 | I38: =14879*-1 -> -14879 | J38: =14854*-1 -> -14854
B39: EBITDA | D39: =D37+D38 -> 2250.8 | E39: =E37+E38 -> -370.8 | F39: =F37+F38 -> 1389.9 | G39: =G37+G38 -> 4772.6 | H39: =H37+H38 -> 4913.3 | I39: =I37+I38 -> 4660.8 | J39: =J37+J38 -> 5668
B41: Depreciation & Amortization | D41: =2191.7*-1 -> -2191.7 | E41: =2141.7*-1 -> -2141.7 | F41: =1999.6*-1 -> -1999.6 | G41: =2080.5*-1 -> -2080.5 | H41: =2185.8*-1 -> -2185.8 | I41: =2951.7*-1 -> -2951.7 | J41: =3292.7*-1 -> -3292.7
B42: EBIT | D42: =D39+D41 -> 59.1 | E42: =E39+E41 -> -2512.5 | F42: =F39+F41 -> -609.7 | G42: =G39+G41 -> 2692.1 | H42: =H39+H41 -> 2727.5 | I42: =I39+I41 -> 1709.1 | J42: =J39+J41 -> 2375.3
B44: Non-Operating Expenses | D44: =279.3*-1 -> -279.3 | E44: =2444.7*-1 -> -2444.7 | F44: =480.3*-1 -> -480.3 | G44: =55.3*-1 -> -55.3 | H44: 309.6 | I44: =1255.7 -> 1255.7 | J44: =757.8*-1 -> -757.8
B45: EBT | D45: =D42+D44 -> -220.2 | E45: =E42+E44 -> -4957.2 | F45: =F42+F44 -> -1090 | G45: =G42+G44 -> 2636.8 | H45: =H42+H44 -> 3037.1 | I45: =I42+I44 -> 2964.8 | J45: =J42+J44 -> 1617.5
B47: Tax | D47: 50.8 | E47: 673.8 | F47: 141.9 | G47: =473.5*-1 -> -473.5 | H47: =342*-1 -> -342 | I47: =152.6*-1 -> -152.6 | J47: =394.5*-1 -> -394.5
B48: Net Income | D48: =D45+D47 -> -169.4 | E48: =E45+E47 -> -4283.4 | F48: =F45+F47 -> -948.1 | G48: =G45+G47 -> 2163.3 | H48: =H45+H47 -> 2695.1 | I48: =I45+I47 -> 2812.2 | J48: =J45+J47 -> 1223

Sheet Company Description
B2: Comparable Companies Descrption
B4: Company | C4: Ticker | D4: Description
B5: Wizz Air Holdings | C5: WIZZ | D5: Wizz Air Holdings Plc is a European ultra-low-cost airline group headquartered in Budapest, Hungary. The company operates an extensive network across Europe and other international markets, with a strong presence in Central and Eastern Europe. Wizz Air focuses on providing affordable air travel through a low-cost operating model, supported by a young Airbus fleet and a high-density route network. The airline serves numerous destinations across Europe, the Middle East and North Africa, operating from a combination of primary, secondary and regional airports. Wizz Air is focused on maintaining a low-cost base while expanding its network and passenger capacity. The company is listed on the London Stock Exchange under the ticker WIZZ.
B6: Ryanair Holdings | C6: RYAAY | D6: Ryanair Holdings Plc is a European airline group and the parent company of Ryanair, Buzz, Lauda, Malta Air and Ryanair UK. The Group operates primarily under a low-cost airline model and has an extensive network connecting airports across Europe and other international markets. Ryanair focuses on offering low fares while maintaining high aircraft utilisation, strong load factors and a cost-efficient operating structure. The Group operates approximately 3,800 daily flights from around 95 bases, connecting more than 220 airports across 35 countries. Its fleet is predominantly based on Boeing 737 aircraft, supporting its low-cost and high-frequency operating model.
B7: Singapore Airlines | C7: C6L | D7: Singapore Airlines Limited is the flag carrier of Singapore and operates a global passenger and cargo air transportation business. The Group provides passenger and cargo air transportation services, supported by complementary businesses including aircraft engineering, pilot training, air charter services, tour activities and loyalty-related services. Singapore Airlines operates an extensive international network connecting Singapore with major destinations across Asia, Europe, the Americas and other regions. The Group follows a full-service airline model, offering premium and economy cabin products across its network. Singapore Airlines is listed on the Singapore Exchange under the ticker C6L and is a subsidiary of Temasek Holdings.

Sheet Income Statement
B2: ='Control Sheet'!B2 -> InterGlobe Aviation
B3: Income Statement
B4: In INR Crores unless stated otherwise
B6: InterGlobe Aviation
B7: Income Statement
B8: In INR Crores unless stated otherwise
B10: Particulars | D10: 2015 | E10: =D10+1 -> 2016 | F10: =E10+1 -> 2017 | G10: =F10+1 -> 2018 | H10: =G10+1 -> 2019 | I10: =H10+1 -> 2020 | J10: =I10+1 -> 2021 | K10: =J10+1 -> 2022 | L10: =K10+1 -> 2023 | ... O10: =N10+1 -> 2026
B12: Revenue from operations | D12: 139253.36 | E12: 161399.09 | F12: 185805 | G12: 230208.87 | H12: 284967.72 | I12: 357560.01 | J12: 146406.31 | K12: 259309.27 | L12: 544464.53 | M12: 689043 | N12: 808029 | O12: 849619
B13: Total Income | D13: =D12 -> 139253.36 | E13: =E12 -> 161399.09 | F13: =F12 -> 185805 | G13: =G12 -> 230208.87 | H13: =H12 -> 284967.72 | I13: =I12 -> 357560.01 | J13: =J12 -> 146406.31 | K13: =K12 -> 259309.27 | ... O13: =O12 -> 849619
B15: Sales Growth % | D15: =IFERROR(D12/C12-1,"NM") -> NM | E15: =IFERROR(E12/D12-1,"NM") -> 0.15903193 | F15: =IFERROR(F12/E12-1,"NM") -> 0.15121467 | G15: =IFERROR(G12/F12-1,"NM") -> 0.23898103 | H15: =IFERROR(H12/G12-1,"NM") -> 0.23786594 | I15: =IFERROR(I12/H12-1,"NM") -> 0.25473864 | J15: =IFERROR(J12/I12-1,"NM") -> -0.59054059 | K15: =IFERROR(K12/J12-1,"NM") -> 0.77116184 | ... O15: =IFERROR(O12/N12-1,"NM") -> 0.051470925
B17: COGS (Cost of Goods Sold)
B18: Aircraft fuel expenses | D18: 57484.86 | E18: 47793.24 | F18: 63415.13 | G18: 77601.36 | H18: 119427.93 | I18: 124537.94 | J18: 38312.77 | K18: 96952.36 | L18: 236460.17 | M18: 239046 | N18: 261973 | O18: 253892
B19: Aircraft and engine rentals | D19: 19522.38 | E19: 26121.52 | F19: 31253.73 | G19: 36101.99 | H19: 49994.49 | I19: 4966.57 | J19: 2804.57 | K19: 3116.84 | L19: 3258.4 | M19: 10752 | N19: 30103 | O19: 20847
B20: Supplementary rentals and aircraft repair and maintenance (net) | D20: 0 | E20: 0 | F20: 0 | G20: 0 | H20: 0 | I20: 58672.37 | J20: 41912.6 | K20: 60897.84 | L20: 80449.6 | M20: 99316 | N20: 112185 | O20: 129121
B21: Airport fees and charges | I21: 29116.84 | J21: 16128.84 | K21: 22868.37 | L21: 36468 | M21: 46239 | N21: 57531 | O21: 65482
B22: Purchase of stock-in-trade (In-flight) | D22: 817.1 | E22: 1147.82 | F22: 1238.32 | G22: 1238.76 | H22: 1397.95 | I22: 1809.08 | J22: 543.21 | K22: 1181.42 | L22: 2872.44 | M22: 3369 | N22: 3834 | O22: 4963
B23: Foreign exchange loss (net) | D23: 0 | E23: 0 | F23: 0 | G23: 516.17 | H23: 4674.87 | I23: 15461.89 | J23: -5230.26 | K23: 9408.38 | L23: 29597.73 | M23: 7174 | N23: 16179 | O23: 89757
B24: Changes in inventories of stock-in-trade | D24: -31.72 | E24: -11.32 | F24: -2.94 | G24: 12.65 | H24: -6.55 | I24: -30.53 | J24: 11.61 | K24: -16.77 | L24: -12.44 | M24: 54 | N24: -2 | O24: -14
B25: Total COGS | D25: =SUM(D18:D24) -> 77792.62 | E25: =SUM(E18:E24) -> 75051.26 | F25: =SUM(F18:F24) -> 95904.24 | G25: =SUM(G18:G24) -> 115470.93 | H25: =SUM(H18:H24) -> 175488.69 | I25: =SUM(I18:I24) -> 234534.16 | J25: =SUM(J18:J24) -> 94483.34 | K25: =SUM(K18:K24) -> 194408.44 | ... O25: =SUM(O18:O24) -> 564048
J26: =J25/J12 -> 0.64535019 | K26: =K25/K12 -> 0.74971651 | L26: =L25/L12 -> 0.7146359 | M26: =M25/M12 -> 0.58915046 | N26: =N25/N12 -> 0.59626944 | O26: =O25/O12 -> 0.66388346
B27: COGS % Sales | D27: =D25/D12 -> 0.55864088 | E27: =E25/E12 -> 0.46500423 | F27: =F25/F12 -> 0.51615532 | G27: =G25/G12 -> 0.50159201 | H27: =H25/H12 -> 0.61581954 | I27: =I25/I12 -> 0.6559295 | J27: =J25/J12 -> 0.64535019 | K27: =K25/K12 -> 0.74971651 | ... O27: =O25/O12 -> 0.66388346
B28: Stock-in-trade % Sales | D28: =D22/D12 -> 0.005867722 | E28: =E22/E12 -> 0.0071116882 | F28: =F22/F12 -> 0.0066646215 | G28: =G22/G12 -> 0.0053810264 | H28: =H22/H12 -> 0.0049056433 | I28: =I22/I12 -> 0.0050595143 | J28: =J22/J12 -> 0.0037102909 | K28: =K22/K12 -> 0.0045560269 | ... O28: =O22/O12 -> 0.0058414419
B29: Change in inventory % Sales | D29: =D24/D12 -> -0.00022778625 | E29: =E24/E12 -> -7.0136703e-05 | F29: =F24/F12 -> -1.582304e-05 | G29: =G24/G12 -> 5.4950098e-05 | H29: =H24/H12 -> -2.298506e-05 | I29: =I24/I12 -> -8.5384269e-05 | J29: =J24/J12 -> 7.9299861e-05 | K29: =K24/K12 -> -6.4671811e-05 | ... O29: =O24/O12 -> -1.6477974e-05
B31: Gross Profit | D31: =D13-D25 -> 61460.74 | E31: =E13-E25 -> 86347.83 | F31: =F13-F25 -> 89900.76 | G31: =G13-G25 -> 114737.94 | H31: =H13-H25 -> 109479.03 | I31: =I13-I25 -> 123025.85 | J31: =J13-J25 -> 51922.97 | K31: =K13-K25 -> 64900.83 | ... O31: =O13-O25 -> 285571
B33: Gross Margin % Sales | D33: =D31/D12 -> 0.44135912 | E33: =E31/E12 -> 0.53499577 | F33: =F31/F12 -> 0.48384468 | G33: =G31/G12 -> 0.49840799 | H33: =H31/H12 -> 0.38418046 | I33: =I31/I12 -> 0.3440705 | J33: =J31/J12 -> 0.35464981 | K33: =K31/K12 -> 0.25028349 | ... O33: =O31/O12 -> 0.33611654
B35: SG&A (Selling, General & Aministrative)
B36: Employee benefits expense | D36: 11886.91 | E36: 17899.23 | F36: 20481.9 | G36: 24550.22 | H36: 32105.57 | I36: 47099.59 | J36: 32954.92 | K36: 34864.43 | L36: 47947.52 | M36: 64618 | N36: 74725 | O36: 82722
B37: Other expenses | D37: 30876.97 | E37: 38393.71 | F37: 47986.24 | G37: 60623.09 | H37: 79407.79 | I37: 35340.04 | J37: 19104.1 | K37: 24563.07 | L37: 42469.61 | M37: 55300 | N37: 70918 | O37: 83015
B39: EBE % Sales | D39: =D36/D12 -> 0.085361746 | E39: =E36/E12 -> 0.11090044 | F39: =F36/F12 -> 0.11023331 | G39: =G36/G12 -> 0.10664324 | H39: =H36/H12 -> 0.11266388 | I39: =I36/I12 -> 0.13172499 | J39: =J36/J12 -> 0.22509221 | K39: =K36/K12 -> 0.13445115 | ... O39: =O36/O12 -> 0.097363642
B40: OE % Sales | D40: =D37/D12 -> 0.22173232 | E40: =E37/E12 -> 0.23788059 | F40: =F37/F12 -> 0.2582613 | G40: =G37/G12 -> 0.26333951 | H40: =H37/H12 -> 0.27865539 | I40: =I37/I12 -> 0.098836668 | J40: =J37/J12 -> 0.13048686 | K40: =K37/K12 -> 0.094724998 | ... O40: =O37/O12 -> 0.097708502
B42: Total SG&A | D42: =SUM(D36:D37) -> 42763.88 | E42: =SUM(E36:E37) -> 56292.94 | F42: =SUM(F36:F37) -> 68468.14 | G42: =SUM(G36:G37) -> 85173.31 | H42: =SUM(H36:H37) -> 111513.36 | I42: =SUM(I36:I37) -> 82439.63 | J42: =SUM(J36:J37) -> 52059.02 | K42: =SUM(K36:K37) -> 59427.5 | ... O42: =SUM(O36:O37) -> 165737
B43: EBITDA | D43: =D31-D42 -> 18696.86 | E43: =E31-E42 -> 30054.89 | F43: =F31-F42 -> 21432.62 | G43: =G31-G42 -> 29564.63 | H43: =H31-H42 -> -2034.33 | I43: =I31-I42 -> 40586.22 | J43: =J31-J42 -> -136.05 | K43: =K31-K42 -> 5473.33 | ... O43: =O31-O42 -> 119834
B45: EBITDA Margin | D45: =D43/D12 -> 0.13426505 | E45: =E43/E12 -> 0.18621474 | F45: =F43/F12 -> 0.11535007 | G45: =G43/G12 -> 0.12842524 | H45: =H43/H12 -> -0.0071388086 | I45: =I43/I12 -> 0.11350883 | J45: =J43/J12 -> -0.00092926323 | K45: =K43/K12 -> 0.021107344 | ... O45: =O43/O12 -> 0.1410444
B47: Less: Depreciation and amortisation expense
B48: Depreciation and amortisation expense | D48: 3022.14 | E48: 5030.79 | F48: 4572.53 | G48: 4368.77 | H48: 7595.8 | I48: 39739.29 | J48: 46994.46 | K48: 50686 | L48: 51029.69 | M48: 64257 | N48: 86802 | O48: 108082
B49: EBIT | D49: =D43-D48 -> 15674.72 | E49: =E43-E48 -> 25024.1 | F49: =F43-F48 -> 16860.09 | G49: =G43-G48 -> 25195.86 | H49: =H43-H48 -> -9630.13 | I49: =I43-I48 -> 846.93 | J49: =J43-J48 -> -47130.51 | K49: =K43-K48 -> -45212.67 | ... O49: =O43-O48 -> 11752
B51: Other income | D51: 3945.83 | E51: 4613.93 | F51: 7890.7 | G51: 9468.56 | H51: 13245.98 | I51: 15355.09 | J51: 10369.64 | K51: 7255.98 | L51: 14349.65 | M51: 23269 | N51: 32953 | O51: 45515
B52: Exceptional Itmes | O52: =17964*-1 -> -17964
B53: Finance costs | D53: =1155.32*-1 -> -1155.32 | E53: =1348.53*-1 -> -1348.53 | F53: =3307.8*-1 -> -3307.8 | G53: =3398.15*-1 -> -3398.15 | H53: =5089.63*-1 -> -5089.63 | I53: =18758.71*-1 -> -18758.71 | J53: =21419.83*-1 -> -21419.83 | K53: =23580.15*-1 -> -23580.15 | L53: =31317.31*-1 -> -31317.31 | M53: =41693.54*-1 -> -41693.54 | N53: =50800*-1 -> -50800 | O53: =58908*-1 -> -58908 | P53: =O51+O52+O53 -> -31357
B54: PBT (Profit Before Tax) | D54: =D49+D51+D53 -> 18465.23 | E54: =E49+E51+E53 -> 28289.5 | F54: =F49+F51+F53 -> 21442.99 | G54: =G49+G51+G53 -> 31266.27 | H54: =H49+H51+H53 -> -1473.78 | I54: =I49+I51+I53 -> -2556.69 | J54: =J49+J51+J53 -> -58180.7 | K54: =K49+K51+K53 -> -61536.84 | ... N54: =N49+N51+N53 -> 75934 | O54: =O49+O51+O53+O52 -> -19605
B56: Tax expense
B57: Current tax | D57: 1874.92 | E57: 7303.93 | F57: 4911.51 | G57: 6689.82 | H57: 15.24 | I57: 91.3 | J57: -78.68 | K57: 4.12 | L57: 14.04 | M57: 10 | N57: 3346 | O57: 139
B58: Deferred tax charge / (credit) | D58: 3548.59 | E58: 1088.37 | F58: -59.99 | G58: 2153.21 | H58: -3061.49 | I58: -311.21 | J58: -37.75 | K58: 77.49 | L58: 0 | M58: -1242 | N58: 4 | O58: 4192
B59: Total tax expense / (credit) | D59: =D57+D58 -> 5423.51 | E59: =E57+E58 -> 8392.3 | F59: =F57+F58 -> 4851.52 | G59: =G57+G58 -> 8843.03 | H59: =H57+H58 -> -3046.25 | I59: =I57+I58 -> -219.91 | J59: =J57+J58 -> -116.43 | K59: =K57+K58 -> 81.61 | ... O59: =O57+O58 -> 4331
B61: Net Income | D61: =D54-D59 -> 13041.72 | E61: =E54-E59 -> 19897.2 | F61: =F54-F59 -> 16591.47 | G61: =G54-G59 -> 22423.24 | H61: =H54-H59 -> 1572.47 | I61: =I54-I59 -> -2336.78 | J61: =J54-J59 -> -58064.27 | K61: =K54-K59 -> -61618.45 | ... O61: =O54-O59 -> -23936
B63: Sales Growth % | D63: =IFERROR(D12/C12-1,"NM") -> NM | E63: =IFERROR(E12/D12-1,"NM") -> 0.15903193 | F63: =IFERROR(F12/E12-1,"NM") -> 0.15121467 | G63: =IFERROR(G12/F12-1,"NM") -> 0.23898103 | H63: =IFERROR(H12/G12-1,"NM") -> 0.23786594 | I63: =IFERROR(I12/H12-1,"NM") -> 0.25473864 | J63: =IFERROR(J12/I12-1,"NM") -> -0.59054059 | K63: =IFERROR(K12/J12-1,"NM") -> 0.77116184 | ... O63: =IFERROR(O12/N12-1,"NM") -> 0.051470925
B64: Gross Profit Margin % | D64: =IFERROR(D31/D12,"NM") -> 0.44135912 | E64: =IFERROR(E31/E12,"NM") -> 0.53499577 | F64: =IFERROR(F31/F12,"NM") -> 0.48384468 | G64: =IFERROR(G31/G12,"NM") -> 0.49840799 | H64: =IFERROR(H31/H12,"NM") -> 0.38418046 | I64: =IFERROR(I31/I12,"NM") -> 0.3440705 | J64: =IFERROR(J31/J12,"NM") -> 0.35464981 | K64: =IFERROR(K31/K12,"NM") -> 0.25028349 | ... O64: =IFERROR(O31/O12,"NM") -> 0.33611654
B65: EBITDA Margin % | D65: =IFERROR(D43/D12,"NM") -> 0.13426505 | E65: =IFERROR(E43/E12,"NM") -> 0.18621474 | F65: =IFERROR(F43/F12,"NM") -> 0.11535007 | G65: =IFERROR(G43/G12,"NM") -> 0.12842524 | H65: =IFERROR(H43/H12,"NM") -> -0.0071388086 | I65: =IFERROR(I43/I12,"NM") -> 0.11350883 | J65: =IFERROR(J43/J12,"NM") -> -0.00092926323 | K65: =IFERROR(K43/K12,"NM") -> 0.021107344 | ... O65: =IFERROR(O43/O12,"NM") -> 0.1410444
B66: EBIT Margin % | D66: =IFERROR(D49/D12,"NM") -> 0.1125626 | E66: =IFERROR(E49/E12,"NM") -> 0.15504486 | F66: =IFERROR(F49/F12,"NM") -> 0.090740777 | G66: =IFERROR(G49/G12,"NM") -> 0.10944782 | H66: =IFERROR(H49/H12,"NM") -> -0.033793757 | I66: =IFERROR(I49/I12,"NM") -> 0.0023686374 | J66: =IFERROR(J49/J12,"NM") -> -0.32191584 | K66: =IFERROR(K49/K12,"NM") -> -0.17435809 | ... O66: =IFERROR(O49/O12,"NM") -> 0.013832082
B67: Actual Tax Rate % | D67: =IFERROR(D59/D54,"NM") -> 0.29371473 | E67: =IFERROR(E59/E54,"NM") -> 0.29665777 | F67: =IFERROR(F59/F54,"NM") -> 0.22625203 | G67: =IFERROR(G59/G54,"NM") -> 0.28282971 | H67: =IFERROR(H59/H54,"NM") -> 2.0669639 | I67: =IFERROR(I59/I54,"NM") -> 0.086013557 | J67: =IFERROR(J59/J54,"NM") -> 0.0020011791 | K67: =IFERROR(K59/K54,"NM") -> -0.0013261974 | ... O67: =IFERROR(O59/O54,"NM") -> -0.22091303
B68: Net Income Margin % | D68: =IFERROR(D61/D12,"NM") -> 0.093654616 | E68: =IFERROR(E61/E12,"NM") -> 0.12327951 | F68: =IFERROR(F61/F12,"NM") -> 0.089295067 | G68: =IFERROR(G61/G12,"NM") -> 0.097403892 | H68: =IFERROR(H61/H12,"NM") -> 0.0055180636 | I68: =IFERROR(I61/I12,"NM") -> -0.0065353505 | J68: =IFERROR(J61/J12,"NM") -> -0.39659677 | K68: =IFERROR(K61/K12,"NM") -> -0.23762533 | ... O68: =IFERROR(O61/O12,"NM") -> -0.028172628

Sheet Balance Sheet
B2: ='Control Sheet'!B2 -> InterGlobe Aviation
B3: Balance Sheet
B4: In INR Crores unless stated otherwise
B6: Particulars | D6: 2015 | E6: =D6+1 -> 2016 | F6: =E6+1 -> 2017 | G6: =F6+1 -> 2018 | H6: =G6+1 -> 2019 | I6: =H6+1 -> 2020 | J6: =I6+1 -> 2021 | K6: =J6+1 -> 2022 | L6: =K6+1 -> 2023 | ... O6: =N6+1 -> 2026
B8: Non-current assets
B9: Property, plant and equipment | D9: 48664.02 | E9: 46755.15 | F9: 37474.72 | G9: 45347.56 | H9: 56315.54 | I9: 24995.69 | J9: 7969.66 | K9: 8239.53 | L9: 11111.69 | M9: 19029 | N9: 26779 | O9: 110871
B10: Right of use assets | D10: 0 | E10: 0 | F10: 0 | G10: 0 | H10: 0 | I10: 142461.38 | J10: 179861.71 | K10: 204381.48 | L10: 265364.95 | M10: 342023 | N10: 490739 | O10: 520540
B11: Capital work-in-progress | D11: 4.53 | E11: 237.34 | F11: 233.03 | G11: 294.2 | H11: 220.15 | I11: 1292.7 | J11: 663.51 | K11: 1193.18 | L11: 0 | M11: 1 | N11: 7 | O11: 387
B12: Intangible assets | D12: 96.37 | E12: 199.74 | F12: 463.69 | G12: 440.53 | H12: 304.88 | I12: 335.91 | J12: 334.96 | K12: 215.62 | L12: 107.27 | M12: 483 | N12: 299 | O12: 160
B13: Intangible assets under development | E13: 82.31 | F13: 18.83 | G13: 30.7 | H13: 16.14 | I13: 109.69 | J13: 54.19 | K13: 60.39 | L13: 208.17 | M13: 13 | N13: 23 | O13: 206
B14: Financial assets
B15: Investments | D15: 0.46 | E15: 0.25 | F15: 0.18 | G15: 0.17 | H15: 0.15 | I15: 0.75 | J15: 0.83 | K15: 0.12 | L15: 0.68 | M15: 9748 | N15: 13183 | O15: 19310
B16: Loans | D16: 11181.34 | E16: 11930.62 | F16: 5440.26 | G16: 6831.34 | H16: 5843.97 | I16: 12759.54 | J16: 15806.57 | K16: 0 | L16: 0 | M16: 0 | N16: 0
B17: Other financial assets | D17: 0 | E17: 0 | F17: 10356.39 | G17: 8195.22 | H17: 1988.21 | I17: 58.3 | J17: 16.34 | K17: 20911.22 | L17: 24499.66 | M17: 52963 | N17: 74933 | O17: 71107
B19: Deferred tax assets (net) | D19: 0 | E19: 0 | F19: 0 | G19: 0 | H19: 9.67 | I19: 2992.82 | J19: 3026.93 | K19: 2949.44 | L19: 2949.44 | M19: 4192 | N19: 4192 | O19: 0
B20: Income tax assets (net) | D20: 0 | E20: 0 | F20: 97.6 | G20: 386.39 | H20: 1240.49 | I20: 4296.71 | J20: 5139.53 | K20: 7119.22 | L20: 10997.87 | M20: 16101 | N20: 17080 | O20: 19775
B21: Other non-current assets | D21: 16055.6 | E21: 14977.84 | F21: 3548.74 | G21: 3451.22 | H21: 3158.76 | I21: 7142.69 | J21: 9498.13 | K21: 12266.99 | L21: 14971.32 | M21: 19161 | N21: 24169 | O21: 38373
B22: Total non-current assets | D22: =SUM(D9:D10,D11:D13,D15:D21) -> 76002.32 | E22: =SUM(E9:E10,E11:E13,E15:E21) -> 74183.25 | F22: =SUM(F9:F10,F11:F13,F15:F21) -> 57633.44 | G22: =SUM(G9:G10,G11:G13,G15:G21) -> 64977.33 | H22: =SUM(H9:H10,H11:H13,H15:H21) -> 69097.96 | I22: =SUM(I9:I10,I11:I13,I15:I21) -> 196446.18 | J22: =SUM(J9:J10,J11:J13,J15:J21) -> 222372.36 | K22: =SUM(K9:K10,K11:K13,K15:K21) -> 257337.19 | ... O22: =SUM(O9:O10,O11:O13,O15:O21) -> 780729
